Workbook

Sheet Config
B3: Dev | C3: https://script.google.com/a/macros/guidewire.com/s/AKfycbyjf46mo1ApBnirDnxmh_9igX15IHnJkS__iaEEncYpK9r_3c0v7RGj9OIw6-AXWw6U/exec
A4: Call Temp Viewer | B4: Prod | C4: https://script.google.com/a/macros/guidewire.com/s/AKfycbws76mywSxgOcVNWcYZ5SsPXMLQG3JCIR9mYIbzxOPMkDguQtOVaHxWuBa3EmfxZlkF/exec
C8: Prod | D8: Tim Kennedy | E8: marketingmanager
D9: =if(C8="Prod",C4,C3) -> https://script.google.com/a/macros/guidewire.com/s/AKfycbws76mywSxgOcVNWcYZ5SsPXMLQG3JCIR9mYIbzxOPMkDguQtOVaHxWuBa3EmfxZlkF/exec
D10: =IF(D8="","","&manager="&SUBSTITUTE(D8," ","%20")) -> &manager=Tim%20Kennedy
D11: =CONCAT("?page=",E8) -> ?page=marketingmanager
C13: link w/page | D13: =concat(D9,+D11) -> https://script.google.com/a/macros/guidewire.com/s/AKfycbws76mywSxgOcVNWcYZ5SsPXMLQG3JCIR9mYIbzxOPMkDguQtOVaHxWuBa3EmfxZlkF/exec?page=marketingmanager
C14: both | D14: =concat(D13,D10) -> https://script.google.com/a/macros/guidewire.com/s/AKfycbws76mywSxgOcVNWcYZ5SsPXMLQG3JCIR9mYIbzxOPMkDguQtOVaHxWuBa3EmfxZlkF/exec?page=marketingmanager&manager=Tim%20Kennedy
C22: =concat(C21,C19)
C23: =concat(C22,C20)

Sheet GW_PartnerManagementActivities
A1: Item Name | B1: Group | C1: Board Name | D1: Partner Name | E1: Monday Item ID | F1: Board ID | G1: Activity Status | H1: Owner | I1: Assigned To | J1: Importance | K1: Activity Type | L1: Date Created | M1: Date Due | N1: Actual Completion | O1: Files | P1: Comments/Notes | Q1: Subitems | R1: Tech Board Type | S1: Alliance Manager | T1: Alliance Manager
A2: another test again | B2: Open Items | C2: Partner Management Activities | E2: 11093054347 | F2: 9791255941 | G2: In Progress | H2: Eric Apse | I2: Tim Kennedy | J2: 1. Urgent | K2: Referal | L2: 45698 | M2: 46028 | P2: just more test | R2: Partner Management Activities
A3: Make sure your parter is certified asap | B3: Open Items | C3: Partner Management Activities | E3: 10941024281 | F3: 9791255941 | G3: In Progress | H3: Eric Apse | I3: Tim Kennedy | J3: 1. Urgent | K3: Partner Management | L3: 45698 | M3: 46036 | R3: Partner Management Activities
A4: test | B4: Open Items | C4: Partner Management Activities | E4: 10809257698 | F4: 9791255941 | G4: In Progress | H4: Eric Apse | I4: Tim Kennedy | J4: 5. N/A | K4: TechAll Marketing | L4: 45698 | M4: 46037 | R4: Partner Management Activities
A5: test 2 | B5: Open Items | C5: Partner Management Activities | E5: 10813317258 | F5: 9791255941 | G5: In Progress | H5: Eric Apse | I5: Tim Kennedy | J5: 1. Urgent | K5: Marketplace | L5: 45698 | M5: 46033 | R5: Partner Management Activities
A6: test 3 | B6: Open Items | C6: Partner Management Activities | E6: 10813553846 | F6: 9791255941 | G6: In Progress | H6: Eric Apse | I6: Tim Kennedy | J6: 1. Urgent | K6: TechAll Marketing | L6: 45698 | M6: 46038 | R6: Partner Management Activities
A7: test3 new | B7: Open Items | C7: Partner Management Activities | E7: 10813549497 | F7: 9791255941 | G7: Halted | H7: Eric Apse | I7: Tim Kennedy | J7: 1. Urgent | K7: Marketplace | L7: 45698 | M7: 46038 | R7: Partner Management Activities
A8: tim test | B8: Open Items | C8: Partner Management Activities | E8: 10819625182 | F8: 9791255941 | G8: Blockers | H8: Tim Kennedy | I8: Tim Kennedy | J8: 1. Urgent | K8: Partner Management | L8: 45698 | M8: 46029 | P8: none | R8: Partner Management Activities

Sheet GW_TechOpsActivities
A1: Item Name | B1: Group | C1: Board Name | D1: Partner Name | E1: Monday Item ID | F1: Board ID | G1: Activity Status | H1: Owner | I1: Assigned To | J1: Importance | K1: Activity Type | L1: Date Created | M1: Date Due | N1: Actual Completion | O1: Files | P1: Comments/Notes | Q1: Subitems | R1: Tech Board Type | S1: Alliance Manager | T1: Alliance Manager
A2: test | B2: Open Items | C2: Tech Ops Activities | E2: 10813055615 | F2: 9791272390 | G2: In Progress | H2: Kayla Page | I2: Tim Kennedy | J2: 1. Urgent | K2: Validation | L2: 45698 | M2: 46052 | P2: none | R2: Tech Ops Activities

Sheet GW_MarketingActivities

Sheet GW_IntegrationComplianceActivit
A1: Item Name | B1: Group | C1: Board Name | D1: Partner Name | E1: Monday Item ID | F1: Board ID | G1: Activity Status | H1: Owner | I1: Assigned To | J1: Importance | K1: Activity Type | L1: Date Created | M1: Date Due | N1: Actual Completion | O1: Files | P1: Comments/Notes | Q1: Subitems | R1: Tech Board Type | S1: Alliance Manager | T1: Alliance Manager
A2: Test | B2: Open Items | C2: Integration Compliance Activities | E2: 11092783913 | F2: 18375013360 | G2: In Progress | H2: Richard Pauly | I2: Tim Kennedy | J2: 1. Urgent | K2: Partner Management | L2: 45698 | M2: 46052 | P2: test

Sheet Approvals2026
A1: Item Name | B1: Group | C1: Board Name | D1: Partner Name | E1: Monday Item ID | F1: Board ID | G1: Subitems | H1: Event URL | I1: Event Date Range and Location | J1: Decision Date By | K1: Primary Objectives | L1: Requestor | M1: Total Cost | N1: Non-participation Risks | O1: Funding Type | P1: MDF Requested | Q1: AWS MDF Requested | R1: Business Rational | S1: Strategic Fit | T1: Estimaged Attendees | U1: Named Customers/Prospects | V1: Target Personas | W1: Partner Recruitment Target | X1: Delivery Type | Y1: Overall Status | Z1: Sponsor Costs | AA1: Other Costs | AB1: AllianceManager | AC1: Partner | AD1: Market Position/Scale | AE1: Joint Customers | AF1: Integration Status | AG1: Recent joint Activities | AH1: Near Term Strategic Exploration | AI1: Event Lead (AM) | AJ1: Onsite Team | AK1: Speaker/Abstract/SessionTitle/link | AL1: Assets and Demo | AM1: SWAG Type/quantity | AN1: Other Assets | AO1: Dependencies | AP1: Requesting Department | AQ1: Partner Marketing Resources | AR1: Product Marketing Resources | AS1: Pre-event activation plan | AT1: Onsite event activation plan | AU1: Post-event activation plan | AV1: Post Event Report Due | AW1: New Leads | AX1: Meetings Held | AY1: Opportunities Created | AZ1: Pipleline $ Influenced | BA1: Boothscans | BB1: Brand/Media impressions | BC1: Customer Feedback/Testimonials | BD1: Competitive Insights | BE1: Learnings for Nextyear | BF1: Prospectus URL | BG1: Prospectus File Upload | BH1: Recommended Sponsor Tier | BI1: Other MPO | BJ1: SME Speakers | BK1: Panel Content | BL1: Industry Tradeshow/conference | BM1: Guidewire Trade Show | BN1: 1:1 Description | BO1: 1:1 Region | BP1: Event Start Date | BQ1: Create Date | BR1: Form Navigation | BS1: Scope Document Public URL | BT1: Alliance Manager
A2: Test from Tim | B2: Incoming | C2: 2026 Approvals | D2: Marketing Team | E2: 10693573595 | F2: 18389979949 | J2: 46022 | K2: Customer Story Capture, MQL Generation | L2: Tim Kennedy | N2: None | O2: Partner Funding Request | X2: Guidewire Trade Show or Conf (Partner Participation Request) | Y2: Submitted | AD2: Medium | AF2: None | BO2: n/a | BP2: 46023 | BQ2: 45994 | BR2: Exec Summary

Sheet 2026Flow
A1: Ignore | B1: Ignore | C1: Column ID | D1: Mandatory | E1: Section Grouping | F1: Group Name | G1: Monday Column | H1: Value
A2: Event Name, name | B2: =IFERROR(__xludf.DUMMYFUNCTION("ARRAYFORMULA(IF(A2:A1007="""",,SPLIT(TRIM(A2:A1007), "","")))"),"Event Name") -> Event Name | C2: =IFERROR(__xludf.DUMMYFUNCTION("""COMPUTED_VALUE""")," name") -> name | D2: TRUE | E2: Group 1 | F2: Executive Summary
A3: Event Start Date, date_mktkb5sf | B3: =IFERROR(__xludf.DUMMYFUNCTION("""COMPUTED_VALUE"""),"Event Start Date") -> Event Start Date | C3: =IFERROR(__xludf.DUMMYFUNCTION("""COMPUTED_VALUE""")," date_mktkb5sf") -> date_mktkb5sf | D3: TRUE | E3: Group 1 | F3: Executive Summary
A4: Event URL, text_mktj8ce4 | B4: =IFERROR(__xludf.DUMMYFUNCTION("""COMPUTED_VALUE"""),"Event URL") -> Event URL | C4: =IFERROR(__xludf.DUMMYFUNCTION("""COMPUTED_VALUE""")," text_mktj8ce4") -> text_mktj8ce4 | E4: Group 1 | F4: Executive Summary
A5: Decision Date By, date_mky170gm | B5: =IFERROR(__xludf.DUMMYFUNCTION("""COMPUTED_VALUE"""),"Decision Date By") -> Decision Date By | C5: =IFERROR(__xludf.DUMMYFUNCTION("""COMPUTED_VALUE""")," date_mky170gm") -> date_mky170gm | D5: TRUE | E5: Group 1 | F5: Executive Summary
A6: Event Date Range and Location, text_mktkdwry | B6: =IFERROR(__xludf.DUMMYFUNCTION("""COMPUTED_VALUE"""),"Event Date Range and Location") -> Event Date Range and Location | C6: =IFERROR(__xludf.DUMMYFUNCTION("""COMPUTED_VALUE""")," text_mktkdwry") -> text_mktkdwry | E6: Group 1 | F6: Executive Summary
A7: Primary Objectives, dropdown_mky16p7m | B7: =IFERROR(__xludf.DUMMYFUNCTION("""COMPUTED_VALUE"""),"Primary Objectives") -> Primary Objectives | C7: =IFERROR(__xludf.DUMMYFUNCTION("""COMPUTED_VALUE""")," dropdown_mky16p7m") -> dropdown_mky16p7m | D7: TRUE | E7: Group 1 | F7: Executive Summary
A8: Requestor, text_mky7xyqh | B8: =IFERROR(__xludf.DUMMYFUNCTION("""COMPUTED_VALUE"""),"Requestor") -> Requestor | C8: =IFERROR(__xludf.DUMMYFUNCTION("""COMPUTED_VALUE""")," text_mky7xyqh") -> text_mky7xyqh | E8: Group 1 | F8: Executive Summary
A9: Non-participation Risks, text_mky7njax | B9: =IFERROR(__xludf.DUMMYFUNCTION("""COMPUTED_VALUE"""),"Non-participation Risks") -> Non-participation Risks | C9: =IFERROR(__xludf.DUMMYFUNCTION("""COMPUTED_VALUE""")," text_mky7njax") -> text_mky7njax | E9: Group 1 | F9: Executive Summary
A10: Funding Type, color_mkxxef94 | B10: =IFERROR(__xludf.DUMMYFUNCTION("""COMPUTED_VALUE"""),"Funding Type") -> Funding Type | C10: =IFERROR(__xludf.DUMMYFUNCTION("""COMPUTED_VALUE""")," color_mkxxef94") -> color_mkxxef94 | D10: TRUE | E10: Group 1 | F10: Executive Summary
A11: Overall Status, status | B11: =IFERROR(__xludf.DUMMYFUNCTION("""COMPUTED_VALUE"""),"Overall Status") -> Overall Status | C11: =IFERROR(__xludf.DUMMYFUNCTION("""COMPUTED_VALUE""")," status") -> status | E11: Group 1 | F11: Executive Summary
A12: MDF Requested, color_mky7z1eq | B12: =IFERROR(__xludf.DUMMYFUNCTION("""COMPUTED_VALUE"""),"MDF Requested") -> MDF Requested | C12: =IFERROR(__xludf.DUMMYFUNCTION("""COMPUTED_VALUE""")," color_mky7z1eq") -> color_mky7z1eq | E12: Group 1 | F12: Executive Summary | G12: color_mky7z1eq | H12: MDF
A13: AWS MDF Requested, color_mky7zxp7 | B13: =IFERROR(__xludf.DUMMYFUNCTION("""COMPUTED_VALUE"""),"AWS MDF Requested") -> AWS MDF Requested | C13: =IFERROR(__xludf.DUMMYFUNCTION("""COMPUTED_VALUE""")," color_mky7zxp7") -> color_mky7zxp7 | E13: Group 1 | F13: Executive Summary | G13: color_mky7z1eq | H13: MDF
A14: Business Rational, long_text_mky25ed4 | B14: =IFERROR(__xludf.DUMMYFUNCTION("""COMPUTED_VALUE"""),"Business Rational") -> Business Rational | C14: =IFERROR(__xludf.DUMMYFUNCTION("""COMPUTED_VALUE""")," long_text_mky25ed4") -> long_text_mky25ed4 | D14: TRUE | E14: Group 2 | F14: Buisiness Rational
A15: Strategic Fit, dropdown_mky29cfy | B15: =IFERROR(__xludf.DUMMYFUNCTION("""COMPUTED_VALUE"""),"Strategic Fit") -> Strategic Fit | C15: =IFERROR(__xludf.DUMMYFUNCTION("""COMPUTED_VALUE""")," dropdown_mky29cfy") -> dropdown_mky29cfy | D15: TRUE | E15: Group 2 | F15: Buisiness Rational
A16: Estimaged Attendees, text_mky7v3a | B16: =IFERROR(__xludf.DUMMYFUNCTION("""COMPUTED_VALUE"""),"Estimaged Attendees") -> Estimaged Attendees | C16: =IFERROR(__xludf.DUMMYFUNCTION("""COMPUTED_VALUE""")," text_mky7v3a") -> text_mky7v3a | E16: Group 3 | F16: Buisiness Outcome
A17: Named Customers/Prospects, text_mky79235 | B17: =IFERROR(__xludf.DUMMYFUNCTION("""COMPUTED_VALUE"""),"Named Customers/Prospects") -> Named Customers/Prospects | C17: =IFERROR(__xludf.DUMMYFUNCTION("""COMPUTED_VALUE""")," text_mky79235") -> text_mky79235 | E17: Group 3 | F17: Buisiness Outcome
A18: Target Personas, dropdown_mky7k6qv | B18: =IFERROR(__xludf.DUMMYFUNCTION("""COMPUTED_VALUE"""),"Target Personas") -> Target Personas | C18: =IFERROR(__xludf.DUMMYFUNCTION("""COMPUTED_VALUE""")," dropdown_mky7k6qv") -> dropdown_mky7k6qv | E18: Group 3 | F18: Buisiness Outcome
A19: Partner Recruitment Target, text_mky7tsn8 | B19: =IFERROR(__xludf.DUMMYFUNCTION("""COMPUTED_VALUE"""),"Partner Recruitment Target") -> Partner Recruitment Target | C19: =IFERROR(__xludf.DUMMYFUNCTION("""COMPUTED_VALUE""")," text_mky7tsn8") -> text_mky7tsn8 | E19: Group 3 | F19: Buisiness Outcome
A20: Delivery Type, color_mky78mye | B20: =IFERROR(__xludf.DUMMYFUNCTION("""COMPUTED_VALUE"""),"Delivery Type") -> Delivery Type | C20: =IFERROR(__xludf.DUMMYFUNCTION("""COMPUTED_VALUE""")," color_mky78mye") -> color_mky78mye | D20: TRUE | E20: Group 4 | F20: Event Specific Information
A21: Prospectus URL, link_mky7wxqq | B21: =IFERROR(__xludf.DUMMYFUNCTION("""COMPUTED_VALUE"""),"Prospectus URL") -> Prospectus URL | C21: =IFERROR(__xludf.DUMMYFUNCTION("""COMPUTED_VALUE""")," link_mky7wxqq") -> link_mky7wxqq | E21: Group 4 | F21: Event Specific Information | G21: color_mky78mye | H21: Partner Trade Show/Conf - Co-Marketing Request, Partner Trade Show/Conf - Sponsor Funding
A22: Prospectus File Upload, file_mky8p6fk | B22: =IFERROR(__xludf.DUMMYFUNCTION("""COMPUTED_VALUE"""),"Prospectus File Upload") -> Prospectus File Upload | C22: =IFERROR(__xludf.DUMMYFUNCTION("""COMPUTED_VALUE""")," file_mky8p6fk") -> file_mky8p6fk | E22: Group 4 | F22: Event Specific Information | G22: color_mky78mye | H22: Partner Trade Show/Conf - Co-Marketing Request, Partner Trade Show/Conf - Sponsor Funding
A23: Recommended Sponsor Tier, text_mky76e8h | B23: =IFERROR(__xludf.DUMMYFUNCTION("""COMPUTED_VALUE"""),"Recommended Sponsor Tier") -> Recommended Sponsor Tier | C23: =IFERROR(__xludf.DUMMYFUNCTION("""COMPUTED_VALUE""")," text_mky76e8h") -> text_mky76e8h | E23: Group 4 | F23: Event Specific Information | G23: color_mky78mye | H23: Partner Trade Show/Conf - Co-Marketing Request, Partner Trade Show/Conf - Sponsor Funding
A24: Other MPO, text_mky7e8yw | B24: =IFERROR(__xludf.DUMMYFUNCTION("""COMPUTED_VALUE"""),"Other MPO") -> Other MPO | C24: =IFERROR(__xludf.DUMMYFUNCTION("""COMPUTED_VALUE""")," text_mky7e8yw") -> text_mky7e8yw | E24: Group 4 | F24: Event Specific Information | G24: color_mky78mye | H24: Partner Trade Show/Conf - Co-Marketing Request, Partner Trade Show/Conf - Sponsor Funding
A25: SME Speakers, text_mky7gcf0 | B25: =IFERROR(__xludf.DUMMYFUNCTION("""COMPUTED_VALUE"""),"SME Speakers") -> SME Speakers | C25: =IFERROR(__xludf.DUMMYFUNCTION("""COMPUTED_VALUE""")," text_mky7gcf0") -> text_mky7gcf0 | E25: Group 4 | F25: Event Specific Information | G25: color_mky78mye | H25: Partner Trade Show/Conf - Co-Marketing Request, Partner Trade Show/Conf - Sponsor Funding
A26: Panel Content, text_mky7c787 | B26: =IFERROR(__xludf.DUMMYFUNCTION("""COMPUTED_VALUE"""),"Panel Content") -> Panel Content | C26: =IFERROR(__xludf.DUMMYFUNCTION("""COMPUTED_VALUE""")," text_mky7c787") -> text_mky7c787 | E26: Group 4 | F26: Event Specific Information | G26: color_mky78mye | H26: Partner Trade Show/Conf - Co-Marketing Request, Partner Trade Show/Conf - Sponsor Funding
A27: Industry Tradeshow/conference, dropdown_mky7b5t0 | B27: =IFERROR(__xludf.DUMMYFUNCTION("""COMPUTED_VALUE"""),"Industry Tradeshow/conference") -> Industry Tradeshow/conference | C27: =IFERROR(__xludf.DUMMYFUNCTION("""COMPUTED_VALUE""")," dropdown_mky7b5t0") -> dropdown_mky7b5t0 | E27: Group 4 | F27: Event Specific Information | G27: color_mky78mye | H27: Industry Trade Show/Conf
A28: Guidewire Trade Show, dropdown_mky7qg9p | B28: =IFERROR(__xludf.DUMMYFUNCTION("""COMPUTED_VALUE"""),"Guidewire Trade Show") -> Guidewire Trade Show | C28: =IFERROR(__xludf.DUMMYFUNCTION("""COMPUTED_VALUE""")," dropdown_mky7qg9p") -> dropdown_mky7qg9p | E28: Group 4 | F28: Event Specific Information | G28: color_mky78mye | H28: Guidewire Trade Show or Conf (Partner Participation Request)
A29: 1:1 Description, text_mky7dz7 | B29: =IFERROR(__xludf.DUMMYFUNCTION("""COMPUTED_VALUE"""),"1:1 Description") -> 1:1 Description | C29: =IFERROR(__xludf.DUMMYFUNCTION("""COMPUTED_VALUE""")," text_mky7dz7") -> text_mky7dz7 | E29: Group 4 | F29: Event Specific Information | G29: dropdown_mky7b5t0 | H29: 1:1 Breakfast or Lunch Meeting
A30: 1:1 Region, color_mky7gz0q | B30: =IFERROR(__xludf.DUMMYFUNCTION("""COMPUTED_VALUE"""),"1:1 Region") -> 1:1 Region | C30: =IFERROR(__xludf.DUMMYFUNCTION("""COMPUTED_VALUE""")," color_mky7gz0q") -> color_mky7gz0q | E30: Group 4 | F30: Event Specific Information | G30: dropdown_mky7b5t0 | H30: 1:1 Breakfast or Lunch Meeting
A31: Partner, text_mkv092nh | B31: =IFERROR(__xludf.DUMMYFUNCTION("""COMPUTED_VALUE"""),"Partner") -> Partner | C31: =IFERROR(__xludf.DUMMYFUNCTION("""COMPUTED_VALUE""")," text_mkv092nh") -> text_mkv092nh | E31: Group 5 | F31: Partner Information
A32: AllianceManager, color_mky7zf8e | B32: =IFERROR(__xludf.DUMMYFUNCTION("""COMPUTED_VALUE"""),"AllianceManager") -> AllianceManager | C32: =IFERROR(__xludf.DUMMYFUNCTION("""COMPUTED_VALUE""")," color_mky7zf8e") -> color_mky7zf8e | E32: Group 5 | F32: Partner Information
A33: Sponsor Costs, numeric_mky791e | B33: =IFERROR(__xludf.DUMMYFUNCTION("""COMPUTED_VALUE"""),"Sponsor Costs") -> Sponsor Costs | C33: =IFERROR(__xludf.DUMMYFUNCTION("""COMPUTED_VALUE""")," numeric_mky791e") -> numeric_mky791e | E33: Group 5 | F33: Partner Information
A34: Other Costs, numeric_mky7r8yp | B34: =IFERROR(__xludf.DUMMYFUNCTION("""COMPUTED_VALUE"""),"Other Costs") -> Other Costs | C34: =IFERROR(__xludf.DUMMYFUNCTION("""COMPUTED_VALUE""")," numeric_mky7r8yp") -> numeric_mky7r8yp | E34: Group 5 | F34: Partner Information
A35: Market Position/Scale, color_mky76dt5 | B35: =IFERROR(__xludf.DUMMYFUNCTION("""COMPUTED_VALUE"""),"Market Position/Scale") -> Market Position/Scale | C35: =IFERROR(__xludf.DUMMYFUNCTION("""COMPUTED_VALUE""")," color_mky76dt5") -> color_mky76dt5 | E35: Group 5 | F35: Partner Information
A36: Joint Customers, text_mky7ywb2 | B36: =IFERROR(__xludf.DUMMYFUNCTION("""COMPUTED_VALUE"""),"Joint Customers") -> Joint Customers | C36: =IFERROR(__xludf.DUMMYFUNCTION("""COMPUTED_VALUE""")," text_mky7ywb2") -> text_mky7ywb2 | E36: Group 5 | F36: Partner Information
A37: Integration Status, color_mky7dc8q | B37: =IFERROR(__xludf.DUMMYFUNCTION("""COMPUTED_VALUE"""),"Integration Status") -> Integration Status | C37: =IFERROR(__xludf.DUMMYFUNCTION("""COMPUTED_VALUE""")," color_mky7dc8q") -> color_mky7dc8q | E37: Group 5 | F37: Partner Information
A38: Recent joint Activities, text_mky75gvt | B38: =IFERROR(__xludf.DUMMYFUNCTION("""COMPUTED_VALUE"""),"Recent joint Activities") -> Recent joint Activities | C38: =IFERROR(__xludf.DUMMYFUNCTION("""COMPUTED_VALUE""")," text_mky75gvt") -> text_mky75gvt | E38: Group 5 | F38: Partner Information
A39: Near Term Strategic Exploration, dropdown_mky7vh1m | B39: =IFERROR(__xludf.DUMMYFUNCTION("""COMPUTED_VALUE"""),"Near Term Strategic Exploration") -> Near Term Strategic Exploration | C39: =IFERROR(__xludf.DUMMYFUNCTION("""COMPUTED_VALUE""")," dropdown_mky7vh1m") -> dropdown_mky7vh1m | E39: Group 5 | F39: Partner Information
A40: Event Lead (AM), text_mky7mp7p | B40: =IFERROR(__xludf.DUMMYFUNCTION("""COMPUTED_VALUE"""),"Event Lead (AM)") -> Event Lead (AM) | C40: =IFERROR(__xludf.DUMMYFUNCTION("""COMPUTED_VALUE""")," text_mky7mp7p") -> text_mky7mp7p | E40: Group 6 | F40: Resourcing Plan
A41: Onsite Team, text_mky74107 | B41: =IFERROR(__xludf.DUMMYFUNCTION("""COMPUTED_VALUE"""),"Onsite Team") -> Onsite Team | C41: =IFERROR(__xludf.DUMMYFUNCTION("""COMPUTED_VALUE""")," text_mky74107") -> text_mky74107 | E41: Group 6 | F41: Resourcing Plan
A42: Speaker/Abstract/SessionTitle/link, text_mky7xdf6 | B42: =IFERROR(__xludf.DUMMYFUNCTION("""COMPUTED_VALUE"""),"Speaker/Abstract/SessionTitle/link") -> Speaker/Abstract/SessionTitle/link | C42: =IFERROR(__xludf.DUMMYFUNCTION("""COMPUTED_VALUE""")," text_mky7xdf6") -> text_mky7xdf6 | E42: Group 6 | F42: Resourcing Plan
A43: Assets and Demo, dropdown_mky72rrn | B43: =IFERROR(__xludf.DUMMYFUNCTION("""COMPUTED_VALUE"""),"Assets and Demo") -> Assets and Demo | C43: =IFERROR(__xludf.DUMMYFUNCTION("""COMPUTED_VALUE""")," dropdown_mky72rrn") -> dropdown_mky72rrn | E43: Group 6 | F43: Resourcing Plan
A44: SWAG Type/quantity, text_mky785z9 | B44: =IFERROR(__xludf.DUMMYFUNCTION("""COMPUTED_VALUE"""),"SWAG Type/quantity") -> SWAG Type/quantity | C44: =IFERROR(__xludf.DUMMYFUNCTION("""COMPUTED_VALUE""")," text_mky785z9") -> text_mky785z9 | E44: Group 6 | F44: Resourcing Plan
A45: Other Assets, text_mky7vayd | B45: =IFERROR(__xludf.DUMMYFUNCTION("""COMPUTED_VALUE"""),"Other Assets") -> Other Assets | C45: =IFERROR(__xludf.DUMMYFUNCTION("""COMPUTED_VALUE""")," text_mky7vayd") -> text_mky7vayd | E45: Group 6 | F45: Resourcing Plan
A46: Dependencies, text_mky7d2z2 | B46: =IFERROR(__xludf.DUMMYFUNCTION("""COMPUTED_VALUE"""),"Dependencies") -> Dependencies | C46: =IFERROR(__xludf.DUMMYFUNCTION("""COMPUTED_VALUE""")," text_mky7d2z2") -> text_mky7d2z2 | E46: Group 6 | F46: Resourcing Plan
A47: Requesting Department, status_1 | B47: =IFERROR(__xludf.DUMMYFUNCTION("""COMPUTED_VALUE"""),"Requesting Department") -> Requesting Department | C47: =IFERROR(__xludf.DUMMYFUNCTION("""COMPUTED_VALUE""")," status_1") -> status_1 | E47: Group 6 | F47: Resourcing Plan
A48: Partner Marketing Resources, text_mky7rr8j | B48: =IFERROR(__xludf.DUMMYFUNCTION("""COMPUTED_VALUE"""),"Partner Marketing Resources") -> Partner Marketing Resources | C48: =IFERROR(__xludf.DUMMYFUNCTION("""COMPUTED_VALUE""")," text_mky7rr8j") -> text_mky7rr8j | E48: Group 6 | F48: Resourcing Plan
A49: Product Marketing Resources, text_mky798s1 | B49: =IFERROR(__xludf.DUMMYFUNCTION("""COMPUTED_VALUE"""),"Product Marketing Resources") -> Product Marketing Resources | C49: =IFERROR(__xludf.DUMMYFUNCTION("""COMPUTED_VALUE""")," text_mky798s1") -> text_mky798s1 | E49: Group 6 | F49: Resourcing Plan
A50: Pre-event activation plan, long_text_mky780sa | B50: =IFERROR(__xludf.DUMMYFUNCTION("""COMPUTED_VALUE"""),"Pre-event activation plan") -> Pre-event activation plan | C50: =IFERROR(__xludf.DUMMYFUNCTION("""COMPUTED_VALUE""")," long_text_mky780sa") -> long_text_mky780sa | E50: Group 7 | F50: Activation Plan
A51: Onsite event activation plan, long_text_mky7mct8 | B51: =IFERROR(__xludf.DUMMYFUNCTION("""COMPUTED_VALUE"""),"Onsite event activation plan") -> Onsite event activation plan | C51: =IFERROR(__xludf.DUMMYFUNCTION("""COMPUTED_VALUE""")," long_text_mky7mct8") -> long_text_mky7mct8 | E51: Group 7 | F51: Activation Plan
A52: Post-event activation plan, long_text_mky72g9a | B52: =IFERROR(__xludf.DUMMYFUNCTION("""COMPUTED_VALUE"""),"Post-event activation plan") -> Post-event activation plan | C52: =IFERROR(__xludf.DUMMYFUNCTION("""COMPUTED_VALUE""")," long_text_mky72g9a") -> long_text_mky72g9a | E52: Group 7 | F52: Activation Plan
A53: Post Event Report Due, date_mky73kmp | B53: =IFERROR(__xludf.DUMMYFUNCTION("""COMPUTED_VALUE"""),"Post Event Report Due") -> Post Event Report Due | C53: =IFERROR(__xludf.DUMMYFUNCTION("""COMPUTED_VALUE""")," date_mky73kmp") -> date_mky73kmp | E53: Group 8 | F53: Reporting and ROI
A54: New Leads, text_mky715r7 | B54: =IFERROR(__xludf.DUMMYFUNCTION("""COMPUTED_VALUE"""),"New Leads") -> New Leads | C54: =IFERROR(__xludf.DUMMYFUNCTION("""COMPUTED_VALUE""")," text_mky715r7") -> text_mky715r7 | E54: Group 8 | F54: Reporting and ROI
A55: Meetings Held, text_mky7bme0 | B55: =IFERROR(__xludf.DUMMYFUNCTION("""COMPUTED_VALUE"""),"Meetings Held") -> Meetings Held | C55: =IFERROR(__xludf.DUMMYFUNCTION("""COMPUTED_VALUE""")," text_mky7bme0") -> text_mky7bme0 | E55: Group 8 | F55: Reporting and ROI
A56: Opportunities Created, text_mky7yx4w | B56: =IFERROR(__xludf.DUMMYFUNCTION("""COMPUTED_VALUE"""),"Opportunities Created") -> Opportunities Created | C56: =IFERROR(__xludf.DUMMYFUNCTION("""COMPUTED_VALUE""")," text_mky7yx4w") -> text_mky7yx4w | E56: Group 8 | F56: Reporting and ROI
A57: Pipleline $ Influenced, text_mky7j1z0 | B57: =IFERROR(__xludf.DUMMYFUNCTION("""COMPUTED_VALUE"""),"Pipleline $ Influenced") -> Pipleline $ Influenced | C57: =IFERROR(__xludf.DUMMYFUNCTION("""COMPUTED_VALUE""")," text_mky7j1z0") -> text_mky7j1z0 | E57: Group 8 | F57: Reporting and ROI
A58: Boothscans, text_mky7kbbz | B58: =IFERROR(__xludf.DUMMYFUNCTION("""COMPUTED_VALUE"""),"Boothscans") -> Boothscans | C58: =IFERROR(__xludf.DUMMYFUNCTION("""COMPUTED_VALUE""")," text_mky7kbbz") -> text_mky7kbbz | E58: Group 8 | F58: Reporting and ROI
A59: Brand/Media impressions, text_mky717tz | B59: =IFERROR(__xludf.DUMMYFUNCTION("""COMPUTED_VALUE"""),"Brand/Media impressions") -> Brand/Media impressions | C59: =IFERROR(__xludf.DUMMYFUNCTION("""COMPUTED_VALUE""")," text_mky717tz") -> text_mky717tz | E59: Group 8 | F59: Reporting and ROI
A60: Customer Feedback/Testimonials, text_mky73vf5 | B60: =IFERROR(__xludf.DUMMYFUNCTION("""COMPUTED_VALUE"""),"Customer Feedback/Testimonials") -> Customer Feedback/Testimonials | C60: =IFERROR(__xludf.DUMMYFUNCTION("""COMPUTED_VALUE""")," text_mky73vf5") -> text_mky73vf5 | E60: Group 8 | F60: Reporting and ROI
A61: Competitive Insights, text_mky7wvep | B61: =IFERROR(__xludf.DUMMYFUNCTION("""COMPUTED_VALUE"""),"Competitive Insights") -> Competitive Insights | C61: =IFERROR(__xludf.DUMMYFUNCTION("""COMPUTED_VALUE""")," text_mky7wvep") -> text_mky7wvep | E61: Group 8 | F61: Reporting and ROI
A62: Learnings for Nextyear, text_mky72rb1 | B62: =IFERROR(__xludf.DUMMYFUNCTION("""COMPUTED_VALUE"""),"Learnings for Nextyear") -> Learnings for Nextyear | C62: =IFERROR(__xludf.DUMMYFUNCTION("""COMPUTED_VALUE""")," text_mky72rb1") -> text_mky72rb1 | E62: Group 8 | F62: Reporting and ROI

Sheet MondayData
A1: Item Name | B1: Group | C1: Board Name | D1: Partner Name | E1: Monday Item ID | F1: Board ID | G1: Subitems | H1: Comments/Notes | I1: Activity Status | J1: Owner | K1: Importance | L1: Activity | M1: Date Created | N1: Date Due | O1: Actual Completion | P1: Files | Q1: Tech Partner Name | R1: Scope Document Public URL | S1: Alliance Manager | T1: Alliance Manager
A2: Agenda for Meeting in December in London | B2: Completed Items | C2: Hyperexponential Ltd Board | D2: Hyperexponential Ltd | E2: 18387680182 | F2: 18402564488 | H2: Patrick has provided. | I2: Completed | K2: 2. High | L2: Marketing | M2: 45982 | O2: 46001 | Q2: Hyperexponential Ltd | S2: Tim Kennedy
A3: American Guaranty Fund Group | B3: Completed Items | C3: Newgen Software Inc. Board | D3: Newgen Software Inc. | E3: 9080309128 | F3: 18402565546 | H3: Newgen has submitted the proposal. waiting for customer to make decision on GW CC + Newgen ECM; In touch with Brittany. | I3: Completed | K3: 2. High | L3: Alliances | M3: 45783 | Q3: Newgen Software Inc. | S3: Tim Kennedy
A4: Ammendment needs signature for annex A | B4: Completed Items | C4: Insurance Services Office (ISO) Board | D4: Insurance Services Office (ISO) | E4: 8714057396 | F4: 18402568111 | I4: Completed | K4: 2. High | L4: Contracts | M4: 45733 | O4: 45985 | Q4: Verisk | S4: Tim Kennedy
A5: Are there sources of data we could buy from Verisk | B5: Completed Items | C5: Insurance Services Office (ISO) Board | D5: Insurance Services Office (ISO) | E5: 8821376581 | F5: 18402568111 | I5: Completed | K5: 4. Low | L5: Alliances | M5: 45747 | O5: 46010 | Q5: Verisk | S5: Tim Kennedy
A6: Ask Gilbert if his team will set up open telemetry on the Dynatrace NPE | B6: Open Items | C6: Dynatrace LLC Board | D6: Dynatrace LLC | E6: 11342942612 | F6: 18402564263 | I6: In Progress | K6: 3. Medium | L6: Sponsorship/Events | M6: 46076 | Q6: Dynatrace LLC | S6: Tim Kennedy
A7: Audit result - next steps - amend agreement on calculations | B7: Open Items | C7: Insurance Services Office (ISO) Board | D7: Insurance Services Office (ISO) | E7: 8821456844 | F7: 18402568111 | I7: SOLD | J7: GW Alliances | K7: 1. Urgent | L7: Contracts | M7: 45698 | Q7: Verisk | S7: Tim Kennedy
A8: Aviva Canada | B8: Completed Items | C8: Whatfix Inc. Board | D8: Whatfix Inc. | E8: 8671192538 | F8: 18402568372 | H8: Rebooked for May | I8: Completed | K8: 3. Medium | L8: Pipeline | M8: 45727 | O8: 45896 | Q8: Whatfix Inc. | S8: Tim Kennedy
A9: BBG TPPA Upate | B9: Open Items | C9: LexisNexis Risk Solutions Inc. Board | D9: LexisNexis Risk Solutions Inc. | E9: 18357680785 | F9: 18402564676 | H9: Tim walked the values.. they want some sort of SLA | I9: Completed | J9: Partner Alliances | K9: 1. Urgent | L9: Alliances | M9: 45966 | Q9: LexisNexis Risk Solutions Inc. | S9: Tim Kennedy
A10: Bhaskar - accelerator or not | B10: Open Items | C10: Dynatrace LLC Board | D10: Dynatrace LLC | E10: 11342940453 | F10: 18402564263 | I10: In Progress | K10: 3. Medium | L10: Sponsorship/Events | M10: 46076 | Q10: Dynatrace LLC | S10: Tim Kennedy
A11: Billing Center Accelerator | B11: Open Items | C11: Whatfix Inc. Board | D11: Whatfix Inc. | E11: 8741290643 | F11: 18402568372 | H11: We have paused this as our team is still assessing which product makes the most sense for us to build Whatfix on. | I11: Halted | J11: Partner Alliances | K11: 3. Medium | L11: Alliances | M11: 45736 | Q11: Whatfix Inc. | S11: Tim Kennedy
A12: BillingCenter Integration with Newgen ECM | B12: Completed Items | C12: Newgen Software Inc. Board | D12: Newgen Software Inc. | E12: 8464228904 | F12: 18402565546 | H12: Scope accepted. Dev in progress | I12: Completed | J12: GW Alliances, Partner Alliances | K12: 3. Medium | L12: Accelerator | M12: 45700 | Q12: Newgen Software Inc. | S12: Tim Kennedy
A13: Blog entry - Tim to edit | B13: Completed Items | C13: WTW Board | D13: WTW | E13: 9413258850 | F13: 18402568518 | I13: Completed | J13: Partner Alliances | K13: 3. Medium | L13: Marketing | M13: 45698 | N13: 46032 | Q13: WTW | S13: Tim Kennedy
A14: BOLT Next Steps & Development Plan | B14: Open Items | C14: Whatfix Inc. Board | D14: Whatfix Inc. | E14: 9849857923 | F14: 18402568372 | H14: As part of restructuring, we disolved our APAC partner team. Tony will have to get engaged. | I14: In Progress | J14: GW Alliances, Partner Alliances, GW Solution Consulting | K14: 2. High | L14: Marketing | M14: 45698 | Q14: Whatfix Inc. | S14: Tim Kennedy
A15: book Friday touch base. | B15: Completed Items | C15: SS&C Blue Prism Board | D15: SS&C Blue Prism | E15: 9035222909 | F15: 18402563983 | I15: Completed | K15: 3. Medium | L15: Alliances | M15: 45776 | O15: 46010 | Q15: Blue Prism | S15: Tim Kennedy
A16: Box - financial servicres summit | B16: Completed Items | C16: Box Board | D16: Box | E16: 18047259948 | F16: 18402563866 | H16: Paul Edwards is speaking from London Markets team | I16: Completed | K16: 2. High | L16: Alliances | M16: 45925 | O16: 45985 | Q16: Box | S16: Tim Kennedy
A17: Box wants to look at esignature | B17: Open Items | C17: Box Board | D17: Box | E17: 11379534221 | F17: 18402563866 | H17: recommend rolling it out in phases | I17: In Progress | J17: GW Alliances | K17: 2. High | L17: Accelerator | M17: 45698 | N17: 46093 | Q17: Box | S17: Tim Kennedy
A18: bundling | B18: Open Items | C18: Mitchell International, Inc. Board | D18: Mitchell International, Inc. | E18: 11428960695 | F18: 18402617065 | H18: phase 2 and phase 3 bundled as one release. | I18: In Progress | J18: Partner Alliances | K18: 2. High | L18: Alliances | M18: 45698 | S18: Tim Kennedy
A19: can we post linked in post for Whatfix premier partner press release | B19: Completed Items | C19: Whatfix Inc. Board | D19: Whatfix Inc. | E19: 10749567978 | F19: 18402568372 | H19: Asking Julie | I19: Completed | K19: 3. Medium | L19: Marketing | M19: 45698 | O19: 46010 | Q19: Whatfix Inc. | S19: Tim Kennedy
A20: Canada Webinar - | B20: Open Items | C20: Open Text Corporation Board | D20: Open Text Corporation | E20: 11377067523 | F20: 18402565219 | I20: Not Started | K20: 5. N/A | L20: Alliances | M20: 46079 | N20: 46093 | Q20: Open Text Corporation | S20: Tim Kennedy
A21: CEO Meeting | B21: Completed Items | C21: Box Board | D21: Box | E21: 18047191750 | F21: 18402563866 | H21: Intel - both agree good momentum. Mike took action to circle back with product leadership team for other product integrations. followup email thread . Will Murphy added... lets put together a workshop to elevate partnership to next level. Work with PWC and Deloitte. Conversation triggered by Safety win earlier this year. Usecase where box can extract structured content from unstructured documents and feed into Guidewire. | I21: Completed | K21: 3. Medium | L21: Alliances | M21: 45925 | O21: 45985 | Q21: Box | S21: Tim Kennedy
A22: Claims Datafill Updates | B22: Completed Items | C22: LexisNexis Risk Solutions Inc. Board | D22: LexisNexis Risk Solutions Inc. | E22: 8577093443 | F22: 18402564676 | H22: I have passed on the information to the BBG team | I22: Completed | K22: 1. Urgent | L22: Accelerator | M22: 45714 | O22: 45805 | Q22: LexisNexis Risk Solutions Inc. | S22: Tim Kennedy
A23: Closures this past year | B23: Completed Items | C23: Newgen Software Inc. Board | D23: Newgen Software Inc. | E23: 8987592914 | F23: 18402565546 | H23: Red River Mutual, QBE, Market, Adica | I23: Completed | J23: Partner Alliances | K23: 3. Medium | L23: Alliances | M23: 45770 | Q23: Newgen Software Inc. | S23: Tim Kennedy
A24: Common Customer List | B24: Completed Items | C24: AKUR8 Board | D24: AKUR8 | E24: 9412594506 | F24: 18402561158 | I24: Completed | K24: 2. High | L24: Pipeline | M24: 45827 | O24: 45985 | Q24: Akur8 | S24: Tim Kennedy
A25: Connections - gold plus | B25: Completed Items | C25: WTW Board | D25: WTW | E25: 9212952335 | F25: 18402568518 | H25: Admiral insurance. GM Financial as well | I25: Completed | K25: 3. Medium | L25: Alliances | M25: 45799 | Q25: WTW | S25: Tim Kennedy
A26: Connections meetings with Alliances and CSM | B26: Completed Items | C26: Newgen Software Inc. Board | D26: Newgen Software Inc. | E26: 9910630591 | F26: 18402565546 | H26: Swapnil wants to meet with CSMs Newgen is working with at GW Connections | I26: Completed | J26: GW Alliances | K26: 1. Urgent | L26: Sponsorship/Events | M26: 45896 | Q26: Newgen Software Inc. | S26: Tim Kennedy
A27: Countersigned Enhancements Contract | B27: Open Items | C27: Mitchell International, Inc. Board | D27: Mitchell International, Inc. | E27: 11428967324 | F27: 18402617065 | H27: Should be soon. | I27: In Progress | J27: GW Alliances | K27: 2. High | L27: Alliances | M27: 46071 | S27: Tim Kennedy
A28: CSAA | B28: Completed Items | C28: Box Board | D28: Box | E28: 18047300561 | F28: 18402563866 | I28: Completed | K28: 3. Medium | L28: Alliances | M28: 45925 | O28: 45985 | Q28: Box | S28: Tim Kennedy
A29: CSAA Police Records having problems with Police Records | B29: Completed Items | C29: LexisNexis Risk Solutions Inc. Board | D29: LexisNexis Risk Solutions Inc. | E29: 8844790265 | F29: 18402564676 | H29: Have passed it on to the BBG Team | I29: Completed | K29: 5. N/A | L29: Alliances | M29: 45749 | O29: 45805 | Q29: LexisNexis Risk Solutions Inc. | S29: Tim Kennedy
A30: CSAA- meeting with David McMinn | B30: Completed Items | C30: Newgen Software Inc. Board | D30: Newgen Software Inc. | E30: 9352347948 | F30: 18402565546 | H30: Newgen Demo scheduled; Tim to help introduce David McMinn | I30: Completed | K30: 3. Medium | L30: Alliances | M30: 45819 | Q30: Newgen Software Inc. | S30: Tim Kennedy
A31: Customer and Pipeline Report | B31: Open Items | C31: Whatfix Inc. Board | D31: Whatfix Inc. | E31: 8564192033 | F31: 18402568372 | I31: Ongoing | J31: Partner Alliances | K31: 3. Medium | L31: Marketing | M31: 45713 | Q31: Whatfix Inc. | S31: Tim Kennedy
A32: Customer and Prospect Tracker | B32: Open Items | C32: Mitchell International, Inc. Board | D32: Mitchell International, Inc. | E32: 11428971401 | F32: 18402617065 | I32: Ongoing | J32: Partner Alliances | K32: 3. Medium | L32: Pipeline | M32: 45735 | S32: Tim Kennedy
A33: Customer List | B33: Completed Items | C33: Box Board | D33: Box | E33: 9750298591 | F33: 18402563866 | H33: done | I33: Completed | K33: 3. Medium | L33: Alliances | M33: 45874 | O33: 45985 | Q33: Box | S33: Tim Kennedy
A34: Customerlist | B34: Open Items | C34: Smarty, LLC Board | D34: Smarty, LLC | E34: 9408382833 | F34: 18402567457 | I34: Ongoing | J34: Partner Alliances | K34: 2. High | L34: Pipeline | M34: 45826 | Q34: Smarty, LLC | S34: Tim Kennedy
A35: Dannon to provide training to GW Rev Team on how to update customer list. | B35: Completed Items | C35: Insurance Services Office (ISO) Board | D35: Insurance Services Office (ISO) | E35: 8608512676 | F35: 18402568111 | I35: Completed | K35: 3. Medium | L35: Contracts | M35: 45719 | O35: 46010 | Q35: Verisk | S35: Tim Kennedy
A36: Demo of Open Archive | B36: Open Items | C36: Open Text Corporation Board | D36: Open Text Corporation | E36: 11309490784 | F36: 18402565219 | I36: In Progress | K36: 3. Medium | L36: Alliances | M36: 46071 | N36: 46085 | Q36: Open Text Corporation | S36: Tim Kennedy
A37: Demo of their ECM Content Management solution | B37: Open Items | C37: Open Text Corporation Board | D37: Open Text Corporation | E37: 11309417699 | F37: 18402565219 | I37: In Progress | J37: Partner Alliances | K37: 3. Medium | L37: Accelerator | M37: 46071 | N37: 46085 | Q37: Open Text Corporation | S37: Tim Kennedy
A38: Dev Environment Upgrade to N | B38: Completed Items | C38: Whatfix Inc. Board | D38: Whatfix Inc. | E38: 8474092336 | F38: 18402568372 | H38: 12/4/24 Update: We are in the process of upgrading our GW instance to the Kufri version of Cloud, and this will be completed soon. Additionally, the version following Kufri, the Las Lenas version, is expected to be released shortly. If it becomes available soon, we plan to first upgrade to the Kufri version and then to Las Lenas. I'll update once we are done on this, as after that we can start the process to test and update the Accelerator version to Kufri on the GW Marketplace (-or Las lenas, if we update to that). | I38: Completed | K38: 1. Urgent | L38: NPE | M38: 45701 | O38: 45722 | Q38: Whatfix Inc. | S38: Tim Kennedy
A39: email on Cogniznant | B39: Completed Items | C39: Insurance Services Office (ISO) Board | D39: Insurance Services Office (ISO) | E39: 9433757764 | F39: 18402568111 | I39: Completed | K39: 5. N/A | L39: Alliances | M39: 45831 | O39: 46010 | Q39: Verisk | S39: Tim Kennedy
A40: Enablement Sessions for CSMs | B40: Open Items | C40: Newgen Software Inc. Board | D40: Newgen Software Inc. | E40: 9765924707 | F40: 18402565546 | I40: Not Started | J40: GW Alliances, Partner Alliances | K40: 2. High | L40: Alliances | M40: 45876 | Q40: Newgen Software Inc. | S40: Tim Kennedy
A41: End to end solution architecture diagram | B41: Completed Items | C41: Box Board | D41: Box | E41: 10750482927 | F41: 18402563866 | H41: We received this diagram from your EMEA team. Do you have something similar for claims and billing as well? Perhaps also a carrier facing version. The example I'm showing here seems to have a broker focus. | I41: Completed | K41: 3. Medium | L41: Alliances | M41: 46001 | O41: 46010 | Q41: Box | S41: Tim Kennedy
A42: Estimate for implementation claims datafill for Erie | B42: Open Items | C42: LexisNexis Risk Solutions Inc. Board | D42: LexisNexis Risk Solutions Inc. | E42: 18357829667 | F42: 18402564676 | H42: don't mention to Erie.. Lexis may pay it. | I42: In Progress | J42: GW Alliances | K42: 3. Medium | L42: Alliances | M42: 45966 | Q42: LexisNexis Risk Solutions Inc. | S42: Tim Kennedy
A43: Extension on Connection for submission | B43: Completed Items | C43: WTW Board | D43: WTW | E43: 8979345875 | F43: 18402568518 | I43: Completed | K43: 2. High | L43: Alliances | M43: 45769 | O43: 45867 | Q43: WTW | S43: Tim Kennedy
A44: Farmers | B44: Completed Items | C44: Whatfix Inc. Board | D44: Whatfix Inc. | E44: 8671124140 | F44: 18402568372 | H44: Call w/ Zac G on 3.11.25 to provide knowledge share of account with Whatfix. Whatfix to digest all of the information around strategy, customer pains, strategic initiatives and progress. Formulate a plan to reconnect with Zac to fold Whatfix into 1-2 90 day stakeholder plans to address key challenges by leveraging Whatfix | I44: Completed | K44: 3. Medium | L44: Pipeline | M44: 45727 | O44: 45896 | Q44: Whatfix Inc. | S44: Tim Kennedy
A45: Farmers | B45: Completed Items | C45: Box Board | D45: Box | E45: 18047300869 | F45: 18402563866 | I45: Completed | K45: 3. Medium | L45: Alliances | M45: 45925 | O45: 45985 | Q45: Box | S45: Tim Kennedy
A46: Find APAC Conferences Guidewire Sponsors | B46: Completed Items | C46: WTW Board | D46: WTW | E46: 8466008325 | F46: 18402568518 | H46: Looking for opportunities to do some joint marketing activities. | I46: Completed | K46: 2. High | L46: Marketing | M46: 45700 | N46: 45738 | O46: 45827 | Q46: WTW | S46: Tim Kennedy
A47: get agreement signed - submitted on May 13gth. | B47: Completed Items | C47: SS&C Blue Prism Board | D47: SS&C Blue Prism | E47: 9035221895 | F47: 18402563983 | H47: still pending. there was a typo | I47: Completed | K47: 3. Medium | L47: Alliances | M47: 45776 | O47: 46010 | Q47: Blue Prism | S47: Tim Kennedy
A48: Get Box in EAA program for AI | B48: Open Items | C48: Box Board | D48: Box | E48: 10707496520 | F48: 18402563866 | I48: In Progress | J48: GW Alliances | K48: 2. High | L48: Accelerator | M48: 45995 | N48: 46009 | Q48: Box | S48: Tim Kennedy
A49: Get Cloud Ammendment signed for NPE | B49: Open Items | C49: LexisNexis Risk Solutions Inc. Board | D49: LexisNexis Risk Solutions Inc. | E49: 8854269838 | F49: 18402564676 | H49: Need before we can review UK addendum | I49: In Progress | J49: Partner Alliances | K49: 3. Medium | L49: Contracts | M49: 45750 | N49: 45773 | Q49: LexisNexis Risk Solutions Inc. | S49: Tim Kennedy
A50: Get feedback on Agentic POC from AI Team | B50: Open Items | C50: Box Board | D50: Box | E50: 10707498827 | F50: 18402563866 | I50: In Progress | J50: GW Alliances | K50: 2. High | L50: Accelerator | M50: 45995 | N50: 46009 | Q50: Box | S50: Tim Kennedy
A51: Get list of EA customers on Open Telemetry | B51: Open Items | C51: Dynatrace LLC Board | D51: Dynatrace LLC | E51: 11342957634 | F51: 18402564263 | I51: In Progress | K51: 3. Medium | L51: Contracts | M51: 45880 | N51: 45894 | Q51: Dynatrace LLC | S51: Tim Kennedy
A52: Get resources trained for NPE | B52: Open Items | C52: Dynatrace LLC Board | D52: Dynatrace LLC | E52: 11342944680 | F52: 18402564263 | I52: In Progress | K52: 3. Medium | L52: Accelerator | M52: 45698 | Q52: Dynatrace LLC | S52: Tim Kennedy
A53: Get revshare doc from Whatfix | B53: Completed Items | C53: Whatfix Inc. Board | D53: Whatfix Inc. | E53: 9252092685 | F53: 18402568372 | I53: Completed | K53: 2. High | L53: Alliances | M53: 45805 | O53: 45852 | Q53: Whatfix Inc. | S53: Tim Kennedy
A54: Get slides for regional views of partners in a value chain... EMEA example | B54: Completed Items | C54: Box Board | D54: Box | E54: 10759894554 | F54: 18402563866 | I54: Completed | K54: 3. Medium | L54: Alliances | M54: 46002 | O54: 46010 | Q54: Box | S54: Tim Kennedy
A55: Get the ISCS acquisition doc signed. | B55: Completed Items | C55: LexisNexis Risk Solutions Inc. Board | D55: LexisNexis Risk Solutions Inc. | E55: 8576513615 | F55: 18402564676 | H55: Currently in for signature. Due in 5-7 days | I55: Completed | K55: 3. Medium | L55: Contracts | M55: 45714 | N55: 45721 | Q55: LexisNexis Risk Solutions Inc. | S55: Tim Kennedy
A56: Get update on Postal Fix and timeline | B56: Completed Items | C56: Smarty, LLC Board | D56: Smarty, LLC | E56: 8906923019 | F56: 18402567457 | H56: Early may with Mamoth release | I56: Completed | K56: 5. N/A | L56: Accelerator | M56: 45757 | O56: 46010 | Q56: Smarty, LLC | S56: Tim Kennedy
A57: Go to Market Planning | B57: Completed Items | C57: Whatfix Inc. Board | D57: Whatfix Inc. | E57: 9819767522 | F57: 18402568372 | H57: Tony has proposed meeting with Julie and WFX Marketing to discuss GTM planning for H2 25' - 2026 . | I57: Completed | K57: 2. High | L57: Marketing | M57: 45698 | O57: 45938 | Q57: Whatfix Inc. | S57: Tim Kennedy
A58: Great American - RFP for undewriting workbench | B58: Completed Items | C58: Newgen Software Inc. Board | D58: Newgen Software Inc. | E58: 8987299473 | F58: 18402565546 | H58: Pat McAllister - Martin Foy- Triangulation meeting with Cognizant | I58: Completed | K58: 5. N/A | L58: Alliances | M58: 45770 | Q58: Newgen Software Inc. | S58: Tim Kennedy
A59: Guidewire EMEA- Newgen Sales Enablement Session | B59: Completed Items | C59: Newgen Software Inc. Board | D59: Newgen Software Inc. | E59: 8720152187 | F59: 18402565546 | H59: Sales Enablement on 30th April | I59: Completed | K59: 2. High | L59: Alliances | M59: 45734 | Q59: Newgen Software Inc. | S59: Tim Kennedy
A60: Guidewire Newgen PwC Webinar | B60: Completed Items | C60: Newgen Software Inc. Board | D60: Newgen Software Inc. | E60: 8720140139 | F60: 18402565546 | H60: Recording on 18th July; Broadcast on 21st Aug | I60: Completed | J60: Partner Alliances, Partner Marketing | K60: 2. High | L60: Alliances | M60: 45698 | Q60: Newgen Software Inc. | S60: Tim Kennedy
A61: Guidewire Technical Demo (Policy + Claims) | B61: Completed Items | C61: Whatfix Inc. Board | D61: Whatfix Inc. | E61: 9849953482 | F61: 18402568372 | H61: As we are working with Zac on aligning CS value drivers that GW CS measures today , compared to user behavioral engagement metrics WFX measures today for Insurtech customers, WFX team is in need of seeing who could provide a demo to understand what the business processes are for end users across relevant workflows via GW applications. Need Tim's help to help set this up for WFX team | I61: Completed | K61: 3. Medium | L61: Marketing | M61: 45698 | O61: 45982 | Q61: Whatfix Inc. | S61: Tim Kennedy
A62: GW Blog Entry | B62: Open Items | C62: Mitchell International, Inc. Board | D62: Mitchell International, Inc. | E62: 11428999639 | F62: 18402617065 | H62: Work on a blog entry. Work on the CSG Accelerator - end of year. | I62: Not Started | J62: GW Alliances, Partner Alliances | K62: 3. Medium | L62: Marketing | M62: 45707 | N62: 46022 | S62: Tim Kennedy
A63: Highspot Featured Content | B63: Open Items | C63: Open Text Corporation Board | D63: Open Text Corporation | E63: 11309574346 | F63: 18402565219 | I63: Not Started | J63: GW Alliances, Partner Alliances | K63: 2. High | L63: Marketing | M63: 46071 | N63: 46085 | Q63: Open Text Corporation | S63: Tim Kennedy
A64: HX is doing a press release announcing their intent to build an integration to Duck Creek. | B64: Completed Items | C64: Hyperexponential Ltd Board | D64: Hyperexponential Ltd | E64: 8992809723 | F64: 18402564488 | I64: Completed | K64: 5. N/A | L64: Marketing | M64: 45770 | O64: 46001 | Q64: Hyperexponential Ltd | S64: Tim Kennedy
A65: ICBC | B65: Open Items | C65: SS&C Blue Prism Board | D65: SS&C Blue Prism | E65: 9269288306 | F65: 18402563983 | H65: having upgrade process problems. hearing they are having challenges migrating v9 to cloud and Accenture. may have follow up questions for me | I65: Not Started | K65: 3. Medium | L65: Alliances | M65: 45807 | Q65: Blue Prism | S65: Tim Kennedy
A66: ICBC signed | B66: Open Items | C66: SS&C Blue Prism Board | D66: SS&C Blue Prism | E66: 9800197993 | F66: 18402563983 | H66: Waiting until. migration is complete to engage after signing | I66: Ongoing | K66: 3. Medium | L66: Alliances | M66: 45881 | N66: 45895 | Q66: Blue Prism | S66: Tim Kennedy
A67: ICPEI | B67: Open Items | C67: Mitchell International, Inc. Board | D67: Mitchell International, Inc. | E67: 11428968160 | F67: 18402617065 | H67: Certificate issue - on top of jar files - this was resolved in the update on Feb 18th. | I67: In Progress | J67: GW Alliances, Partner Alliances | K67: 2. High | L67: Accelerator | M67: 46071 | S67: Tim Kennedy
A68: Indico alternative | B68: Completed Items | C68: Newgen Software Inc. Board | D68: Newgen Software Inc. | E68: 8987471009 | F68: 18402565546 | H68: book Partner Day in San Mateo - Partner Summit | I68: Completed | K68: 2. High | L68: Alliances | M68: 45698 | N68: 45843 | Q68: Newgen Software Inc. | S68: Tim Kennedy
A69: iNow integration - WTW | B69: Completed Items | C69: WTW Board | D69: WTW | E69: 8979293464 | F69: 18402568518 | H69: Kannampuzhayil Murali, Anoop (Cognizant) <anoopk.murali@cognizant.com> is the cognizant contact. Need a iNow customer to do this. | I69: Completed | J69: GW Alliances | K69: 3. Medium | L69: Accelerator | M69: 45769 | Q69: WTW | S69: Tim Kennedy
A70: Introduce account team for Radian to Box | B70: Completed Items | C70: Box Board | D70: Box | E70: 10731340390 | F70: 18402563866 | I70: Completed | K70: 3. Medium | L70: Alliances | M70: 45698 | O70: 46010 | Q70: Box | S70: Tim Kennedy
A71: investigate v10 | B71: Open Items | C71: SS&C Blue Prism Board | D71: SS&C Blue Prism | E71: 9985314102 | F71: 18402563983 | H71: we would need to get approval as we have a restriction agains V10 for Blue Prism | I71: Halted | K71: 5. N/A | L71: Alliances | M71: 45905 | N71: 46060 | Q71: Blue Prism | S71: Tim Kennedy
A72: Is there are Partner Enablement day in the US this year | B72: Completed Items | C72: LexisNexis Risk Solutions Inc. Board | D72: LexisNexis Risk Solutions Inc. | E72: 8576736658 | F72: 18402564676 | H72: Yes it will be the 2nd week of June | I72: Completed | K72: 4. Low | L72: Alliances | M72: 45714 | N72: 45722 | Q72: LexisNexis Risk Solutions Inc. | S72: Tim Kennedy
A73: Jack Morgenson - value consulting team | B73: Completed Items | C73: Whatfix Inc. Board | D73: Whatfix Inc. | E73: 8630454925 | F73: 18402568372 | I73: Completed | K73: 3. Medium | L73: Marketing | M73: 45698 | O73: 45722 | Q73: Whatfix Inc. | S73: Tim Kennedy
A74: Joint Webinar | B74: Completed Items | C74: Whatfix Inc. Board | D74: Whatfix Inc. | E74: 8741290653 | F74: 18402568372 | H74: Tony scheduled meeting on Wednesday 9/3 to discuss with Tim + GW Marketing (if required) | I74: Completed | K74: 3. Medium | L74: Marketing | M74: 45736 | O74: 45930 | Q74: Whatfix Inc. | S74: Tim Kennedy
A75: Leah is transitioning off the Accelerator team. New person is Cindy. Wants a meeting with GW | B75: Completed Items | C75: Insurance Services Office (ISO) Board | D75: Insurance Services Office (ISO) | E75: 9021275363 | F75: 18402568111 | H75: Wants to have a meeting to talk about problems with cloud accelerators and how we could do better. | I75: Completed | K75: 5. N/A | L75: Alliances | M75: 45775 | O75: 46010 | Q75: Verisk | S75: Tim Kennedy
A76: Lightspeed Auto Referral - 12 page document | B76: Open Items | C76: Insurance Services Office (ISO) Board | D76: Insurance Services Office (ISO) | E76: 8821335440 | F76: 18402568111 | I76: Not Started | K76: 3. Medium | L76: Marketing | M76: 45747 | Q76: Verisk | S76: Tim Kennedy
A77: marketing push - two Lightspeed solutions - | B77: Open Items | C77: Insurance Services Office (ISO) Board | D77: Insurance Services Office (ISO) | E77: 8821490085 | F77: 18402568111 | I77: Not Started | K77: 3. Medium | L77: Marketing | M77: 45747 | Q77: Verisk | S77: Tim Kennedy
A78: Marketplace Upgrade for Customer Procurement | B78: Completed Items | C78: Whatfix Inc. Board | D78: Whatfix Inc. | E78: 8741290634 | F78: 18402568372 | I78: Completed | K78: 3. Medium | L78: Sponsorship/Events | M78: 45736 | Q78: Whatfix Inc. | S78: Tim Kennedy
A79: Marketplace Video Recording | B79: Open Items | C79: Mitchell International, Inc. Board | D79: Mitchell International, Inc. | E79: 11428974127 | F79: 18402617065 | H79: Defer until we have a customer. | I79: Not Started | J79: Partner Alliances | K79: 3. Medium | L79: Marketing | M79: 46071 | S79: Tim Kennedy
A80: Meet with Patrick as he gets engaged | B80: Completed Items | C80: Hyperexponential Ltd Board | D80: Hyperexponential Ltd | E80: 8741572943 | F80: 18402564488 | I80: Completed | K80: 5. N/A | L80: Alliances | M80: 45722 | O80: 46010 | Q80: Hyperexponential Ltd | S80: Tim Kennedy
A81: Meeting in person with Zac | B81: Completed Items | C81: Whatfix Inc. Board | D81: Whatfix Inc. | E81: 9031521513 | F81: 18402568372 | H81: Target May 15 | I81: Completed | K81: 5. N/A | L81: Alliances | M81: 45776 | O81: 45896 | Q81: Whatfix Inc. | S81: Tim Kennedy
A82: Mercury - pending | B82: Completed Items | C82: Whatfix Inc. Board | D82: Whatfix Inc. | E82: 8630574030 | F82: 18402568372 | I82: Completed | K82: 3. Medium | L82: Pipeline | M82: 45721 | O82: 45896 | Q82: Whatfix Inc. | S82: Tim Kennedy
A83: Montana State Fund | B83: Completed Items | C83: Box Board | D83: Box | E83: 18047290615 | F83: 18402563866 | H83: Early customer migrating to the cloud. Met with Kennen | I83: Completed | K83: 3. Medium | L83: Alliances | M83: 45925 | O83: 46010 | Q83: Box | S83: Tim Kennedy
A84: Move NPE to Mamoth | B84: Completed Items | C84: WTW Board | D84: WTW | E84: 8906448460 | F84: 18402568518 | H84: working on the upgrade now. | I84: Completed | K84: 2. High | L84: Alliances | M84: 45757 | O84: 45769 | Q84: WTW | S84: Tim Kennedy
A85: Move to Premier | B85: Open Items | C85: WTW Board | D85: WTW | E85: 10672681065 | F85: 18402568518 | I85: In Progress | J85: GW Alliances | K85: 2. High | L85: Contracts | M85: 45992 | N85: 46053 | Q85: WTW | S85: Tim Kennedy
A86: MVR PA issue | B86: Open Items | C86: LexisNexis Risk Solutions Inc. Board | D86: LexisNexis Risk Solutions Inc. | E86: 9249912437 | F86: 18402564676 | H86: Lexis has denied us a contract change to share risk with customers | I86: Completed | J86: Partner Alliances | K86: 1. Urgent | L86: Accelerator | M86: 45748 | Q86: LexisNexis Risk Solutions Inc. | S86: Tim Kennedy
A87: N-2 compliance | B87: Completed Items | C87: Insurance Services Office (ISO) Board | D87: Insurance Services Office (ISO) | E87: 8821325027 | F87: 18402568111 | I87: Completed | K87: 5. N/A | L87: Alliances | M87: 45698 | O87: 46010 | Q87: Verisk | S87: Tim Kennedy
A88: Nationwide | B88: Completed Items | C88: AKUR8 Board | D88: AKUR8 | E88: 9920080769 | F88: 18402561158 | H88: may have some customers on rating, but not Nationwide | I88: Completed | K88: 3. Medium | L88: Alliances | M88: 45897 | O88: 46010 | Q88: Akur8 | S88: Tim Kennedy
A89: Nationwide | B89: Completed Items | C89: AKUR8 Board | D89: AKUR8 | E89: 9412600861 | F89: 18402561158 | I89: Completed | K89: 2. High | L89: Pipeline | M89: 45827 | O89: 46010 | Q89: Akur8 | S89: Tim Kennedy
A90: Need additional people added to partner portal | B90: Completed Items | C90: AKUR8 Board | D90: AKUR8 | E90: 8741568938 | F90: 18402561158 | I90: Completed | K90: 3. Medium | L90: Alliances | M90: 45722 | O90: 45827 | Q90: Akur8 | S90: Tim Kennedy
A91: need to do a go to market planning | B91: Completed Items | C91: WTW Board | D91: WTW | E91: 9819438330 | F91: 18402568518 | H91: focus | I91: Completed | K91: 3. Medium | L91: Marketing | M91: 45698 | Q91: WTW | S91: Tim Kennedy
A92: need to focus on getting word out in the US | B92: Open Items | C92: WTW Board | D92: WTW | E92: 9819423422 | F92: 18402568518 | H92: do some webinars. Deloitte is their auditor | I92: In Progress | K92: 3. Medium | L92: Alliances | M92: 45883 | N92: 46060 | Q92: WTW | S92: Tim Kennedy
A93: Need to get a purchase order for compliance payment for Verisk audit | B93: Open Items | C93: Insurance Services Office (ISO) Board | D93: Insurance Services Office (ISO) | E93: 8822033746 | F93: 18402568111 | I93: Not Started | J93: GW Alliances | K93: 2. High | L93: Contracts | M93: 45747 | Q93: Verisk | S93: Tim Kennedy
A94: Need to update accelerator and submit for cloud update | B94: Open Items | C94: AKUR8 Board | D94: AKUR8 | E94: 10808906008 | F94: 18402561158 | I94: In Progress | J94: Partner Alliances | K94: 1. Urgent | L94: Alliances | M94: 46009 | N94: 46025 | Q94: Akur8 | S94: Tim Kennedy
A95: Need to update accelerator version | B95: Open Items | C95: SS&C Blue Prism Board | D95: SS&C Blue Prism | E95: 11357008078 | F95: 18402563983 | H95: Ed to send me their pdf | I95: Not Started | K95: 5. N/A | L95: Alliances | M95: 46077 | N95: 46091 | Q95: Blue Prism | S95: Tim Kennedy
A96: New accelerator for Rating coming in 2026 | B96: Open Items | C96: AKUR8 Board | D96: AKUR8 | E96: 10808998140 | F96: 18402561158 | H96: Make sure you meet with Bhaskar and GTF to approve scope document BEFORE development begins | I96: Not Started | K96: 5. N/A | L96: Alliances | M96: 45698 | N96: 46137 | Q96: Akur8 | S96: Tim Kennedy
A97: New item | B97: Open Items | C97: Mitchell International, Inc. Board | D97: Mitchell International, Inc. | E97: 11428910202 | F97: 18402617065 | I97: Not Started | K97: 5. N/A | L97: Alliances | M97: 46083 | N97: 46097 | Q97: Indico Data Solutions, Inc. | S97: Tim Kennedy
A98: New item | B98: Open Items | C98: Perforce Software, Inc. Board | D98: Perforce Software, Inc. | E98: 11428910895 | F98: 18402616813 | I98: Not Started | K98: 5. N/A | L98: Alliances | M98: 46083 | N98: 46097 | Q98: Indico Data Solutions, Inc. | S98: Tim Kennedy
A99: New item | B99: Open Items | C99: Wilbur Solutions Pty Ltd Board | D99: Wilbur Solutions Pty Ltd | E99: 11427223504 | F99: 18402585657 | I99: Not Started | K99: 5. N/A | L99: Alliances | M99: 46083 | N99: 46097 | Q99: Indico Data Solutions, Inc. | S99: Rod Gowin
A100: New item | B100: Open Items | C100: Vertafore Agency Platform Board | D100: Vertafore Agency Platform | E100: 11427215449 | F100: 18402585523 | I100: Not Started | K100: 5. N/A | L100: Alliances | M100: 46083 | N100: 46097 | Q100: Indico Data Solutions, Inc. | S100: Eric Apse
...

Sheet GWMondayData
A1: =IFERROR(__xludf.DUMMYFUNCTION("QUERY({GW_PartnerManagementActivities!A:Z;GW_TechOpsActivities!A2:Z999;GW_MarketingActivities!A2:Z999;GW_MarketplaceActivities!A2:Z999}, ""SELECT * WHERE Col1 IS NOT NULL"", 1)"),"Item Name") -> Item Name | B1: =IFERROR(__xludf.DUMMYFUNCTION("""COMPUTED_VALUE"""),"Group") -> Group | C1: =IFERROR(__xludf.DUMMYFUNCTION("""COMPUTED_VALUE"""),"Board Name") -> Board Name | D1: =IFERROR(__xludf.DUMMYFUNCTION("""COMPUTED_VALUE"""),"Partner Name") -> Partner Name | E1: =IFERROR(__xludf.DUMMYFUNCTION("""COMPUTED_VALUE"""),"Monday Item ID") -> Monday Item ID | F1: =IFERROR(__xludf.DUMMYFUNCTION("""COMPUTED_VALUE"""),"Board ID") -> Board ID | G1: =IFERROR(__xludf.DUMMYFUNCTION("""COMPUTED_VALUE"""),"Activity Status") -> Activity Status | H1: =IFERROR(__xludf.DUMMYFUNCTION("""COMPUTED_VALUE"""),"Owner") -> Owner | I1: =IFERROR(__xludf.DUMMYFUNCTION("""COMPUTED_VALUE"""),"Assigned To") -> Assigned To | J1: =IFERROR(__xludf.DUMMYFUNCTION("""COMPUTED_VALUE"""),"Importance") -> Importance | K1: =IFERROR(__xludf.DUMMYFUNCTION("""COMPUTED_VALUE"""),"Activity Type") -> Activity Type | L1: =IFERROR(__xludf.DUMMYFUNCTION("""COMPUTED_VALUE"""),"Date Created") -> Date Created | M1: =IFERROR(__xludf.DUMMYFUNCTION("""COMPUTED_VALUE"""),"Date Due") -> Date Due | N1: =IFERROR(__xludf.DUMMYFUNCTION("""COMPUTED_VALUE"""),"Actual Completion") -> Actual Completion | O1: =IFERROR(__xludf.DUMMYFUNCTION("""COMPUTED_VALUE"""),"Files") -> Files | P1: =IFERROR(__xludf.DUMMYFUNCTION("""COMPUTED_VALUE"""),"Comments/Notes") -> Comments/Notes | Q1: =IFERROR(__xludf.DUMMYFUNCTION("""COMPUTED_VALUE"""),"Subitems") -> Subitems | R1: =IFERROR(__xludf.DUMMYFUNCTION("""COMPUTED_VALUE"""),"Tech Board Type") -> Tech Board Type | S1: =IFERROR(__xludf.DUMMYFUNCTION("""COMPUTED_VALUE"""),"Alliance Manager") -> Alliance Manager | T1: =IFERROR(__xludf.DUMMYFUNCTION("""COMPUTED_VALUE"""),"Alliance Manager") -> Alliance Manager | U1: =IFERROR(__xludf.DUMMYFUNCTION("""COMPUTED_VALUE"""),"") | V1: =IFERROR(__xludf.DUMMYFUNCTION("""COMPUTED_VALUE"""),"") | W1: =IFERROR(__xludf.DUMMYFUNCTION("""COMPUTED_VALUE"""),"") | X1: =IFERROR(__xludf.DUMMYFUNCTION("""COMPUTED_VALUE"""),"") | Y1: =IFERROR(__xludf.DUMMYFUNCTION("""COMPUTED_VALUE"""),"") | Z1: =IFERROR(__xludf.DUMMYFUNCTION("""COMPUTED_VALUE"""),"")
A2: =IFERROR(__xludf.DUMMYFUNCTION("""COMPUTED_VALUE"""),"another test again") -> another test again | B2: =IFERROR(__xludf.DUMMYFUNCTION("""COMPUTED_VALUE"""),"Open Items") -> Open Items | C2: =IFERROR(__xludf.DUMMYFUNCTION("""COMPUTED_VALUE"""),"Partner Management Activities") -> Partner Management Activities | E2: =IFERROR(__xludf.DUMMYFUNCTION("""COMPUTED_VALUE"""),1.1093054347E10) -> 11093054347 | F2: =IFERROR(__xludf.DUMMYFUNCTION("""COMPUTED_VALUE"""),9.791255941E9) -> 9791255941 | G2: =IFERROR(__xludf.DUMMYFUNCTION("""COMPUTED_VALUE"""),"In Progress") -> In Progress | H2: =IFERROR(__xludf.DUMMYFUNCTION("""COMPUTED_VALUE"""),"Eric Apse") -> Eric Apse | I2: =IFERROR(__xludf.DUMMYFUNCTION("""COMPUTED_VALUE"""),"Tim Kennedy") -> Tim Kennedy | J2: =IFERROR(__xludf.DUMMYFUNCTION("""COMPUTED_VALUE"""),"1. Urgent") -> 1. Urgent | K2: =IFERROR(__xludf.DUMMYFUNCTION("""COMPUTED_VALUE"""),"Referal") -> Referal | L2: =IFERROR(__xludf.DUMMYFUNCTION("""COMPUTED_VALUE"""),45698.0) -> 45698 | M2: =IFERROR(__xludf.DUMMYFUNCTION("""COMPUTED_VALUE"""),46028.0) -> 46028 | P2: =IFERROR(__xludf.DUMMYFUNCTION("""COMPUTED_VALUE"""),"just more test") -> just more test | R2: =IFERROR(__xludf.DUMMYFUNCTION("""COMPUTED_VALUE"""),"Partner Management Activities") -> Partner Management Activities
A3: =IFERROR(__xludf.DUMMYFUNCTION("""COMPUTED_VALUE"""),"Make sure your parter is certified asap") -> Make sure your parter is certified asap | B3: =IFERROR(__xludf.DUMMYFUNCTION("""COMPUTED_VALUE"""),"Open Items") -> Open Items | C3: =IFERROR(__xludf.DUMMYFUNCTION("""COMPUTED_VALUE"""),"Partner Management Activities") -> Partner Management Activities | E3: =IFERROR(__xludf.DUMMYFUNCTION("""COMPUTED_VALUE"""),1.0941024281E10) -> 10941024281 | F3: =IFERROR(__xludf.DUMMYFUNCTION("""COMPUTED_VALUE"""),9.791255941E9) -> 9791255941 | G3: =IFERROR(__xludf.DUMMYFUNCTION("""COMPUTED_VALUE"""),"In Progress") -> In Progress | H3: =IFERROR(__xludf.DUMMYFUNCTION("""COMPUTED_VALUE"""),"Eric Apse") -> Eric Apse | I3: =IFERROR(__xludf.DUMMYFUNCTION("""COMPUTED_VALUE"""),"Tim Kennedy") -> Tim Kennedy | J3: =IFERROR(__xludf.DUMMYFUNCTION("""COMPUTED_VALUE"""),"1. Urgent") -> 1. Urgent | K3: =IFERROR(__xludf.DUMMYFUNCTION("""COMPUTED_VALUE"""),"Partner Management") -> Partner Management | L3: =IFERROR(__xludf.DUMMYFUNCTION("""COMPUTED_VALUE"""),45698.0) -> 45698 | M3: =IFERROR(__xludf.DUMMYFUNCTION("""COMPUTED_VALUE"""),46036.0) -> 46036 | R3: =IFERROR(__xludf.DUMMYFUNCTION("""COMPUTED_VALUE"""),"Partner Management Activities") -> Partner Management Activities
A4: =IFERROR(__xludf.DUMMYFUNCTION("""COMPUTED_VALUE"""),"test") -> test | B4: =IFERROR(__xludf.DUMMYFUNCTION("""COMPUTED_VALUE"""),"Open Items") -> Open Items | C4: =IFERROR(__xludf.DUMMYFUNCTION("""COMPUTED_VALUE"""),"Partner Management Activities") -> Partner Management Activities | E4: =IFERROR(__xludf.DUMMYFUNCTION("""COMPUTED_VALUE"""),1.0809257698E10) -> 10809257698 | F4: =IFERROR(__xludf.DUMMYFUNCTION("""COMPUTED_VALUE"""),9.791255941E9) -> 9791255941 | G4: =IFERROR(__xludf.DUMMYFUNCTION("""COMPUTED_VALUE"""),"In Progress") -> In Progress | H4: =IFERROR(__xludf.DUMMYFUNCTION("""COMPUTED_VALUE"""),"Eric Apse") -> Eric Apse | I4: =IFERROR(__xludf.DUMMYFUNCTION("""COMPUTED_VALUE"""),"Tim Kennedy") -> Tim Kennedy | J4: =IFERROR(__xludf.DUMMYFUNCTION("""COMPUTED_VALUE"""),"5. N/A") -> 5. N/A | K4: =IFERROR(__xludf.DUMMYFUNCTION("""COMPUTED_VALUE"""),"TechAll Marketing") -> TechAll Marketing | L4: =IFERROR(__xludf.DUMMYFUNCTION("""COMPUTED_VALUE"""),45698.0) -> 45698 | M4: =IFERROR(__xludf.DUMMYFUNCTION("""COMPUTED_VALUE"""),46037.0) -> 46037 | R4: =IFERROR(__xludf.DUMMYFUNCTION("""COMPUTED_VALUE"""),"Partner Management Activities") -> Partner Management Activities
A5: =IFERROR(__xludf.DUMMYFUNCTION("""COMPUTED_VALUE"""),"test 2") -> test 2 | B5: =IFERROR(__xludf.DUMMYFUNCTION("""COMPUTED_VALUE"""),"Open Items") -> Open Items | C5: =IFERROR(__xludf.DUMMYFUNCTION("""COMPUTED_VALUE"""),"Partner Management Activities") -> Partner Management Activities | E5: =IFERROR(__xludf.DUMMYFUNCTION("""COMPUTED_VALUE"""),1.0813317258E10) -> 10813317258 | F5: =IFERROR(__xludf.DUMMYFUNCTION("""COMPUTED_VALUE"""),9.791255941E9) -> 9791255941 | G5: =IFERROR(__xludf.DUMMYFUNCTION("""COMPUTED_VALUE"""),"In Progress") -> In Progress | H5: =IFERROR(__xludf.DUMMYFUNCTION("""COMPUTED_VALUE"""),"Eric Apse") -> Eric Apse | I5: =IFERROR(__xludf.DUMMYFUNCTION("""COMPUTED_VALUE"""),"Tim Kennedy") -> Tim Kennedy | J5: =IFERROR(__xludf.DUMMYFUNCTION("""COMPUTED_VALUE"""),"1. Urgent") -> 1. Urgent | K5: =IFERROR(__xludf.DUMMYFUNCTION("""COMPUTED_VALUE"""),"Marketplace") -> Marketplace | L5: =IFERROR(__xludf.DUMMYFUNCTION("""COMPUTED_VALUE"""),45698.0) -> 45698 | M5: =IFERROR(__xludf.DUMMYFUNCTION("""COMPUTED_VALUE"""),46033.0) -> 46033 | R5: =IFERROR(__xludf.DUMMYFUNCTION("""COMPUTED_VALUE"""),"Partner Management Activities") -> Partner Management Activities
A6: =IFERROR(__xludf.DUMMYFUNCTION("""COMPUTED_VALUE"""),"test 3") -> test 3 | B6: =IFERROR(__xludf.DUMMYFUNCTION("""COMPUTED_VALUE"""),"Open Items") -> Open Items | C6: =IFERROR(__xludf.DUMMYFUNCTION("""COMPUTED_VALUE"""),"Partner Management Activities") -> Partner Management Activities | E6: =IFERROR(__xludf.DUMMYFUNCTION("""COMPUTED_VALUE"""),1.0813553846E10) -> 10813553846 | F6: =IFERROR(__xludf.DUMMYFUNCTION("""COMPUTED_VALUE"""),9.791255941E9) -> 9791255941 | G6: =IFERROR(__xludf.DUMMYFUNCTION("""COMPUTED_VALUE"""),"In Progress") -> In Progress | H6: =IFERROR(__xludf.DUMMYFUNCTION("""COMPUTED_VALUE"""),"Eric Apse") -> Eric Apse | I6: =IFERROR(__xludf.DUMMYFUNCTION("""COMPUTED_VALUE"""),"Tim Kennedy") -> Tim Kennedy | J6: =IFERROR(__xludf.DUMMYFUNCTION("""COMPUTED_VALUE"""),"1. Urgent") -> 1. Urgent | K6: =IFERROR(__xludf.DUMMYFUNCTION("""COMPUTED_VALUE"""),"TechAll Marketing") -> TechAll Marketing | L6: =IFERROR(__xludf.DUMMYFUNCTION("""COMPUTED_VALUE"""),45698.0) -> 45698 | M6: =IFERROR(__xludf.DUMMYFUNCTION("""COMPUTED_VALUE"""),46038.0) -> 46038 | R6: =IFERROR(__xludf.DUMMYFUNCTION("""COMPUTED_VALUE"""),"Partner Management Activities") -> Partner Management Activities
A7: =IFERROR(__xludf.DUMMYFUNCTION("""COMPUTED_VALUE"""),"test3 new") -> test3 new | B7: =IFERROR(__xludf.DUMMYFUNCTION("""COMPUTED_VALUE"""),"Open Items") -> Open Items | C7: =IFERROR(__xludf.DUMMYFUNCTION("""COMPUTED_VALUE"""),"Partner Management Activities") -> Partner Management Activities | E7: =IFERROR(__xludf.DUMMYFUNCTION("""COMPUTED_VALUE"""),1.0813549497E10) -> 10813549497 | F7: =IFERROR(__xludf.DUMMYFUNCTION("""COMPUTED_VALUE"""),9.791255941E9) -> 9791255941 | G7: =IFERROR(__xludf.DUMMYFUNCTION("""COMPUTED_VALUE"""),"Halted") -> Halted | H7: =IFERROR(__xludf.DUMMYFUNCTION("""COMPUTED_VALUE"""),"Eric Apse") -> Eric Apse | I7: =IFERROR(__xludf.DUMMYFUNCTION("""COMPUTED_VALUE"""),"Tim Kennedy") -> Tim Kennedy | J7: =IFERROR(__xludf.DUMMYFUNCTION("""COMPUTED_VALUE"""),"1. Urgent") -> 1. Urgent | K7: =IFERROR(__xludf.DUMMYFUNCTION("""COMPUTED_VALUE"""),"Marketplace") -> Marketplace | L7: =IFERROR(__xludf.DUMMYFUNCTION("""COMPUTED_VALUE"""),45698.0) -> 45698 | M7: =IFERROR(__xludf.DUMMYFUNCTION("""COMPUTED_VALUE"""),46038.0) -> 46038 | R7: =IFERROR(__xludf.DUMMYFUNCTION("""COMPUTED_VALUE"""),"Partner Management Activities") -> Partner Management Activities
A8: =IFERROR(__xludf.DUMMYFUNCTION("""COMPUTED_VALUE"""),"tim test") -> tim test | B8: =IFERROR(__xludf.DUMMYFUNCTION("""COMPUTED_VALUE"""),"Open Items") -> Open Items | C8: =IFERROR(__xludf.DUMMYFUNCTION("""COMPUTED_VALUE"""),"Partner Management Activities") -> Partner Management Activities | E8: =IFERROR(__xludf.DUMMYFUNCTION("""COMPUTED_VALUE"""),1.0819625182E10) -> 10819625182 | F8: =IFERROR(__xludf.DUMMYFUNCTION("""COMPUTED_VALUE"""),9.791255941E9) -> 9791255941 | G8: =IFERROR(__xludf.DUMMYFUNCTION("""COMPUTED_VALUE"""),"Blockers") -> Blockers | H8: =IFERROR(__xludf.DUMMYFUNCTION("""COMPUTED_VALUE"""),"Tim Kennedy") -> Tim Kennedy | I8: =IFERROR(__xludf.DUMMYFUNCTION("""COMPUTED_VALUE"""),"Tim Kennedy") -> Tim Kennedy | J8: =IFERROR(__xludf.DUMMYFUNCTION("""COMPUTED_VALUE"""),"1. Urgent") -> 1. Urgent | K8: =IFERROR(__xludf.DUMMYFUNCTION("""COMPUTED_VALUE"""),"Partner Management") -> Partner Management | L8: =IFERROR(__xludf.DUMMYFUNCTION("""COMPUTED_VALUE"""),45698.0) -> 45698 | M8: =IFERROR(__xludf.DUMMYFUNCTION("""COMPUTED_VALUE"""),46029.0) -> 46029 | P8: =IFERROR(__xludf.DUMMYFUNCTION("""COMPUTED_VALUE"""),"none") -> none | R8: =IFERROR(__xludf.DUMMYFUNCTION("""COMPUTED_VALUE"""),"Partner Management Activities") -> Partner Management Activities
A9: =IFERROR(__xludf.DUMMYFUNCTION("""COMPUTED_VALUE"""),"test") -> test | B9: =IFERROR(__xludf.DUMMYFUNCTION("""COMPUTED_VALUE"""),"Open Items") -> Open Items | C9: =IFERROR(__xludf.DUMMYFUNCTION("""COMPUTED_VALUE"""),"Tech Ops Activities") -> Tech Ops Activities | E9: =IFERROR(__xludf.DUMMYFUNCTION("""COMPUTED_VALUE"""),1.0813055615E10) -> 10813055615 | F9: =IFERROR(__xludf.DUMMYFUNCTION("""COMPUTED_VALUE"""),9.79127239E9) -> 9791272390 | G9: =IFERROR(__xludf.DUMMYFUNCTION("""COMPUTED_VALUE"""),"In Progress") -> In Progress | H9: =IFERROR(__xludf.DUMMYFUNCTION("""COMPUTED_VALUE"""),"Kayla Page") -> Kayla Page | I9: =IFERROR(__xludf.DUMMYFUNCTION("""COMPUTED_VALUE"""),"Tim Kennedy") -> Tim Kennedy | J9: =IFERROR(__xludf.DUMMYFUNCTION("""COMPUTED_VALUE"""),"1. Urgent") -> 1. Urgent | K9: =IFERROR(__xludf.DUMMYFUNCTION("""COMPUTED_VALUE"""),"Validation") -> Validation | L9: =IFERROR(__xludf.DUMMYFUNCTION("""COMPUTED_VALUE"""),45698.0) -> 45698 | M9: =IFERROR(__xludf.DUMMYFUNCTION("""COMPUTED_VALUE"""),46052.0) -> 46052 | P9: =IFERROR(__xludf.DUMMYFUNCTION("""COMPUTED_VALUE"""),"none") -> none | R9: =IFERROR(__xludf.DUMMYFUNCTION("""COMPUTED_VALUE"""),"Tech Ops Activities") -> Tech Ops Activities
A10: =IFERROR(__xludf.DUMMYFUNCTION("""COMPUTED_VALUE"""),"Test") -> Test | B10: =IFERROR(__xludf.DUMMYFUNCTION("""COMPUTED_VALUE"""),"Open Items") -> Open Items | C10: =IFERROR(__xludf.DUMMYFUNCTION("""COMPUTED_VALUE"""),"Marketplace Activities") -> Marketplace Activities | E10: =IFERROR(__xludf.DUMMYFUNCTION("""COMPUTED_VALUE"""),1.1092783913E10) -> 11092783913 | F10: =IFERROR(__xludf.DUMMYFUNCTION("""COMPUTED_VALUE"""),1.837501336E10) -> 18375013360 | G10: =IFERROR(__xludf.DUMMYFUNCTION("""COMPUTED_VALUE"""),"In Progress") -> In Progress | H10: =IFERROR(__xludf.DUMMYFUNCTION("""COMPUTED_VALUE"""),"Richard Pauly") -> Richard Pauly | I10: =IFERROR(__xludf.DUMMYFUNCTION("""COMPUTED_VALUE"""),"Tim Kennedy") -> Tim Kennedy | J10: =IFERROR(__xludf.DUMMYFUNCTION("""COMPUTED_VALUE"""),"1. Urgent") -> 1. Urgent | K10: =IFERROR(__xludf.DUMMYFUNCTION("""COMPUTED_VALUE"""),"Partner Management") -> Partner Management | L10: =IFERROR(__xludf.DUMMYFUNCTION("""COMPUTED_VALUE"""),45698.0) -> 45698 | M10: =IFERROR(__xludf.DUMMYFUNCTION("""COMPUTED_VALUE"""),46052.0) -> 46052 | P10: =IFERROR(__xludf.DUMMYFUNCTION("""COMPUTED_VALUE"""),"test") -> test | R10: =IFERROR(__xludf.DUMMYFUNCTION("""COMPUTED_VALUE"""),"Marketplace Activities") -> Marketplace Activities

Sheet GW_MarketplaceActivities
A1: Item Name | B1: Group | C1: Board Name | D1: Partner Name | E1: Monday Item ID | F1: Board ID | G1: Activity Status | H1: Owner | I1: Assigned To | J1: Importance | K1: Activity Type | L1: Date Created | M1: Date Due | N1: Actual Completion | O1: Files | P1: Comments/Notes | Q1: Subitems | R1: Tech Board Type | S1: Alliance Manager
A2: Test | B2: Open Items | C2: Marketplace Activities | E2: 11092783913 | F2: 18375013360 | G2: In Progress | H2: Richard Pauly | I2: Tim Kennedy | J2: 1. Urgent | K2: Partner Management | L2: 45698 | M2: 46052 | P2: test | R2: Marketplace Activities

Sheet MarketingApproval
A1: Item Name | B1: Group | C1: Board Name | D1: Partner Name | E1: Monday Item ID | F1: Board ID | G1: Subitems | H1: Event URL | I1: Priority | J1: Funding Type | K1: Overall Status | L1: AllianceManager | M1: Partner | N1: Requesting Department | O1: Cost | P1: Date and Location | Q1: Start Date | R1: Request Type | S1: Urgency | T1: Number of Meetings or Receptions | U1: Total Audience | V1: Expected Attendance | W1: Speaking Opportunity | X1: Justification Link | Y1: Brand Details | Z1: Create Date | AA1: Scope Document Public URL | AB1: Alliance Manager | AC1: Final Approval Date | AD1: Eric Decision | AE1: Marketing Decision | AF1: Will Decision | AG1: Scope Document Public URL | AH1: Alliance Manager
A2: Earnix 2026 Excelerate | B2: Incoming | C2: Marketing Events Approval Requests | D2: Marketing Team | E2: 9759595231 | F2: 9710279044 | I2: Priority 1 | J2: Partner Funding Request | K2: Submitted | L2: Tim Kennedy | M2: Earnix | N2: Partner Management | O2: 20000 | P2: London 2026 | Q2: 46280 | R2: Live Event | S2: Normal | T2: 4 | U2: 300 | V2: 300 | W2: No | Y2: Logo on a booth
A3: Live event for AWS | B3: Incoming | C3: Marketing Events Approval Requests | D3: Marketing Team | E3: 9779348217 | F3: 9710279044 | I3: Priority 1 | J3: Partner Funding Request | K3: Approved | N3: Partner Management | O3: 10000 | R3: Live Event | S3: Normal | Z3: 45877
A4: AAIS | B4: Incoming | C4: Marketing Events Approval Requests | D4: Marketing Team | E4: 9766632601 | F4: 9710279044 | H4: https://events.aaisonline.com/2025aaismaineventsponsorships/Opportunities | I4: Priority 1 | J4: Partner Funding Request | K4: Approved | L4: Aaron Shaw | M4: AAIS | N4: Partner Management | O4: 14000 | P4: April 6-8 ClearWater FLA | Q4: 45753 | R4: Live Event | S4: Normal | T4: 3 in total = 1 potential carrier (Insurors Indemnity) 2 vanguard prospects (FireFly + Adaptify), 1 existing partner(P*K) | U4: 300-400 | V4: 300 | W4: No | Y4: Table in the Exhibit Hall with Marketplace branding. Guidewire Corp logo during Keynote speaker and networking break sessions
A5: InsurtechLIVE Networking Event in Australia (Ketaki Padhye to complete) Approved via Will Murphy, leadership meeting, 12/19. | B5: Incoming | C5: Marketing Events Approval Requests | D5: Marketing Team | E5: 9766632719 | F5: 9710279044 | I5: Priority 1 | J5: Partner Funding Request | K5: Approved | L5: Ketaki Padehye | N5: Marketing | O5: 6050 | R5: Live Event | S5: Normal
A6: Workers Comp IV Pitch Day (with GIF or Insurtech Insights) | B6: Incoming | C6: Marketing Events Approval Requests | D6: Marketing Team | E6: 9766632803 | F6: 9710279044 | I6: Priority 1 | J6: Partner Funding Request | K6: Approved | L6: Eric Apse | N6: Marketing | O6: 25000 | P6: 40368 | Q6: 45847 | R6: Live Event | S6: Normal
A7: Nearmap Execitve Summit with GW Sponsor | B7: Incoming | C7: Marketing Events Approval Requests | D7: Marketing Team | E7: 9766632873 | F7: 9710279044 | I7: Priority 1 | J7: Partner Funding Request | K7: Approved | L7: Ketaki Padehye | M7: Nearmap US, Inc. | N7: Partner Management | O7: 22000 | R7: Live Event | S7: Normal
A8: APAC MYSU | B8: Incoming | C8: Marketing Events Approval Requests | D8: Marketing Team | E8: 9766632936 | F8: 9710279044 | I8: Priority 1 | J8: Partner Funding Request | K8: Approved | O8: 0 | R8: Live Event | S8: Normal
A9: Box Works | B9: Incoming | C9: Marketing Events Approval Requests | D9: Marketing Team | E9: 9766633017 | F9: 9710279044 | H9: BOX | I9: Priority 1 | J9: Partner Funding Request | K9: Approved | L9: Tim Kennedy | M9: Box | N9: Partner Management | O9: 5000 | P9: November 12 -13 , 2024 San Francisco, CA | Q9: 45973 | R9: Live Event | S9: Normal
A10: CoreLogic Customer Event | B10: Incoming | C10: Marketing Events Approval Requests | D10: Marketing Team | E10: 9766633088 | F10: 9710279044 | H10: CoreLogic | I10: Priority 1 | J10: Partner Funding Request | K10: Approved | L10: Tim Kennedy | M10: CoreLogic | N10: Partner Management | O10: 16000 | P10: March 23 -25, 2025 Los Angeles, CA (rescheduled) | Q10: 45739 | R10: Live Event | S10: Normal | U10: InsuranceSuite Customers | V10: 1200 | W10: No speaking role | Y10: Logo will appear on a booth
A11: Developer Summit + hackathon | B11: Incoming | C11: Marketing Events Approval Requests | D11: Marketing Team | E11: 9766633185 | F11: 9710279044 | I11: Priority 1 | J11: Partner Funding Request | K11: Approved | N11: Marketplace | O11: 80000 | R11: Live Event | S11: Normal
A12: Earnix | B12: Incoming | C12: Marketing Events Approval Requests | D12: Marketing Team | E12: 9766633269 | F12: 9710279044 | H12: https://www.excelerate.earnix.com/ | I12: Priority 1 | J12: Partner Funding Request | K12: Approved | L12: Tim Kennedy | M12: Earnix | N12: Partner Management | O12: 25000 | P12: September 25-26, 2024. London | Q12: 45925 | R12: Live Event | S12: Normal | U12: PolicyCenter and iNow customers | V12: 500 | W12: Christina Lucas is a keynote | Y12: Logo will appear on booth
A13: WTW - event pending | B13: Incoming | C13: Marketing Events Approval Requests | D13: Marketing Team | E13: 9766633364 | F13: 9710279044 | I13: Priority 3 | J13: Partner Funding Request | K13: Approved | L13: Tim Kennedy | M13: WTW | N13: Partner Management | O13: 0 | P13: London.. summer 2025 | Q13: 45809 | R13: Live Event | S13: Normal | V13: 500 | W13: No | Y13: None
A14: EMEA IV Pitch Day (with GIF or Insurtech Insights, London Markets) | B14: Incoming | C14: Marketing Events Approval Requests | D14: Marketing Team | E14: 9766633444 | F14: 9710279044 | I14: Priority 1 | J14: Partner Funding Request | K14: Approved | L14: Eric Apse | N14: Marketing | O14: 20000 | P14: June 26th | Q14: 45834 | R14: Live Event | S14: Normal
A15: EMEA Mid year sales update MYSU | B15: Incoming | C15: Marketing Events Approval Requests | D15: Marketing Team | E15: 9766633524 | F15: 9710279044 | I15: Priority 1 | J15: Partner Funding Request | K15: Approved | N15: Marketing | O15: 0 | R15: Live Event | S15: Normal
A16: Evolution IQ | B16: Incoming | C16: Marketing Events Approval Requests | D16: Marketing Team | E16: 9766633594 | F16: 9710279044 | H16: https://www.wcrinet.org/news/news_info/save-the-date-2025-wcri-issues-research-conference-march-6-7-in-phoenix-az | I16: Priority 1 | J16: Partner Funding Request | K16: Approved | L16: Gregg Rabenold | M16: EvolutionIQ | N16: Partner Management | O16: 5000 | P16: Workers Compensation Research Institute Conference, March 6- 7 Phoenix | Q16: 45722 | R16: Live Event | S16: Normal | T16: Dinner with 20 customers/prospects | U16: Joint customers and prospects | V16: 15 - 20 | W16: Dinners / social events around other EIQ or GW participting events | Y16: Sales pitch and networking
A17: Evolution IQ | B17: Incoming | C17: Marketing Events Approval Requests | D17: Marketing Team | E17: 9766633661 | F17: 9710279044 | H17: https://www.ncci.com/Articles/Pages/Insights-AIS-Save-the-Date-2025.aspx | I17: Priority 1 | J17: Partner Funding Request | K17: Approved | L17: Gregg Rabenold | M17: EvolutionIQ | N17: Partner Management | O17: 5000 | P17: National Council on Compensation Insurance, May 12 -13, 2025 | Q17: 45789 | R17: Live Event | S17: Normal | T17: Dinner with 20 customers/prospects | U17: Joint customers and prospects | V17: 15 - 20 | W17: Dinners / social events around other EIQ or GW participting events | Y17: Sales pitch and networking
A18: Evolution IQ | B18: Incoming | C18: Marketing Events Approval Requests | D18: Marketing Team | E18: 9766633725 | F18: 9710279044 | I18: Priority 1 | J18: Partner Funding Request | K18: Approved | L18: Gregg Rabenold | M18: EvolutionIQ | N18: Partner Management | O18: 5000 | P18: TBD - (NYC or Chicago) | R18: Live Event | S18: Normal | T18: Dinner with 20 customers/prospects | U18: Joint customers and prospects | V18: 15-20
A19: Executive Symposium | B19: Incoming | C19: Marketing Events Approval Requests | D19: Marketing Team | E19: 9766633791 | F19: 9710279044 | I19: Priority 1 | J19: Partner Funding Request | K19: Approved | N19: Marketing | O19: 0 | Q19: 45736 | R19: Live Event | S19: Normal
A20: Genesys | B20: Incoming | C20: Marketing Events Approval Requests | D20: Marketing Team | E20: 9766633845 | F20: 9710279044 | I20: Priority 1 | J20: Partner Funding Request | K20: Approved | L20: Gregg Rabenold | M20: Genesys Cloud Services, Inc. | N20: Partner Management | O20: 5000 | P20: TBD - working on co-marketing event ideas | R20: Live Event | S20: Normal
A21: Genesys conference | B21: Incoming | C21: Marketing Events Approval Requests | D21: Marketing Team | E21: 9766633917 | F21: 9710279044 | H21: https://www.genesys.com/xperience | I21: Priority 1 | J21: Partner Funding Request | K21: Approved | L21: Gregg Rabenold | M21: Genesys Cloud Services, Inc. | N21: Partner Management | O21: 20000 | P21: September 8-10 Nashville | Q21: 45908 | R21: Live Event | S21: Normal | U21: Joint customers and prospects | V21: 3000 (200 insurers) | W21: Panel speaking opportunity, Gregg R to participate | Y21: Small booth, banner and meeting recognition
A22: Insurtech (Las Vegas) - IV Pitch Day | B22: Incoming | C22: Marketing Events Approval Requests | D22: Marketing Team | E22: 9766633969 | F22: 9710279044 | I22: Priority 1 | J22: Partner Funding Request | K22: Approved | L22: Eric Apse | N22: Partner Management | O22: 30000 | R22: Live Event | S22: Normal
A23: Insurtech Hartford | B23: Incoming | C23: Marketing Events Approval Requests | D23: Marketing Team | E23: 9766634060 | F23: 9710279044 | I23: Priority 1 | J23: Partner Funding Request | K23: Approved | L23: Eric Apse | N23: Partner Management | O23: 5000 | R23: Live Event | S23: Normal
A24: Insurtech Innovators - Nordics | B24: Incoming | C24: Marketing Events Approval Requests | D24: Marketing Team | E24: 9766632612 | F24: 9710279044 | I24: Priority 1 | J24: Partner Funding Request | K24: Approved | N24: Marketing | R24: Live Event | S24: Normal
A25: Insurtech Insights London - Show Customer Marketplace | B25: Incoming | C25: Marketing Events Approval Requests | D25: Marketing Team | E25: 9766632692 | F25: 9710279044 | I25: Priority 1 | J25: Partner Funding Request | K25: Approved | L25: Eric Apse | N25: Marketing | R25: Live Event | S25: Normal
A26: Invoice Cloud / Guidewire | B26: Incoming | C26: Marketing Events Approval Requests | D26: Marketing Team | E26: 9766632771 | F26: 9710279044 | I26: Priority 1 | J26: Partner Funding Request | K26: Approved | L26: Kelly Clayton | N26: Partner Management | O26: 15000 | P26: 46249.792 | Q26: 45884 | R26: Live Event | S26: Normal | T26: Bourbon Tasting - Behind the barrel
A27: ITC Trade Show Vegas - Partner Recruitment | B27: Incoming | C27: Marketing Events Approval Requests | D27: Marketing Team | E27: 9766632892 | F27: 9710279044 | H27: https://vegas.insuretechconnect.com/ | I27: Priority 1 | J27: Partner Funding Request | K27: Approved | L27: Lisa Vingerhoet, Gregg Rabenold | N27: Marketing | O27: 44295 | P27: Las Vegas, 10/15- 10/17 | Q27: 45945 | R27: Live Event | S27: Normal | T27: Nearmap reception and EIQ
A28: IVANS | B28: Incoming | C28: Marketing Events Approval Requests | D28: Marketing Team | E28: 9766632957 | F28: 9710279044 | H28: Link | I28: Priority 1 | J28: Partner Funding Request | K28: Approved | L28: Gregg Rabenold | M28: Applied Systems Inc | N28: Partner Management | O28: 5000 | P28: Ivans Insuretech Boston May 15th | Q28: 45792 | R28: Live Event | S28: Normal | T28: Conference | U28: 3 - 500
A29: Marketplace Lunch and Learn (in planning) | B29: Incoming | C29: Marketing Events Approval Requests | D29: Marketing Team | E29: 9766633051 | F29: 9710279044 | I29: Priority 1 | J29: Partner Funding Request | K29: Approved | N29: Marketplace | R29: Live Event | S29: Normal
A30: One Inc Customer Conference | B30: Incoming | C30: Marketing Events Approval Requests | D30: Marketing Team | E30: 9766633144 | F30: 9710279044 | I30: Priority 1 | J30: Partner Funding Request | K30: Approved | L30: Lisa Vingerhoet | M30: One Inc | N30: Partner Management | O30: 50000 | P30: Marco Island, May 7-9 | Q30: 45784 | R30: Live Event | S30: Normal
A31: One Inc Masters Event | B31: Incoming | C31: Marketing Events Approval Requests | D31: Marketing Team | E31: 9766633218 | F31: 9710279044 | I31: Priority 1 | J31: Partner Funding Request | K31: Approved | L31: Lisa Vingerhoet | M31: One Inc | N31: Partner Management | O31: 74950 | P31: Augusta GA, April 7 - 13 | Q31: 45754 | R31: Live Event | S31: Normal | U31: Customer execs | V31: 10 customers - Chubb, PMA, West Bend, Aspire, The Hartford, TMHCC, EMC, Encova | W31: N/A
A32: Re:Invent Customer Dinner | B32: Incoming | C32: Marketing Events Approval Requests | D32: Marketing Team | E32: 9766633323 | F32: 9710279044 | I32: Priority 1 | J32: Partner Funding Request | K32: Approved | L32: Paul Harper | N32: Partner Management | R32: Live Event | S32: Normal
A33: Re:Invent Executive Track Dinner | B33: Incoming | C33: Marketing Events Approval Requests | D33: Marketing Team | E33: 9766633397 | F33: 9710279044 | I33: Priority 1 | J33: Partner Funding Request | K33: Approved | L33: Paul Harper | N33: Partner Management | R33: Live Event | S33: Normal
A34: Smart AMER | B34: Incoming | C34: Marketing Events Approval Requests | D34: Marketing Team | E34: 9766633454 | F34: 9710279044 | H34: https://www.smartcommunications.com/resources/events/innovate/ | I34: Priority 1 | J34: Partner Funding Request | K34: Approved | L34: Lisa Vingerhoet | M34: SmartComms LLC | N34: Partner Management | O34: 10000 | P34: New Orleans, April 23-25, 2025 | Q34: 45770 | R34: Live Event | S34: Normal | T34: 12 | U34: 150 | W34: Yes - Future of Claims break out to insurance attendees | Y34: Marketplace logo at the table and on all materials
A35: Smart Communications MDF 20K | B35: Incoming | C35: Marketing Events Approval Requests | D35: Marketing Team | E35: 9766633506 | F35: 9710279044 | I35: Priority 1 | J35: Partner Funding Request | K35: Approved | L35: Lisa Vingerhoet | M35: SmartComms LLC | N35: Partner Management | R35: Live Event | S35: Normal
A36: Smart EMEA | B36: Incoming | C36: Marketing Events Approval Requests | D36: Marketing Team | E36: 9766633578 | F36: 9710279044 | I36: Priority 1 | J36: Partner Funding Request | K36: Approved | L36: Lisa Vingerhoet | M36: SmartComms LLC | N36: Partner Management | O36: 4625 | P36: London, Sept 2025 | Q36: 45901 | R36: Live Event | S36: Normal
A37: Syngery / VPMOM Post Q4 (CKO) | B37: Incoming | C37: Marketing Events Approval Requests | D37: Marketing Team | E37: 9766633658 | F37: 9710279044 | I37: Priority 1 | J37: Partner Funding Request | K37: Approved | N37: Marketing | R37: Live Event | S37: Normal
A38: Verisk Claims | B38: Incoming | C38: Marketing Events Approval Requests | D38: Marketing Team | E38: 9766633718 | F38: 9710279044 | H38: https://events.verisk.com/event/4b92d2b7-71a6-4fcb-82ed-0a8a2938aa20/websitePage:97164067-80b9-419d-a1d4-5c44539aed43 | I38: Priority 1 | J38: Partner Funding Request | K38: Approved | L38: Tim Kennedy | M38: Insurance Services Office (ISO) | N38: Partner Management | O38: 15000 | P38: Salt Lake City. Feb 3-6 2025 | Q38: 45694 | R38: Live Event | S38: Normal | U38: Claimcenter and iNow customerws | V38: 800 | W38: none | Y38: Booth
A39: Insurtech Australia Gold Partner Sponsorship | B39: Incoming | C39: Marketing Events Approval Requests | D39: Marketing Team | E39: 9766633768 | F39: 9710279044 | H39: https://insurtechaustralia.org/ | I39: Priority 1 | J39: Partner Funding Request | K39: Approved | L39: Ketaki Padehye | N39: Marketing | P39: 12 months MEMBERSHIP | R39: Live Event | S39: Normal | U39: Insurtech Community and P&C Carriers in Australia and NZ | W39: TBD | Y39: 1. Facilitated Introductions to insurtech network 2. Exclusive invitations to IA Partner and Insurtech-only networking events 3. Promotion of partner event/s or initiative/s to IA networks 4. Priority for development of thought leadership contribution (articles, events, digital channels).
A40: CCC | B40: Incoming | C40: Marketing Events Approval Requests | D40: Marketing Team | E40: 9766633833 | F40: 9710279044 | I40: Priority 2 | J40: Partner Funding Request | K40: Approved | L40: Gregg Rabenold | M40: CCC Intelligent Solutions Inc | N40: Partner Management | O40: 15000 | P40: May 13 - 15, 2025 Frisco Texas | Q40: 45790 | R40: Live Event | S40: Normal | U40: InsuranceSuite Customers | V40: 2000 | W40: Gregg Rabenold speaking on panel during conference about ecosystems | Y40: Logo will appear on a booth
A41: GSAC | B41: Incoming | C41: Marketing Events Approval Requests | D41: Marketing Team | E41: 9766633885 | F41: 9710279044 | I41: Priority 2 | J41: Partner Funding Request | K41: Approved | N41: Marketing | R41: Live Event | S41: Normal
A42: GSAC/CAPS Professional Services Meeting | B42: Incoming | C42: Marketing Events Approval Requests | D42: Marketing Team | E42: 9766633932 | F42: 9710279044 | I42: Priority 2 | J42: Partner Funding Request | K42: Approved | N42: GSC | R42: Live Event | S42: Normal
A43: Marketplace Summit (in planning, possibly combine with InsurPitch) | B43: Incoming | C43: Marketing Events Approval Requests | D43: Marketing Team | E43: 9766633970 | F43: 9710279044 | I43: Priority 1 | J43: Partner Funding Request | K43: Approved | N43: Marketing | R43: Live Event | S43: Normal
A44: CIAB ILF (Council for Insurance Agents and Brokers) | B44: Incoming | C44: Marketing Events Approval Requests | D44: Marketing Team | E44: 9766632641 | F44: 9710279044 | I44: Priority 3 | J44: Partner Funding Request | K44: Approved | N44: Marketing | R44: Live Event | S44: Normal
A45: Connected Claims | B45: Incoming | C45: Marketing Events Approval Requests | D45: Marketing Team | E45: 9766632753 | F45: 9710279044 | I45: Priority 3 | J45: Partner Funding Request | K45: Approved | N45: Marketing | R45: Live Event | S45: Normal
A46: EMEA Paris Seller Enablement | B46: Incoming | C46: Marketing Events Approval Requests | D46: Marketing Team | E46: 9766632826 | F46: 9710279044 | I46: Priority 3 | J46: Partner Funding Request | K46: Approved | N46: Marketing | R46: Live Event | S46: Normal
A47: EMEA Regional Sales KO | B47: Incoming | C47: Marketing Events Approval Requests | D47: Marketing Team | E47: 9766634721 | F47: 9710279044 | I47: Priority 3 | J47: Partner Funding Request | K47: Approved | N47: Marketing | R47: Live Event | S47: Normal
A48: EMEA SI Partner Advisory | B48: Incoming | C48: Marketing Events Approval Requests | D48: Marketing Team | E48: 9766634986 | F48: 9710279044 | I48: Priority 3 | J48: Partner Funding Request | K48: Approved | N48: Marketing | R48: Live Event | S48: Normal
A49: NAMIC Management | B49: Incoming | C49: Marketing Events Approval Requests | D49: Marketing Team | E49: 9766635027 | F49: 9710279044 | I49: Priority 3 | J49: Partner Funding Request | K49: Approved | N49: Partner Management | R49: Live Event | S49: Normal
A50: National Insurance Conference of Canada | B50: Incoming | C50: Marketing Events Approval Requests | D50: Marketing Team | E50: 9766635081 | F50: 9710279044 | I50: Priority 3 | J50: Partner Funding Request | K50: Approved | N50: Partner Management | R50: Live Event | S50: Normal
A51: TinTech Power Lunch UK | B51: Incoming | C51: Marketing Events Approval Requests | D51: Marketing Team | E51: 9766635143 | F51: 9710279044 | I51: Priority 3 | J51: Partner Funding Request | K51: Approved | N51: Marketing | R51: Live Event | S51: Normal
A52: Auto Insurance Report Conf | B52: Incoming | C52: Marketing Events Approval Requests | D52: Marketing Team | E52: 9766635191 | F52: 9710279044 | I52: Priority 3 | J52: Partner Funding Request | K52: Approved | N52: Marketing | R52: Live Event | S52: Normal
A53: OnRamp | B53: Incoming | C53: Marketing Events Approval Requests | D53: Marketing Team | E53: 9766635238 | F53: 9710279044 | I53: Priority 3 | J53: Partner Funding Request | K53: Approved | L53: Eric Apse | N53: Partner Management | R53: Live Event | S53: Normal
A54: Cotality Interconnect 2026 - Headshot studio sponsor - $10,000 | B54: Incoming | C54: Marketing Events Approval Requests | D54: Marketing Team | E54: 10637627477 | F54: 9710279044 | H54: https://intrconnect.cotality.com/event/6924361e-50f7-40b7-8ed4-19f64208d9a4/intrconnect-26 | I54: Priority 2 | J54: Partner Funding Request | K54: Submitted | L54: Tim Kennedy | M54: CoreLogic | N54: Partner Management | O54: 10000 | P54: 46044 | Q54: 46044 | R54: Live Event | S54: Normal | U54: 2000 | W54: No | Y54: Headshot studio sponsor - We would have Guidewire branding on the headshot studio. Totality sponsored connections this year and there is strong hope for reciprocal support | Z54: 45986
A55: test 3 | B55: Incoming | C55: Marketing Events Approval Requests | D55: Marketing Team | E55: 10649866817 | F55: 9710279044 | I55: Priority 2 | J55: Partner Funding Request | K55: Submitted | L55: Tim Kennedy | M55: AKUR8 | N55: Marketplace | R55: Whitepaper or Customer Success | S55: Normal | Z55: 45987

Sheet AllianceManager
A1: =IFERROR(__xludf.DUMMYFUNCTION("IMPORTRANGE(""https://docs.google.com/spreadsheets/d/1hJgoW3KY2iQ6LAjhGfcTao8eYjfrSeosQFy_fL4Zo3Q/edit"", ""GWAllianceManager!A:Z"")"),"Manager") -> Manager | B1: =IFERROR(__xludf.DUMMYFUNCTION("""COMPUTED_VALUE"""),"Email") -> Email | C1: =IFERROR(__xludf.DUMMYFUNCTION("""COMPUTED_VALUE"""),"Title") -> Title
A2: =IFERROR(__xludf.DUMMYFUNCTION("""COMPUTED_VALUE"""),"Aaron Shaw") -> Aaron Shaw | B2: =IFERROR(__xludf.DUMMYFUNCTION("""COMPUTED_VALUE"""),"aashaw@guidewire.com") -> aashaw@guidewire.com | C2: =IFERROR(__xludf.DUMMYFUNCTION("""COMPUTED_VALUE"""),"Global Technology Alliance Manager") -> Global Technology Alliance Manager
A3: =IFERROR(__xludf.DUMMYFUNCTION("""COMPUTED_VALUE"""),"Aditi Kulkarni") -> Aditi Kulkarni | B3: =IFERROR(__xludf.DUMMYFUNCTION("""COMPUTED_VALUE"""),"adkulkarni@guidewire.com") -> adkulkarni@guidewire.com | C3: =IFERROR(__xludf.DUMMYFUNCTION("""COMPUTED_VALUE"""),"Partner Strategy, Programs, and Marketing Director") -> Partner Strategy, Programs, and Marketing Director
A4: =IFERROR(__xludf.DUMMYFUNCTION("""COMPUTED_VALUE"""),"Anne Scognamiglo") -> Anne Scognamiglo | B4: =IFERROR(__xludf.DUMMYFUNCTION("""COMPUTED_VALUE"""),"ascognamiglio@guidewire.com") -> ascognamiglio@guidewire.com | C4: =IFERROR(__xludf.DUMMYFUNCTION("""COMPUTED_VALUE"""),"Senior Alliance Manager, APAC") -> Senior Alliance Manager, APAC
A5: =IFERROR(__xludf.DUMMYFUNCTION("""COMPUTED_VALUE"""),"Ben Barker") -> Ben Barker | B5: =IFERROR(__xludf.DUMMYFUNCTION("""COMPUTED_VALUE"""),"bbarker@guidewire.com") -> bbarker@guidewire.com | C5: =IFERROR(__xludf.DUMMYFUNCTION("""COMPUTED_VALUE"""),"Global Consulting Alliances") -> Global Consulting Alliances
A6: =IFERROR(__xludf.DUMMYFUNCTION("""COMPUTED_VALUE"""),"Carolee Dagenais") -> Carolee Dagenais | B6: =IFERROR(__xludf.DUMMYFUNCTION("""COMPUTED_VALUE"""),"cdagenais@guidewire.com") -> cdagenais@guidewire.com | C6: =IFERROR(__xludf.DUMMYFUNCTION("""COMPUTED_VALUE"""),"Vice President Alliance Management") -> Vice President Alliance Management
A7: =IFERROR(__xludf.DUMMYFUNCTION("""COMPUTED_VALUE"""),"Corinna Lovan") -> Corinna Lovan | B7: =IFERROR(__xludf.DUMMYFUNCTION("""COMPUTED_VALUE"""),"clovan@guidewire.com") -> clovan@guidewire.com | C7: =IFERROR(__xludf.DUMMYFUNCTION("""COMPUTED_VALUE"""),"Partner Programs Operations Manager") -> Partner Programs Operations Manager
A8: =IFERROR(__xludf.DUMMYFUNCTION("""COMPUTED_VALUE"""),"Dariusz Debowczyk") -> Dariusz Debowczyk | B8: =IFERROR(__xludf.DUMMYFUNCTION("""COMPUTED_VALUE"""),"ddebowczyk@guidewire.com") -> ddebowczyk@guidewire.com | C8: =IFERROR(__xludf.DUMMYFUNCTION("""COMPUTED_VALUE"""),"Senior Director Partner Success") -> Senior Director Partner Success
A9: =IFERROR(__xludf.DUMMYFUNCTION("""COMPUTED_VALUE"""),"Eric Apse") -> Eric Apse | B9: =IFERROR(__xludf.DUMMYFUNCTION("""COMPUTED_VALUE"""),"eapse@guidewire.com") -> eapse@guidewire.com | C9: =IFERROR(__xludf.DUMMYFUNCTION("""COMPUTED_VALUE"""),"Senior Global Technology Alliance Director") -> Senior Global Technology Alliance Director
A10: =IFERROR(__xludf.DUMMYFUNCTION("""COMPUTED_VALUE"""),"Fatima Aoulagha-Bannou") -> Fatima Aoulagha-Bannou | B10: =IFERROR(__xludf.DUMMYFUNCTION("""COMPUTED_VALUE"""),"faoulagha@guidewire.com") -> faoulagha@guidewire.com | C10: =IFERROR(__xludf.DUMMYFUNCTION("""COMPUTED_VALUE"""),"Global Technology Alliances Partner Buisiness Development") -> Global Technology Alliances Partner Buisiness Development
A11: =IFERROR(__xludf.DUMMYFUNCTION("""COMPUTED_VALUE"""),"Gregg Rabenold") -> Gregg Rabenold | B11: =IFERROR(__xludf.DUMMYFUNCTION("""COMPUTED_VALUE"""),"grabenold@guidewire.com") -> grabenold@guidewire.com | C11: =IFERROR(__xludf.DUMMYFUNCTION("""COMPUTED_VALUE"""),"Senior Global Technology Alliance Manager") -> Senior Global Technology Alliance Manager
A12: =IFERROR(__xludf.DUMMYFUNCTION("""COMPUTED_VALUE"""),"Haleh Nakhai") -> Haleh Nakhai | B12: =IFERROR(__xludf.DUMMYFUNCTION("""COMPUTED_VALUE"""),"hnakhai@guidewire.com") -> hnakhai@guidewire.com | C12: =IFERROR(__xludf.DUMMYFUNCTION("""COMPUTED_VALUE"""),"Global Consulting Alliances") -> Global Consulting Alliances
A13: =IFERROR(__xludf.DUMMYFUNCTION("""COMPUTED_VALUE"""),"Ian Doyle") -> Ian Doyle | B13: =IFERROR(__xludf.DUMMYFUNCTION("""COMPUTED_VALUE"""),"idoyle@guidewire.com") -> idoyle@guidewire.com | C13: =IFERROR(__xludf.DUMMYFUNCTION("""COMPUTED_VALUE"""),"Director, Global Delivery") -> Director, Global Delivery
A14: =IFERROR(__xludf.DUMMYFUNCTION("""COMPUTED_VALUE"""),"J Giles") -> J Giles | B14: =IFERROR(__xludf.DUMMYFUNCTION("""COMPUTED_VALUE"""),"jgiles@guidewire.com") -> jgiles@guidewire.com | C14: =IFERROR(__xludf.DUMMYFUNCTION("""COMPUTED_VALUE"""),"Global Consulting Alliances") -> Global Consulting Alliances
A15: =IFERROR(__xludf.DUMMYFUNCTION("""COMPUTED_VALUE"""),"Jerin Puthuparampil") -> Jerin Puthuparampil | B15: =IFERROR(__xludf.DUMMYFUNCTION("""COMPUTED_VALUE"""),"jputhuparampil@guidewire.com") -> jputhuparampil@guidewire.com | C15: =IFERROR(__xludf.DUMMYFUNCTION("""COMPUTED_VALUE"""),"Director, Partner Success") -> Director, Partner Success
A16: =IFERROR(__xludf.DUMMYFUNCTION("""COMPUTED_VALUE"""),"Julie Higuchi") -> Julie Higuchi | B16: =IFERROR(__xludf.DUMMYFUNCTION("""COMPUTED_VALUE"""),"jhiguchi@guidewire.com") -> jhiguchi@guidewire.com | C16: =IFERROR(__xludf.DUMMYFUNCTION("""COMPUTED_VALUE"""),"Alliance Markets and Enablement Manager") -> Alliance Markets and Enablement Manager
A17: =IFERROR(__xludf.DUMMYFUNCTION("""COMPUTED_VALUE"""),"Karolina Kuczko") -> Karolina Kuczko | B17: =IFERROR(__xludf.DUMMYFUNCTION("""COMPUTED_VALUE"""),"kakuczko@guidewire.com") -> kakuczko@guidewire.com | C17: =IFERROR(__xludf.DUMMYFUNCTION("""COMPUTED_VALUE"""),"Global Consulting Alliances") -> Global Consulting Alliances
A18: =IFERROR(__xludf.DUMMYFUNCTION("""COMPUTED_VALUE"""),"Kayla Page") -> Kayla Page | B18: =IFERROR(__xludf.DUMMYFUNCTION("""COMPUTED_VALUE"""),"kapage@guidewire.com") -> kapage@guidewire.com | C18: =IFERROR(__xludf.DUMMYFUNCTION("""COMPUTED_VALUE"""),"Technology Operations Manager") -> Technology Operations Manager
A19: =IFERROR(__xludf.DUMMYFUNCTION("""COMPUTED_VALUE"""),"Kelly Clayton") -> Kelly Clayton | B19: =IFERROR(__xludf.DUMMYFUNCTION("""COMPUTED_VALUE"""),"kclayton@guidewire.com") -> kclayton@guidewire.com | C19: =IFERROR(__xludf.DUMMYFUNCTION("""COMPUTED_VALUE"""),"Senior Global Technology Alliance Manager") -> Senior Global Technology Alliance Manager
A20: =IFERROR(__xludf.DUMMYFUNCTION("""COMPUTED_VALUE"""),"Ketaki Padhye") -> Ketaki Padhye | B20: =IFERROR(__xludf.DUMMYFUNCTION("""COMPUTED_VALUE"""),"kpadhye@guidewire.com") -> kpadhye@guidewire.com | C20: =IFERROR(__xludf.DUMMYFUNCTION("""COMPUTED_VALUE"""),"Senior RegionalTechnology Alliance Manager") -> Senior RegionalTechnology Alliance Manager
A21: =IFERROR(__xludf.DUMMYFUNCTION("""COMPUTED_VALUE"""),"Leon Liberman") -> Leon Liberman | B21: =IFERROR(__xludf.DUMMYFUNCTION("""COMPUTED_VALUE"""),"lliberman@guidewire.com") -> lliberman@guidewire.com | C21: =IFERROR(__xludf.DUMMYFUNCTION("""COMPUTED_VALUE"""),"Global Technology Alliances Partner Sales Manager") -> Global Technology Alliances Partner Sales Manager
A22: =IFERROR(__xludf.DUMMYFUNCTION("""COMPUTED_VALUE"""),"Lisa Vingerhoet") -> Lisa Vingerhoet | B22: =IFERROR(__xludf.DUMMYFUNCTION("""COMPUTED_VALUE"""),"lvingerhoet@guidewire.com") -> lvingerhoet@guidewire.com | C22: =IFERROR(__xludf.DUMMYFUNCTION("""COMPUTED_VALUE"""),"Global Technology Alliance Partner Specialist") -> Global Technology Alliance Partner Specialist
A23: =IFERROR(__xludf.DUMMYFUNCTION("""COMPUTED_VALUE"""),"Lisa Walsh") -> Lisa Walsh | B23: =IFERROR(__xludf.DUMMYFUNCTION("""COMPUTED_VALUE"""),"lwalsh@guidewire.com") -> lwalsh@guidewire.com | C23: =IFERROR(__xludf.DUMMYFUNCTION("""COMPUTED_VALUE"""),"Group Vice President Global Alliances") -> Group Vice President Global Alliances
A24: =IFERROR(__xludf.DUMMYFUNCTION("""COMPUTED_VALUE"""),"Molly Black") -> Molly Black | B24: =IFERROR(__xludf.DUMMYFUNCTION("""COMPUTED_VALUE"""),"mblack@guidewire.com") -> mblack@guidewire.com | C24: =IFERROR(__xludf.DUMMYFUNCTION("""COMPUTED_VALUE"""),"Senior Director Partner Programs") -> Senior Director Partner Programs
A25: =IFERROR(__xludf.DUMMYFUNCTION("""COMPUTED_VALUE"""),"Nikko Lee") -> Nikko Lee | B25: =IFERROR(__xludf.DUMMYFUNCTION("""COMPUTED_VALUE"""),"nlee@guidewire.com") -> nlee@guidewire.com | C25: =IFERROR(__xludf.DUMMYFUNCTION("""COMPUTED_VALUE"""),"Partner Program Coordinator") -> Partner Program Coordinator
A26: =IFERROR(__xludf.DUMMYFUNCTION("""COMPUTED_VALUE"""),"Paul Harper") -> Paul Harper | B26: =IFERROR(__xludf.DUMMYFUNCTION("""COMPUTED_VALUE"""),"pharper@guidewire.com") -> pharper@guidewire.com | C26: =IFERROR(__xludf.DUMMYFUNCTION("""COMPUTED_VALUE"""),"Senior Global Technology Alliance Manager") -> Senior Global Technology Alliance Manager
A27: =IFERROR(__xludf.DUMMYFUNCTION("""COMPUTED_VALUE"""),"Regina Kean") -> Regina Kean | B27: =IFERROR(__xludf.DUMMYFUNCTION("""COMPUTED_VALUE"""),"rkean@guidewire.com") -> rkean@guidewire.com | C27: =IFERROR(__xludf.DUMMYFUNCTION("""COMPUTED_VALUE"""),"Global Consulting Alliances") -> Global Consulting Alliances
A28: =IFERROR(__xludf.DUMMYFUNCTION("""COMPUTED_VALUE"""),"Richard Pauly") -> Richard Pauly | B28: =IFERROR(__xludf.DUMMYFUNCTION("""COMPUTED_VALUE"""),"rpauly@guidewire.com") -> rpauly@guidewire.com | C28: =IFERROR(__xludf.DUMMYFUNCTION("""COMPUTED_VALUE"""),"Senior Director, Marketplace") -> Senior Director, Marketplace
A29: =IFERROR(__xludf.DUMMYFUNCTION("""COMPUTED_VALUE"""),"Richard Vahlhaus") -> Richard Vahlhaus | B29: =IFERROR(__xludf.DUMMYFUNCTION("""COMPUTED_VALUE"""),"rvahlhaus@guidewire.com") -> rvahlhaus@guidewire.com | C29: =IFERROR(__xludf.DUMMYFUNCTION("""COMPUTED_VALUE"""),"Global Consulting Alliances") -> Global Consulting Alliances
A30: =IFERROR(__xludf.DUMMYFUNCTION("""COMPUTED_VALUE"""),"Rod Gowin") -> Rod Gowin | B30: =IFERROR(__xludf.DUMMYFUNCTION("""COMPUTED_VALUE"""),"rgowin@guidewire.com") -> rgowin@guidewire.com | C30: =IFERROR(__xludf.DUMMYFUNCTION("""COMPUTED_VALUE"""),"Global Technology Alliance Manager") -> Global Technology Alliance Manager
A31: =IFERROR(__xludf.DUMMYFUNCTION("""COMPUTED_VALUE"""),"Shannon Spies") -> Shannon Spies | B31: =IFERROR(__xludf.DUMMYFUNCTION("""COMPUTED_VALUE"""),"syates@guidewire.com") -> syates@guidewire.com | C31: =IFERROR(__xludf.DUMMYFUNCTION("""COMPUTED_VALUE"""),"Global Technology Alliance Manager") -> Global Technology Alliance Manager
A32: =IFERROR(__xludf.DUMMYFUNCTION("""COMPUTED_VALUE"""),"Shyam Sundar Krovvidi") -> Shyam Sundar Krovvidi | B32: =IFERROR(__xludf.DUMMYFUNCTION("""COMPUTED_VALUE"""),"skrovvidi@guidewire.com") -> skrovvidi@guidewire.com | C32: =IFERROR(__xludf.DUMMYFUNCTION("""COMPUTED_VALUE"""),"Partner Success Manager") -> Partner Success Manager
A33: =IFERROR(__xludf.DUMMYFUNCTION("""COMPUTED_VALUE"""),"Steve Doss") -> Steve Doss | B33: =IFERROR(__xludf.DUMMYFUNCTION("""COMPUTED_VALUE"""),"sdoss@guidewire.com") -> sdoss@guidewire.com | C33: =IFERROR(__xludf.DUMMYFUNCTION("""COMPUTED_VALUE"""),"Global Consulting Alliances") -> Global Consulting Alliances
A34: =IFERROR(__xludf.DUMMYFUNCTION("""COMPUTED_VALUE"""),"Ted Ogrean") -> Ted Ogrean | B34: =IFERROR(__xludf.DUMMYFUNCTION("""COMPUTED_VALUE"""),"togrean@guidewire.com") -> togrean@guidewire.com | C34: =IFERROR(__xludf.DUMMYFUNCTION("""COMPUTED_VALUE"""),"Director, Marketplace Delivery") -> Director, Marketplace Delivery
A35: =IFERROR(__xludf.DUMMYFUNCTION("""COMPUTED_VALUE"""),"Tim Kennedy") -> Tim Kennedy | B35: =IFERROR(__xludf.DUMMYFUNCTION("""COMPUTED_VALUE"""),"tkennedy@guidewire.com") -> tkennedy@guidewire.com | C35: =IFERROR(__xludf.DUMMYFUNCTION("""COMPUTED_VALUE"""),"Director, Technology Alliances") -> Director, Technology Alliances
A36: =IFERROR(__xludf.DUMMYFUNCTION("""COMPUTED_VALUE"""),"Tony Rosati") -> Tony Rosati | B36: =IFERROR(__xludf.DUMMYFUNCTION("""COMPUTED_VALUE"""),"trosati@guidewire.com") -> trosati@guidewire.com | C36: =IFERROR(__xludf.DUMMYFUNCTION("""COMPUTED_VALUE"""),"Global Consulting Alliances") -> Global Consulting Alliances
A37: =IFERROR(__xludf.DUMMYFUNCTION("""COMPUTED_VALUE"""),"Vivienne Hoary") -> Vivienne Hoary | B37: =IFERROR(__xludf.DUMMYFUNCTION("""COMPUTED_VALUE"""),"vhoary@guidewire.com") -> vhoary@guidewire.com | C37: =IFERROR(__xludf.DUMMYFUNCTION("""COMPUTED_VALUE"""),"Technology Alliance Manager") -> Technology Alliance Manager
A38: =IFERROR(__xludf.DUMMYFUNCTION("""COMPUTED_VALUE"""),"Will Murphy") -> Will Murphy | B38: =IFERROR(__xludf.DUMMYFUNCTION("""COMPUTED_VALUE"""),"wmurphy@guidewire.com") -> wmurphy@guidewire.com | C38: =IFERROR(__xludf.DUMMYFUNCTION("""COMPUTED_VALUE"""),"VP Technology Alliances") -> VP Technology Alliances

Sheet TechAllianceManager
A1: =IFERROR(__xludf.DUMMYFUNCTION("IMPORTRANGE(""https://docs.google.com/spreadsheets/d/1oFbyWxkC8heYznfw1h4dnXBL4l2AX10e3McVtA5anLI/edit"", ""AllianceManagers!A:Z"")"),"Manager") -> Manager | B1: =IFERROR(__xludf.DUMMYFUNCTION("""COMPUTED_VALUE"""),"Email") -> Email | C1: =IFERROR(__xludf.DUMMYFUNCTION("""COMPUTED_VALUE"""),"Title") -> Title | D1: =IFERROR(__xludf.DUMMYFUNCTION("""COMPUTED_VALUE"""),"AuthRole") -> AuthRole | E1: =IFERROR(__xludf.DUMMYFUNCTION("""COMPUTED_VALUE"""),"Role") -> Role | F1: =IFERROR(__xludf.DUMMYFUNCTION("""COMPUTED_VALUE"""),"EmailAccess") -> EmailAccess | G1: =IFERROR(__xludf.DUMMYFUNCTION("""COMPUTED_VALUE"""),"ReturnName") -> ReturnName | H1: =IFERROR(__xludf.DUMMYFUNCTION("""COMPUTED_VALUE"""),"ReturnEmail") -> ReturnEmail | I1: =IFERROR(__xludf.DUMMYFUNCTION("""COMPUTED_VALUE"""),"Function") -> Function | J1: =IFERROR(__xludf.DUMMYFUNCTION("""COMPUTED_VALUE"""),"MondayBoards") -> MondayBoards | K1: =IFERROR(__xludf.DUMMYFUNCTION("""COMPUTED_VALUE"""),"MondayRole") -> MondayRole | L1: =IFERROR(__xludf.DUMMYFUNCTION("""COMPUTED_VALUE"""),"Reports") -> Reports | M1: =IFERROR(__xludf.DUMMYFUNCTION("""COMPUTED_VALUE"""),"UID") -> UID
A2: =IFERROR(__xludf.DUMMYFUNCTION("""COMPUTED_VALUE"""),"Aaron Shaw") -> Aaron Shaw | B2: =IFERROR(__xludf.DUMMYFUNCTION("""COMPUTED_VALUE"""),"aashaw@guidewire.com") -> aashaw@guidewire.com | C2: =IFERROR(__xludf.DUMMYFUNCTION("""COMPUTED_VALUE"""),"Global Technology Alliance Manager") -> Global Technology Alliance Manager | D2: =IFERROR(__xludf.DUMMYFUNCTION("""COMPUTED_VALUE"""),"BASIC") -> BASIC | E2: =IFERROR(__xludf.DUMMYFUNCTION("""COMPUTED_VALUE"""),"Director") -> Director | F2: =IFERROR(__xludf.DUMMYFUNCTION("""COMPUTED_VALUE"""),"AllianceManagerAccess") -> AllianceManagerAccess | G2: =IFERROR(__xludf.DUMMYFUNCTION("""COMPUTED_VALUE"""),"Aaron Shaw") -> Aaron Shaw | H2: =IFERROR(__xludf.DUMMYFUNCTION("""COMPUTED_VALUE"""),"aashaw@guidewire.com") -> aashaw@guidewire.com | I2: =IFERROR(__xludf.DUMMYFUNCTION("""COMPUTED_VALUE"""),"PartnerManagement") -> PartnerManagement | J2: =IFERROR(__xludf.DUMMYFUNCTION("""COMPUTED_VALUE"""),"MarketingCalendar, PartnerActivites, PartnerHealthHeatmap, PartnerManagement, SolutionOps, MarketingProjects, Marketplace") -> MarketingCalendar, PartnerActivites, PartnerHealthHeatmap, PartnerManagement, SolutionOps, MarketingProjects, Marketplace | K2: =IFERROR(__xludf.DUMMYFUNCTION("""COMPUTED_VALUE"""),"User") -> User | M2: =IFERROR(__xludf.DUMMYFUNCTION("""COMPUTED_VALUE"""),"88ab7c311bc011e2") -> 88ab7c311bc011e2
A3: =IFERROR(__xludf.DUMMYFUNCTION("""COMPUTED_VALUE"""),"Customer Success") -> Customer Success | B3: =IFERROR(__xludf.DUMMYFUNCTION("""COMPUTED_VALUE"""),"tkennedy@guidewire.com") -> tkennedy@guidewire.com | C3: =IFERROR(__xludf.DUMMYFUNCTION("""COMPUTED_VALUE"""),"Customer Success Team") -> Customer Success Team | D3: =IFERROR(__xludf.DUMMYFUNCTION("""COMPUTED_VALUE"""),"BASIC") -> BASIC | E3: =IFERROR(__xludf.DUMMYFUNCTION("""COMPUTED_VALUE"""),"Admin") -> Admin | F3: =IFERROR(__xludf.DUMMYFUNCTION("""COMPUTED_VALUE"""),"NoAccess") -> NoAccess | I3: =IFERROR(__xludf.DUMMYFUNCTION("""COMPUTED_VALUE"""),"GSC") -> GSC | J3: =IFERROR(__xludf.DUMMYFUNCTION("""COMPUTED_VALUE"""),"PartnerActivites, PartnerHealthHeatmap, PartnerManagement, SolutionOps, MarketingProjects, Marketplace") -> PartnerActivites, PartnerHealthHeatmap, PartnerManagement, SolutionOps, MarketingProjects, Marketplace | K3: =IFERROR(__xludf.DUMMYFUNCTION("""COMPUTED_VALUE"""),"User") -> User | M3: =IFERROR(__xludf.DUMMYFUNCTION("""COMPUTED_VALUE"""),"95f9bbab2bffe41a") -> 95f9bbab2bffe41a
A4: =IFERROR(__xludf.DUMMYFUNCTION("""COMPUTED_VALUE"""),"Delli Bhaskar Jagadeesan") -> Delli Bhaskar Jagadeesan | B4: =IFERROR(__xludf.DUMMYFUNCTION("""COMPUTED_VALUE"""),"djagadeesan@guidewire.com") -> djagadeesan@guidewire.com | C4: =IFERROR(__xludf.DUMMYFUNCTION("""COMPUTED_VALUE"""),"Principal Technology Evangelist") -> Principal Technology Evangelist | D4: =IFERROR(__xludf.DUMMYFUNCTION("""COMPUTED_VALUE"""),"BASIC") -> BASIC | E4: =IFERROR(__xludf.DUMMYFUNCTION("""COMPUTED_VALUE"""),"Admin") -> Admin | F4: =IFERROR(__xludf.DUMMYFUNCTION("""COMPUTED_VALUE"""),"NoAccess") -> NoAccess | I4: =IFERROR(__xludf.DUMMYFUNCTION("""COMPUTED_VALUE"""),"GSC") -> GSC | J4: =IFERROR(__xludf.DUMMYFUNCTION("""COMPUTED_VALUE"""),"PartnerActivites, PartnerHealthHeatmap, PartnerManagement, SolutionOps, MarketingProjects, Marketplace") -> PartnerActivites, PartnerHealthHeatmap, PartnerManagement, SolutionOps, MarketingProjects, Marketplace | K4: =IFERROR(__xludf.DUMMYFUNCTION("""COMPUTED_VALUE"""),"User") -> User | M4: =IFERROR(__xludf.DUMMYFUNCTION("""COMPUTED_VALUE"""),"231b6521c7488a5b") -> 231b6521c7488a5b
A5: =IFERROR(__xludf.DUMMYFUNCTION("""COMPUTED_VALUE"""),"Drew Birtwistle") -> Drew Birtwistle | B5: =IFERROR(__xludf.DUMMYFUNCTION("""COMPUTED_VALUE"""),"dbirtwistle@guidewire.com") -> dbirtwistle@guidewire.com | C5: =IFERROR(__xludf.DUMMYFUNCTION("""COMPUTED_VALUE"""),"Director Product Management Ecosystem") -> Director Product Management Ecosystem | D5: =IFERROR(__xludf.DUMMYFUNCTION("""COMPUTED_VALUE"""),"BASIC") -> BASIC | E5: =IFERROR(__xludf.DUMMYFUNCTION("""COMPUTED_VALUE"""),"Admin") -> Admin | F5: =IFERROR(__xludf.DUMMYFUNCTION("""COMPUTED_VALUE"""),"NoAccess") -> NoAccess | I5: =IFERROR(__xludf.DUMMYFUNCTION("""COMPUTED_VALUE"""),"PartnerManagement") -> PartnerManagement | J5: =IFERROR(__xludf.DUMMYFUNCTION("""COMPUTED_VALUE"""),"PartnerActivites, PartnerHealthHeatmap, PartnerManagement, SolutionOps, MarketingProjects, Marketplace") -> PartnerActivites, PartnerHealthHeatmap, PartnerManagement, SolutionOps, MarketingProjects, Marketplace | K5: =IFERROR(__xludf.DUMMYFUNCTION("""COMPUTED_VALUE"""),"User") -> User | M5: =IFERROR(__xludf.DUMMYFUNCTION("""COMPUTED_VALUE"""),"afb196cf6f0305ff") -> afb196cf6f0305ff
A6: =IFERROR(__xludf.DUMMYFUNCTION("""COMPUTED_VALUE"""),"Eric Apse") -> Eric Apse | B6: =IFERROR(__xludf.DUMMYFUNCTION("""COMPUTED_VALUE"""),"eapse@guidewire.com") -> eapse@guidewire.com | C6: =IFERROR(__xludf.DUMMYFUNCTION("""COMPUTED_VALUE"""),"Senior Global Technology Alliance Director") -> Senior Global Technology Alliance Director | D6: =IFERROR(__xludf.DUMMYFUNCTION("""COMPUTED_VALUE"""),"BASIC") -> BASIC | E6: =IFERROR(__xludf.DUMMYFUNCTION("""COMPUTED_VALUE"""),"Director") -> Director | F6: =IFERROR(__xludf.DUMMYFUNCTION("""COMPUTED_VALUE"""),"AllianceManagerAccess") -> AllianceManagerAccess | G6: =IFERROR(__xludf.DUMMYFUNCTION("""COMPUTED_VALUE"""),"Eric Apse") -> Eric Apse | H6: =IFERROR(__xludf.DUMMYFUNCTION("""COMPUTED_VALUE"""),"eapse@guidewire.com") -> eapse@guidewire.com | I6: =IFERROR(__xludf.DUMMYFUNCTION("""COMPUTED_VALUE"""),"PartnerManagement") -> PartnerManagement | J6: =IFERROR(__xludf.DUMMYFUNCTION("""COMPUTED_VALUE"""),"MarketingApprovals, 2026MarketingApprovals, MarketingCalendar, Activity Stats, PartnerActivites, PartnerHealthHeatmap, PartnerManagement, SolutionOps, Marketplace, MarketingProjects") -> MarketingApprovals, 2026MarketingApprovals, MarketingCalendar, Activity Stats, PartnerActivites, PartnerHealthHeatmap, PartnerManagement, SolutionOps, Marketplace, MarketingProjects | K6: =IFERROR(__xludf.DUMMYFUNCTION("""COMPUTED_VALUE"""),"SrDirector") -> SrDirector | L6: =IFERROR(__xludf.DUMMYFUNCTION("""COMPUTED_VALUE"""),"Aaron Shaw, Eric Apse, Fatima Aoulagha-Bannou, Gregg Rabenold, Kelly Clayton, Ketaki Padhye, Vivienne Hoary, Tim Kennedy, Shannon Spies, Rod Gowin, Paul Harper") -> Aaron Shaw, Eric Apse, Fatima Aoulagha-Bannou, Gregg Rabenold, Kelly Clayton, Ketaki Padhye, Vivienne Hoary, Tim Kennedy, Shannon Spies, Rod Gowin, Paul Harper | M6: =IFERROR(__xludf.DUMMYFUNCTION("""COMPUTED_VALUE"""),"0e8eac820dbd7ff2") -> 0e8eac820dbd7ff2
A7: =IFERROR(__xludf.DUMMYFUNCTION("""COMPUTED_VALUE"""),"Fatima Aoulagha-Bannou") -> Fatima Aoulagha-Bannou | B7: =IFERROR(__xludf.DUMMYFUNCTION("""COMPUTED_VALUE"""),"faoulagha@guidewire.com") -> faoulagha@guidewire.com | C7: =IFERROR(__xludf.DUMMYFUNCTION("""COMPUTED_VALUE"""),"Global Technology Alliances Partner Buisiness Development") -> Global Technology Alliances Partner Buisiness Development | D7: =IFERROR(__xludf.DUMMYFUNCTION("""COMPUTED_VALUE"""),"BASIC") -> BASIC | E7: =IFERROR(__xludf.DUMMYFUNCTION("""COMPUTED_VALUE"""),"Director") -> Director | F7: =IFERROR(__xludf.DUMMYFUNCTION("""COMPUTED_VALUE"""),"AllianceManagerAccess") -> AllianceManagerAccess | G7: =IFERROR(__xludf.DUMMYFUNCTION("""COMPUTED_VALUE"""),"Fatima Aoulagha-Bannou") -> Fatima Aoulagha-Bannou | H7: =IFERROR(__xludf.DUMMYFUNCTION("""COMPUTED_VALUE"""),"faoulagha@guidewire.com") -> faoulagha@guidewire.com | I7: =IFERROR(__xludf.DUMMYFUNCTION("""COMPUTED_VALUE"""),"PartnerManagement") -> PartnerManagement | J7: =IFERROR(__xludf.DUMMYFUNCTION("""COMPUTED_VALUE"""),"MarketingCalendar, PartnerActivites, PartnerHealthHeatmap, PartnerManagement, SolutionOps, MarketingProjects, Marketplace") -> MarketingCalendar, PartnerActivites, PartnerHealthHeatmap, PartnerManagement, SolutionOps, MarketingProjects, Marketplace | K7: =IFERROR(__xludf.DUMMYFUNCTION("""COMPUTED_VALUE"""),"Manager") -> Manager | L7: =IFERROR(__xludf.DUMMYFUNCTION("""COMPUTED_VALUE"""),"Vivienne Hoary") -> Vivienne Hoary | M7: =IFERROR(__xludf.DUMMYFUNCTION("""COMPUTED_VALUE"""),"cca315d1f6bf7e0d") -> cca315d1f6bf7e0d
A8: =IFERROR(__xludf.DUMMYFUNCTION("""COMPUTED_VALUE"""),"Ian Doyle") -> Ian Doyle | B8: =IFERROR(__xludf.DUMMYFUNCTION("""COMPUTED_VALUE"""),"idoyle@guidewire.com") -> idoyle@guidewire.com | C8: =IFERROR(__xludf.DUMMYFUNCTION("""COMPUTED_VALUE"""),"Director, Global Delivery") -> Director, Global Delivery | D8: =IFERROR(__xludf.DUMMYFUNCTION("""COMPUTED_VALUE"""),"BASIC") -> BASIC | E8: =IFERROR(__xludf.DUMMYFUNCTION("""COMPUTED_VALUE"""),"TechTeam") -> TechTeam | F8: =IFERROR(__xludf.DUMMYFUNCTION("""COMPUTED_VALUE"""),"NoAccess") -> NoAccess | I8: =IFERROR(__xludf.DUMMYFUNCTION("""COMPUTED_VALUE"""),"GSC") -> GSC | J8: =IFERROR(__xludf.DUMMYFUNCTION("""COMPUTED_VALUE"""),"PartnerActivites, PartnerHealthHeatmap, PartnerManagement, SolutionOps, MarketingProjects, Marketplace") -> PartnerActivites, PartnerHealthHeatmap, PartnerManagement, SolutionOps, MarketingProjects, Marketplace | K8: =IFERROR(__xludf.DUMMYFUNCTION("""COMPUTED_VALUE"""),"User") -> User | M8: =IFERROR(__xludf.DUMMYFUNCTION("""COMPUTED_VALUE"""),"695e072b07e2a274") -> 695e072b07e2a274
A9: =IFERROR(__xludf.DUMMYFUNCTION("""COMPUTED_VALUE"""),"Jay Grayson") -> Jay Grayson | B9: =IFERROR(__xludf.DUMMYFUNCTION("""COMPUTED_VALUE"""),"jgrayson@guidewire.com") -> jgrayson@guidewire.com | C9: =IFERROR(__xludf.DUMMYFUNCTION("""COMPUTED_VALUE"""),"VP Corporate Development") -> VP Corporate Development | D9: =IFERROR(__xludf.DUMMYFUNCTION("""COMPUTED_VALUE"""),"BASIC") -> BASIC | E9: =IFERROR(__xludf.DUMMYFUNCTION("""COMPUTED_VALUE"""),"Admin") -> Admin | F9: =IFERROR(__xludf.DUMMYFUNCTION("""COMPUTED_VALUE"""),"NoAccess") -> NoAccess | I9: =IFERROR(__xludf.DUMMYFUNCTION("""COMPUTED_VALUE"""),"PartnerManagement") -> PartnerManagement | J9: =IFERROR(__xludf.DUMMYFUNCTION("""COMPUTED_VALUE"""),"PartnerActivites, PartnerHealthHeatmap, PartnerManagement, SolutionOps, MarketingProjects, Marketplace") -> PartnerActivites, PartnerHealthHeatmap, PartnerManagement, SolutionOps, MarketingProjects, Marketplace | K9: =IFERROR(__xludf.DUMMYFUNCTION("""COMPUTED_VALUE"""),"User") -> User | M9: =IFERROR(__xludf.DUMMYFUNCTION("""COMPUTED_VALUE"""),"dfe1f6be2215de9c") -> dfe1f6be2215de9c
A10: =IFERROR(__xludf.DUMMYFUNCTION("""COMPUTED_VALUE"""),"Julie Higuchi") -> Julie Higuchi | B10: =IFERROR(__xludf.DUMMYFUNCTION("""COMPUTED_VALUE"""),"jhiguchi@guidewire.com") -> jhiguchi@guidewire.com | C10: =IFERROR(__xludf.DUMMYFUNCTION("""COMPUTED_VALUE"""),"Allliance Markets and Enablement Manager") -> Allliance Markets and Enablement Manager | D10: =IFERROR(__xludf.DUMMYFUNCTION("""COMPUTED_VALUE"""),"SUPERUSER") -> SUPERUSER | E10: =IFERROR(__xludf.DUMMYFUNCTION("""COMPUTED_VALUE"""),"Admin") -> Admin | F10: =IFERROR(__xludf.DUMMYFUNCTION("""COMPUTED_VALUE"""),"FullAccess") -> FullAccess | G10: =IFERROR(__xludf.DUMMYFUNCTION("""COMPUTED_VALUE"""),"Julie Higuchi") -> Julie Higuchi | H10: =IFERROR(__xludf.DUMMYFUNCTION("""COMPUTED_VALUE"""),"jhiguchi@guidewire.com") -> jhiguchi@guidewire.com | I10: =IFERROR(__xludf.DUMMYFUNCTION("""COMPUTED_VALUE"""),"Marketing") -> Marketing | J10: =IFERROR(__xludf.DUMMYFUNCTION("""COMPUTED_VALUE"""),"2026MarketingApprovals, MarketingCalendar, MarketingProjects, Activity Stats") -> 2026MarketingApprovals, MarketingCalendar, MarketingProjects, Activity Stats | K10: =IFERROR(__xludf.DUMMYFUNCTION("""COMPUTED_VALUE"""),"Admin") -> Admin | M10: =IFERROR(__xludf.DUMMYFUNCTION("""COMPUTED_VALUE"""),"295b3097d9516c38") -> 295b3097d9516c38
A11: =IFERROR(__xludf.DUMMYFUNCTION("""COMPUTED_VALUE"""),"Kayla Page") -> Kayla Page | B11: =IFERROR(__xludf.DUMMYFUNCTION("""COMPUTED_VALUE"""),"kapage@guidewire.com") -> kapage@guidewire.com | C11: =IFERROR(__xludf.DUMMYFUNCTION("""COMPUTED_VALUE"""),"Technology Alliances Operation Manager") -> Technology Alliances Operation Manager | D11: =IFERROR(__xludf.DUMMYFUNCTION("""COMPUTED_VALUE"""),"SUPERUSER") -> SUPERUSER | E11: =IFERROR(__xludf.DUMMYFUNCTION("""COMPUTED_VALUE"""),"Admin") -> Admin | F11: =IFERROR(__xludf.DUMMYFUNCTION("""COMPUTED_VALUE"""),"FullAccess") -> FullAccess | G11: =IFERROR(__xludf.DUMMYFUNCTION("""COMPUTED_VALUE"""),"Guidewire Technology Alliance Operations") -> Guidewire Technology Alliance Operations | H11: =IFERROR(__xludf.DUMMYFUNCTION("""COMPUTED_VALUE"""),"techallianceops@guidewire.com") -> techallianceops@guidewire.com | I11: =IFERROR(__xludf.DUMMYFUNCTION("""COMPUTED_VALUE"""),"TechOps") -> TechOps | J11: =IFERROR(__xludf.DUMMYFUNCTION("""COMPUTED_VALUE"""),"MarketingApprovals, 2026MarketingApprovals, MarketingCalendar, Activity Stats, PartnerActivites, PartnerHealthHeatmap, PartnerManagement, SolutionOps, Marketplace, MarketingProjects") -> MarketingApprovals, 2026MarketingApprovals, MarketingCalendar, Activity Stats, PartnerActivites, PartnerHealthHeatmap, PartnerManagement, SolutionOps, Marketplace, MarketingProjects | K11: =IFERROR(__xludf.DUMMYFUNCTION("""COMPUTED_VALUE"""),"Admin") -> Admin | M11: =IFERROR(__xludf.DUMMYFUNCTION("""COMPUTED_VALUE"""),"1e1bc3c1d1ae6adf") -> 1e1bc3c1d1ae6adf
A12: =IFERROR(__xludf.DUMMYFUNCTION("""COMPUTED_VALUE"""),"Kelly Clayton") -> Kelly Clayton | B12: =IFERROR(__xludf.DUMMYFUNCTION("""COMPUTED_VALUE"""),"kclayton@guidewire.com") -> kclayton@guidewire.com | C12: =IFERROR(__xludf.DUMMYFUNCTION("""COMPUTED_VALUE"""),"Senior Global Technology Alliance Manager") -> Senior Global Technology Alliance Manager | D12: =IFERROR(__xludf.DUMMYFUNCTION("""COMPUTED_VALUE"""),"BASIC") -> BASIC | E12: =IFERROR(__xludf.DUMMYFUNCTION("""COMPUTED_VALUE"""),"Director") -> Director | F12: =IFERROR(__xludf.DUMMYFUNCTION("""COMPUTED_VALUE"""),"AllianceManagerAccess") -> AllianceManagerAccess | G12: =IFERROR(__xludf.DUMMYFUNCTION("""COMPUTED_VALUE"""),"Kelly Clayton") -> Kelly Clayton | H12: =IFERROR(__xludf.DUMMYFUNCTION("""COMPUTED_VALUE"""),"kclayton@guidewire.com") -> kclayton@guidewire.com | I12: =IFERROR(__xludf.DUMMYFUNCTION("""COMPUTED_VALUE"""),"PartnerManagement") -> PartnerManagement | J12: =IFERROR(__xludf.DUMMYFUNCTION("""COMPUTED_VALUE"""),"MarketingCalendar, PartnerActivites, PartnerHealthHeatmap, PartnerManagement, SolutionOps, MarketingProjects, Marketplace") -> MarketingCalendar, PartnerActivites, PartnerHealthHeatmap, PartnerManagement, SolutionOps, MarketingProjects, Marketplace | K12: =IFERROR(__xludf.DUMMYFUNCTION("""COMPUTED_VALUE"""),"User") -> User | M12: =IFERROR(__xludf.DUMMYFUNCTION("""COMPUTED_VALUE"""),"aa281f57ec746c97") -> aa281f57ec746c97
A13: =IFERROR(__xludf.DUMMYFUNCTION("""COMPUTED_VALUE"""),"Ketaki Padhye") -> Ketaki Padhye | B13: =IFERROR(__xludf.DUMMYFUNCTION("""COMPUTED_VALUE"""),"kpadhye@guidewire.com") -> kpadhye@guidewire.com | C13: =IFERROR(__xludf.DUMMYFUNCTION("""COMPUTED_VALUE"""),"Senior RegionalTechnology Alliance Manager") -> Senior RegionalTechnology Alliance Manager | D13: =IFERROR(__xludf.DUMMYFUNCTION("""COMPUTED_VALUE"""),"BASIC") -> BASIC | E13: =IFERROR(__xludf.DUMMYFUNCTION("""COMPUTED_VALUE"""),"Director") -> Director | F13: =IFERROR(__xludf.DUMMYFUNCTION("""COMPUTED_VALUE"""),"NoAccess") -> NoAccess | I13: =IFERROR(__xludf.DUMMYFUNCTION("""COMPUTED_VALUE"""),"PartnerManagement") -> PartnerManagement | J13: =IFERROR(__xludf.DUMMYFUNCTION("""COMPUTED_VALUE"""),"PartnerActivites, PartnerHealthHeatmap, PartnerManagement, SolutionOps, MarketingProjects, Marketplace") -> PartnerActivites, PartnerHealthHeatmap, PartnerManagement, SolutionOps, MarketingProjects, Marketplace | K13: =IFERROR(__xludf.DUMMYFUNCTION("""COMPUTED_VALUE"""),"User") -> User | M13: =IFERROR(__xludf.DUMMYFUNCTION("""COMPUTED_VALUE"""),"eb731de2db50609b") -> eb731de2db50609b
A14: =IFERROR(__xludf.DUMMYFUNCTION("""COMPUTED_VALUE"""),"Kyle Strumberger") -> Kyle Strumberger | B14: =IFERROR(__xludf.DUMMYFUNCTION("""COMPUTED_VALUE"""),"kstrumberger@guidewire.com") -> kstrumberger@guidewire.com | C14: =IFERROR(__xludf.DUMMYFUNCTION("""COMPUTED_VALUE"""),"Marketplace Manager") -> Marketplace Manager | D14: =IFERROR(__xludf.DUMMYFUNCTION("""COMPUTED_VALUE"""),"BASIC") -> BASIC | E14: =IFERROR(__xludf.DUMMYFUNCTION("""COMPUTED_VALUE"""),"Admin") -> Admin | F14: =IFERROR(__xludf.DUMMYFUNCTION("""COMPUTED_VALUE"""),"NoAccess") -> NoAccess | I14: =IFERROR(__xludf.DUMMYFUNCTION("""COMPUTED_VALUE"""),"Marketplace") -> Marketplace | J14: =IFERROR(__xludf.DUMMYFUNCTION("""COMPUTED_VALUE"""),"PartnerActivites, PartnerHealthHeatmap, PartnerManagement, SolutionOps, MarketingProjects, Marketplace") -> PartnerActivites, PartnerHealthHeatmap, PartnerManagement, SolutionOps, MarketingProjects, Marketplace | K14: =IFERROR(__xludf.DUMMYFUNCTION("""COMPUTED_VALUE"""),"User") -> User | M14: =IFERROR(__xludf.DUMMYFUNCTION("""COMPUTED_VALUE"""),"1ce038729a591160") -> 1ce038729a591160
A15: =IFERROR(__xludf.DUMMYFUNCTION("""COMPUTED_VALUE"""),"Lisa Vingerhoet") -> Lisa Vingerhoet | B15: =IFERROR(__xludf.DUMMYFUNCTION("""COMPUTED_VALUE"""),"lvingerhoet@guidewire.com") -> lvingerhoet@guidewire.com | C15: =IFERROR(__xludf.DUMMYFUNCTION("""COMPUTED_VALUE"""),"Global Technology Alliance Partner Specialist") -> Global Technology Alliance Partner Specialist | D15: =IFERROR(__xludf.DUMMYFUNCTION("""COMPUTED_VALUE"""),"BASIC") -> BASIC | E15: =IFERROR(__xludf.DUMMYFUNCTION("""COMPUTED_VALUE"""),"Director") -> Director | F15: =IFERROR(__xludf.DUMMYFUNCTION("""COMPUTED_VALUE"""),"NoAccess") -> NoAccess | I15: =IFERROR(__xludf.DUMMYFUNCTION("""COMPUTED_VALUE"""),"TechOps") -> TechOps | J15: =IFERROR(__xludf.DUMMYFUNCTION("""COMPUTED_VALUE"""),"2026MarketingApprovals, MarketingCalendar, SolutionOps, PartnerHealthHeatmap") -> 2026MarketingApprovals, MarketingCalendar, SolutionOps, PartnerHealthHeatmap | K15: =IFERROR(__xludf.DUMMYFUNCTION("""COMPUTED_VALUE"""),"SrDirector") -> SrDirector | L15: =IFERROR(__xludf.DUMMYFUNCTION("""COMPUTED_VALUE"""),"Lisa Vingerhoet, Julie Higuchi") -> Lisa Vingerhoet, Julie Higuchi | M15: =IFERROR(__xludf.DUMMYFUNCTION("""COMPUTED_VALUE"""),"d21718d507b30af5") -> d21718d507b30af5
A16: =IFERROR(__xludf.DUMMYFUNCTION("""COMPUTED_VALUE"""),"Melinda Earlywine") -> Melinda Earlywine | B16: =IFERROR(__xludf.DUMMYFUNCTION("""COMPUTED_VALUE"""),"mearlywine@guidewire.com") -> mearlywine@guidewire.com | C16: =IFERROR(__xludf.DUMMYFUNCTION("""COMPUTED_VALUE"""),"Solution Alliance Markets Enablement Director") -> Solution Alliance Markets Enablement Director | D16: =IFERROR(__xludf.DUMMYFUNCTION("""COMPUTED_VALUE"""),"BASIC") -> BASIC | E16: =IFERROR(__xludf.DUMMYFUNCTION("""COMPUTED_VALUE"""),"Admin") -> Admin | F16: =IFERROR(__xludf.DUMMYFUNCTION("""COMPUTED_VALUE"""),"NoAccess") -> NoAccess | I16: =IFERROR(__xludf.DUMMYFUNCTION("""COMPUTED_VALUE"""),"Marketing") -> Marketing | J16: =IFERROR(__xludf.DUMMYFUNCTION("""COMPUTED_VALUE"""),"2026MarketingApprovals, MarketingCalendar, MarketingProjects") -> 2026MarketingApprovals, MarketingCalendar, MarketingProjects | K16: =IFERROR(__xludf.DUMMYFUNCTION("""COMPUTED_VALUE"""),"SrDirector") -> SrDirector | L16: =IFERROR(__xludf.DUMMYFUNCTION("""COMPUTED_VALUE"""),"Melinda Earlywine, Julie Higuchi") -> Melinda Earlywine, Julie Higuchi | M16: =IFERROR(__xludf.DUMMYFUNCTION("""COMPUTED_VALUE"""),"73ce1335862d099a") -> 73ce1335862d099a
A17: =IFERROR(__xludf.DUMMYFUNCTION("""COMPUTED_VALUE"""),"Nathan Ash") -> Nathan Ash | B17: =IFERROR(__xludf.DUMMYFUNCTION("""COMPUTED_VALUE"""),"naash@guidewire.com") -> naash@guidewire.com | C17: =IFERROR(__xludf.DUMMYFUNCTION("""COMPUTED_VALUE"""),"Channel and Partner Sales Manage") -> Channel and Partner Sales Manage | D17: =IFERROR(__xludf.DUMMYFUNCTION("""COMPUTED_VALUE"""),"BASIC") -> BASIC | E17: =IFERROR(__xludf.DUMMYFUNCTION("""COMPUTED_VALUE"""),"Admin") -> Admin | F17: =IFERROR(__xludf.DUMMYFUNCTION("""COMPUTED_VALUE"""),"NoAccess") -> NoAccess | I17: =IFERROR(__xludf.DUMMYFUNCTION("""COMPUTED_VALUE"""),"PartnerManagement") -> PartnerManagement | J17: =IFERROR(__xludf.DUMMYFUNCTION("""COMPUTED_VALUE"""),"MarketingCalendar, PartnerActivites, PartnerHealthHeatmap, PartnerManagement, SolutionOps, MarketingProjects, Marketplace") -> MarketingCalendar, PartnerActivites, PartnerHealthHeatmap, PartnerManagement, SolutionOps, MarketingProjects, Marketplace | K17: =IFERROR(__xludf.DUMMYFUNCTION("""COMPUTED_VALUE"""),"User") -> User | M17: =IFERROR(__xludf.DUMMYFUNCTION("""COMPUTED_VALUE"""),"2f25ef1e964e3554") -> 2f25ef1e964e3554
A18: =IFERROR(__xludf.DUMMYFUNCTION("""COMPUTED_VALUE"""),"Partner Marketing") -> Partner Marketing | B18: =IFERROR(__xludf.DUMMYFUNCTION("""COMPUTED_VALUE"""),"partnermarketing@guidewire.com") -> partnermarketing@guidewire.com | C18: =IFERROR(__xludf.DUMMYFUNCTION("""COMPUTED_VALUE"""),"Guidewire Partner Marketing") -> Guidewire Partner Marketing | D18: =IFERROR(__xludf.DUMMYFUNCTION("""COMPUTED_VALUE"""),"SUPERUSER") -> SUPERUSER | E18: =IFERROR(__xludf.DUMMYFUNCTION("""COMPUTED_VALUE"""),"Admin") -> Admin | F18: =IFERROR(__xludf.DUMMYFUNCTION("""COMPUTED_VALUE"""),"FullAccess") -> FullAccess | G18: =IFERROR(__xludf.DUMMYFUNCTION("""COMPUTED_VALUE"""),"Partner Marketing") -> Partner Marketing | H18: =IFERROR(__xludf.DUMMYFUNCTION("""COMPUTED_VALUE"""),"partnermarketing@guidewire.com") -> partnermarketing@guidewire.com | I18: =IFERROR(__xludf.DUMMYFUNCTION("""COMPUTED_VALUE"""),"Marketing") -> Marketing | J18: =IFERROR(__xludf.DUMMYFUNCTION("""COMPUTED_VALUE"""),"2026MarketingApprovals, MarketingCalendar, MarketingProjects, Activity Stats") -> 2026MarketingApprovals, MarketingCalendar, MarketingProjects, Activity Stats | K18: =IFERROR(__xludf.DUMMYFUNCTION("""COMPUTED_VALUE"""),"User") -> User | M18: =IFERROR(__xludf.DUMMYFUNCTION("""COMPUTED_VALUE"""),"3dbd9e0636d9bb37") -> 3dbd9e0636d9bb37
A19: =IFERROR(__xludf.DUMMYFUNCTION("""COMPUTED_VALUE"""),"Paul Harper") -> Paul Harper | B19: =IFERROR(__xludf.DUMMYFUNCTION("""COMPUTED_VALUE"""),"pharper@guidewire.com") -> pharper@guidewire.com | C19: =IFERROR(__xludf.DUMMYFUNCTION("""COMPUTED_VALUE"""),"Senior Global Technology Alliance Manager") -> Senior Global Technology Alliance Manager | D19: =IFERROR(__xludf.DUMMYFUNCTION("""COMPUTED_VALUE"""),"BASIC") -> BASIC | E19: =IFERROR(__xludf.DUMMYFUNCTION("""COMPUTED_VALUE"""),"Director") -> Director | F19: =IFERROR(__xludf.DUMMYFUNCTION("""COMPUTED_VALUE"""),"AllianceManagerAccess") -> AllianceManagerAccess | G19: =IFERROR(__xludf.DUMMYFUNCTION("""COMPUTED_VALUE"""),"Paul Harper") -> Paul Harper | H19: =IFERROR(__xludf.DUMMYFUNCTION("""COMPUTED_VALUE"""),"pharper@guidewire.com") -> pharper@guidewire.com | I19: =IFERROR(__xludf.DUMMYFUNCTION("""COMPUTED_VALUE"""),"PartnerManagement") -> PartnerManagement | J19: =IFERROR(__xludf.DUMMYFUNCTION("""COMPUTED_VALUE"""),"MarketingCalendar, PartnerActivites, PartnerHealthHeatmap, PartnerManagement, SolutionOps, MarketingProjects, Marketplace") -> MarketingCalendar, PartnerActivites, PartnerHealthHeatmap, PartnerManagement, SolutionOps, MarketingProjects, Marketplace | K19: =IFERROR(__xludf.DUMMYFUNCTION("""COMPUTED_VALUE"""),"User") -> User | M19: =IFERROR(__xludf.DUMMYFUNCTION("""COMPUTED_VALUE"""),"d8da4b00d2b07d08") -> d8da4b00d2b07d08
A20: =IFERROR(__xludf.DUMMYFUNCTION("""COMPUTED_VALUE"""),"Richard Pauly") -> Richard Pauly | B20: =IFERROR(__xludf.DUMMYFUNCTION("""COMPUTED_VALUE"""),"rpauly@guidewire.com") -> rpauly@guidewire.com | C20: =IFERROR(__xludf.DUMMYFUNCTION("""COMPUTED_VALUE"""),"Senior Director, Marketplace") -> Senior Director, Marketplace | D20: =IFERROR(__xludf.DUMMYFUNCTION("""COMPUTED_VALUE"""),"BASIC") -> BASIC | E20: =IFERROR(__xludf.DUMMYFUNCTION("""COMPUTED_VALUE"""),"Admin") -> Admin | F20: =IFERROR(__xludf.DUMMYFUNCTION("""COMPUTED_VALUE"""),"NoAccess") -> NoAccess | I20: =IFERROR(__xludf.DUMMYFUNCTION("""COMPUTED_VALUE"""),"Marketplace") -> Marketplace | J20: =IFERROR(__xludf.DUMMYFUNCTION("""COMPUTED_VALUE"""),"MarketingCalendar, PartnerActivites, PartnerHealthHeatmap, PartnerManagement, SolutionOps, MarketingProjects, Marketplace") -> MarketingCalendar, PartnerActivites, PartnerHealthHeatmap, PartnerManagement, SolutionOps, MarketingProjects, Marketplace | K20: =IFERROR(__xludf.DUMMYFUNCTION("""COMPUTED_VALUE"""),"SrDirector") -> SrDirector | L20: =IFERROR(__xludf.DUMMYFUNCTION("""COMPUTED_VALUE"""),"Richard Pauly, Kyle Strumberger") -> Richard Pauly, Kyle Strumberger | M20: =IFERROR(__xludf.DUMMYFUNCTION("""COMPUTED_VALUE"""),"385b4f34ff221df4") -> 385b4f34ff221df4
A21: =IFERROR(__xludf.DUMMYFUNCTION("""COMPUTED_VALUE"""),"Rod Gowin") -> Rod Gowin | B21: =IFERROR(__xludf.DUMMYFUNCTION("""COMPUTED_VALUE"""),"rgowin@guidewire.com") -> rgowin@guidewire.com | C21: =IFERROR(__xludf.DUMMYFUNCTION("""COMPUTED_VALUE"""),"Senior RegionalTechnology Alliance Manager") -> Senior RegionalTechnology Alliance Manager | D21: =IFERROR(__xludf.DUMMYFUNCTION("""COMPUTED_VALUE"""),"BASIC") -> BASIC | E21: =IFERROR(__xludf.DUMMYFUNCTION("""COMPUTED_VALUE"""),"Director") -> Director | F21: =IFERROR(__xludf.DUMMYFUNCTION("""COMPUTED_VALUE"""),"AllianceManagerAccess") -> AllianceManagerAccess | G21: =IFERROR(__xludf.DUMMYFUNCTION("""COMPUTED_VALUE"""),"Rod Gowin") -> Rod Gowin | H21: =IFERROR(__xludf.DUMMYFUNCTION("""COMPUTED_VALUE"""),"rgowin@guidewire.com") -> rgowin@guidewire.com | I21: =IFERROR(__xludf.DUMMYFUNCTION("""COMPUTED_VALUE"""),"PartnerManagement") -> PartnerManagement | J21: =IFERROR(__xludf.DUMMYFUNCTION("""COMPUTED_VALUE"""),"MarketingCalendar, PartnerActivites, PartnerHealthHeatmap, PartnerManagement, SolutionOps, MarketingProjects, Marketplace") -> MarketingCalendar, PartnerActivites, PartnerHealthHeatmap, PartnerManagement, SolutionOps, MarketingProjects, Marketplace | K21: =IFERROR(__xludf.DUMMYFUNCTION("""COMPUTED_VALUE"""),"User") -> User | M21: =IFERROR(__xludf.DUMMYFUNCTION("""COMPUTED_VALUE"""),"9779c13548002968") -> 9779c13548002968
A22: =IFERROR(__xludf.DUMMYFUNCTION("""COMPUTED_VALUE"""),"Rusty Gaynes") -> Rusty Gaynes | B22: =IFERROR(__xludf.DUMMYFUNCTION("""COMPUTED_VALUE"""),"rgaynes@guidewire.com") -> rgaynes@guidewire.com | C22: =IFERROR(__xludf.DUMMYFUNCTION("""COMPUTED_VALUE"""),"Senior Partner Sales Manager") -> Senior Partner Sales Manager | D22: =IFERROR(__xludf.DUMMYFUNCTION("""COMPUTED_VALUE"""),"BASIC") -> BASIC | E22: =IFERROR(__xludf.DUMMYFUNCTION("""COMPUTED_VALUE"""),"Admin") -> Admin | F22: =IFERROR(__xludf.DUMMYFUNCTION("""COMPUTED_VALUE"""),"NoAccess") -> NoAccess | I22: =IFERROR(__xludf.DUMMYFUNCTION("""COMPUTED_VALUE"""),"PartnerManagement") -> PartnerManagement | J22: =IFERROR(__xludf.DUMMYFUNCTION("""COMPUTED_VALUE"""),"PartnerActivites, PartnerHealthHeatmap, PartnerManagement, SolutionOps, MarketingProjects, Marketplace") -> PartnerActivites, PartnerHealthHeatmap, PartnerManagement, SolutionOps, MarketingProjects, Marketplace | K22: =IFERROR(__xludf.DUMMYFUNCTION("""COMPUTED_VALUE"""),"Admin") -> Admin | M22: =IFERROR(__xludf.DUMMYFUNCTION("""COMPUTED_VALUE"""),"c7b5fc8020aa24d3") -> c7b5fc8020aa24d3
A23: =IFERROR(__xludf.DUMMYFUNCTION("""COMPUTED_VALUE"""),"Shannon Spies") -> Shannon Spies | B23: =IFERROR(__xludf.DUMMYFUNCTION("""COMPUTED_VALUE"""),"syates@guidewire.com") -> syates@guidewire.com | C23: =IFERROR(__xludf.DUMMYFUNCTION("""COMPUTED_VALUE"""),"Global Technology Alliance Manager") -> Global Technology Alliance Manager | D23: =IFERROR(__xludf.DUMMYFUNCTION("""COMPUTED_VALUE"""),"BASIC") -> BASIC | E23: =IFERROR(__xludf.DUMMYFUNCTION("""COMPUTED_VALUE"""),"Director") -> Director | F23: =IFERROR(__xludf.DUMMYFUNCTION("""COMPUTED_VALUE"""),"AllianceManagerAccess") -> AllianceManagerAccess | G23: =IFERROR(__xludf.DUMMYFUNCTION("""COMPUTED_VALUE"""),"Shannon Spies") -> Shannon Spies | H23: =IFERROR(__xludf.DUMMYFUNCTION("""COMPUTED_VALUE"""),"syates@guidewire.com") -> syates@guidewire.com | I23: =IFERROR(__xludf.DUMMYFUNCTION("""COMPUTED_VALUE"""),"PartnerManagement") -> PartnerManagement | J23: =IFERROR(__xludf.DUMMYFUNCTION("""COMPUTED_VALUE"""),"MarketingCalendar, PartnerActivites, PartnerHealthHeatmap, PartnerManagement, SolutionOps, MarketingProjects, Marketplace") -> MarketingCalendar, PartnerActivites, PartnerHealthHeatmap, PartnerManagement, SolutionOps, MarketingProjects, Marketplace | K23: =IFERROR(__xludf.DUMMYFUNCTION("""COMPUTED_VALUE"""),"User") -> User | M23: =IFERROR(__xludf.DUMMYFUNCTION("""COMPUTED_VALUE"""),"36f60957efcf1e11") -> 36f60957efcf1e11
A24: =IFERROR(__xludf.DUMMYFUNCTION("""COMPUTED_VALUE"""),"Syed Ali") -> Syed Ali | B24: =IFERROR(__xludf.DUMMYFUNCTION("""COMPUTED_VALUE"""),"syali@guidewire.com ") -> syali@guidewire.com | D24: =IFERROR(__xludf.DUMMYFUNCTION("""COMPUTED_VALUE"""),"BASIC") -> BASIC | E24: =IFERROR(__xludf.DUMMYFUNCTION("""COMPUTED_VALUE"""),"TechTeam") -> TechTeam | F24: =IFERROR(__xludf.DUMMYFUNCTION("""COMPUTED_VALUE"""),"NoAccess") -> NoAccess | I24: =IFERROR(__xludf.DUMMYFUNCTION("""COMPUTED_VALUE"""),"GSC") -> GSC | J24: =IFERROR(__xludf.DUMMYFUNCTION("""COMPUTED_VALUE"""),"PartnerActivites, PartnerHealthHeatmap, PartnerManagement, SolutionOps, MarketingProjects, Marketplace") -> PartnerActivites, PartnerHealthHeatmap, PartnerManagement, SolutionOps, MarketingProjects, Marketplace | K24: =IFERROR(__xludf.DUMMYFUNCTION("""COMPUTED_VALUE"""),"User") -> User | M24: =IFERROR(__xludf.DUMMYFUNCTION("""COMPUTED_VALUE"""),"64fb8e2bf75fcfa8") -> 64fb8e2bf75fcfa8
A25: =IFERROR(__xludf.DUMMYFUNCTION("""COMPUTED_VALUE"""),"Ted Ogrean") -> Ted Ogrean | B25: =IFERROR(__xludf.DUMMYFUNCTION("""COMPUTED_VALUE"""),"togrean@guidewire.com") -> togrean@guidewire.com | C25: =IFERROR(__xludf.DUMMYFUNCTION("""COMPUTED_VALUE"""),"Director, Marketplace Delivery") -> Director, Marketplace Delivery | D25: =IFERROR(__xludf.DUMMYFUNCTION("""COMPUTED_VALUE"""),"BASIC") -> BASIC | E25: =IFERROR(__xludf.DUMMYFUNCTION("""COMPUTED_VALUE"""),"TechTeam") -> TechTeam | F25: =IFERROR(__xludf.DUMMYFUNCTION("""COMPUTED_VALUE"""),"NoAccess") -> NoAccess | I25: =IFERROR(__xludf.DUMMYFUNCTION("""COMPUTED_VALUE"""),"GSC") -> GSC | J25: =IFERROR(__xludf.DUMMYFUNCTION("""COMPUTED_VALUE"""),"PartnerActivites, PartnerHealthHeatmap, PartnerManagement, SolutionOps, MarketingProjects, Marketplace") -> PartnerActivites, PartnerHealthHeatmap, PartnerManagement, SolutionOps, MarketingProjects, Marketplace | K25: =IFERROR(__xludf.DUMMYFUNCTION("""COMPUTED_VALUE"""),"User") -> User | M25: =IFERROR(__xludf.DUMMYFUNCTION("""COMPUTED_VALUE"""),"790e00120dc92c11") -> 790e00120dc92c11
A26: =IFERROR(__xludf.DUMMYFUNCTION("""COMPUTED_VALUE"""),"Tim Kennedy") -> Tim Kennedy | B26: =IFERROR(__xludf.DUMMYFUNCTION("""COMPUTED_VALUE"""),"tkennedy@guidewire.com") -> tkennedy@guidewire.com | C26: =IFERROR(__xludf.DUMMYFUNCTION("""COMPUTED_VALUE"""),"Technology Alliance Director") -> Technology Alliance Director | D26: =IFERROR(__xludf.DUMMYFUNCTION("""COMPUTED_VALUE"""),"ADMIN") -> ADMIN | E26: =IFERROR(__xludf.DUMMYFUNCTION("""COMPUTED_VALUE"""),"Director") -> Director | F26: =IFERROR(__xludf.DUMMYFUNCTION("""COMPUTED_VALUE"""),"FullAccess") -> FullAccess | G26: =IFERROR(__xludf.DUMMYFUNCTION("""COMPUTED_VALUE"""),"Tim Kennedy") -> Tim Kennedy | H26: =IFERROR(__xludf.DUMMYFUNCTION("""COMPUTED_VALUE"""),"tkennedy@guidewire.com") -> tkennedy@guidewire.com | I26: =IFERROR(__xludf.DUMMYFUNCTION("""COMPUTED_VALUE"""),"PartnerManagement") -> PartnerManagement | J26: =IFERROR(__xludf.DUMMYFUNCTION("""COMPUTED_VALUE"""),"MarketingApprovals, 2026MarketingApprovals, MarketingCalendar, Activity Stats, PartnerActivites, PartnerHealthHeatmap, PartnerManagement, SolutionOps, Marketplace, MarketingProjects") -> MarketingApprovals, 2026MarketingApprovals, MarketingCalendar, Activity Stats, PartnerActivites, PartnerHealthHeatmap, PartnerManagement, SolutionOps, Marketplace, MarketingProjects | K26: =IFERROR(__xludf.DUMMYFUNCTION("""COMPUTED_VALUE"""),"SrDirector") -> SrDirector | L26: =IFERROR(__xludf.DUMMYFUNCTION("""COMPUTED_VALUE"""),"Aaron Shaw, Shannon Spies, Rod Gowin, Tim Kennedy") -> Aaron Shaw, Shannon Spies, Rod Gowin, Tim Kennedy | M26: =IFERROR(__xludf.DUMMYFUNCTION("""COMPUTED_VALUE"""),"95f9bbab2bffe41a") -> 95f9bbab2bffe41a
A27: =IFERROR(__xludf.DUMMYFUNCTION("""COMPUTED_VALUE"""),"Vivienne Hoary") -> Vivienne Hoary | B27: =IFERROR(__xludf.DUMMYFUNCTION("""COMPUTED_VALUE"""),"vhoary@guidewire.com") -> vhoary@guidewire.com | C27: =IFERROR(__xludf.DUMMYFUNCTION("""COMPUTED_VALUE"""),"Technology Alliance Manager") -> Technology Alliance Manager | D27: =IFERROR(__xludf.DUMMYFUNCTION("""COMPUTED_VALUE"""),"BASIC") -> BASIC | E27: =IFERROR(__xludf.DUMMYFUNCTION("""COMPUTED_VALUE"""),"Director") -> Director | F27: =IFERROR(__xludf.DUMMYFUNCTION("""COMPUTED_VALUE"""),"AllianceManagerAccess") -> AllianceManagerAccess | G27: =IFERROR(__xludf.DUMMYFUNCTION("""COMPUTED_VALUE"""),"Vivienne Hoary") -> Vivienne Hoary | H27: =IFERROR(__xludf.DUMMYFUNCTION("""COMPUTED_VALUE"""),"vhoary@guidewire.com") -> vhoary@guidewire.com | I27: =IFERROR(__xludf.DUMMYFUNCTION("""COMPUTED_VALUE"""),"PartnerManagement") -> PartnerManagement | J27: =IFERROR(__xludf.DUMMYFUNCTION("""COMPUTED_VALUE"""),"MarketingCalendar, PartnerActivites, PartnerHealthHeatmap, PartnerManagement, SolutionOps, MarketingProjects, Marketplace") -> MarketingCalendar, PartnerActivites, PartnerHealthHeatmap, PartnerManagement, SolutionOps, MarketingProjects, Marketplace | K27: =IFERROR(__xludf.DUMMYFUNCTION("""COMPUTED_VALUE"""),"User") -> User | M27: =IFERROR(__xludf.DUMMYFUNCTION("""COMPUTED_VALUE"""),"7b6f255a393e36ac") -> 7b6f255a393e36ac
A28: =IFERROR(__xludf.DUMMYFUNCTION("""COMPUTED_VALUE"""),"Will Murphy") -> Will Murphy | B28: =IFERROR(__xludf.DUMMYFUNCTION("""COMPUTED_VALUE"""),"wmurphy@guidewire.com") -> wmurphy@guidewire.com | C28: =IFERROR(__xludf.DUMMYFUNCTION("""COMPUTED_VALUE"""),"VP Technology Alliances") -> VP Technology Alliances | D28: =IFERROR(__xludf.DUMMYFUNCTION("""COMPUTED_VALUE"""),"BASIC") -> BASIC | E28: =IFERROR(__xludf.DUMMYFUNCTION("""COMPUTED_VALUE"""),"Admin") -> Admin | F28: =IFERROR(__xludf.DUMMYFUNCTION("""COMPUTED_VALUE"""),"NoAccess") -> NoAccess | I28: =IFERROR(__xludf.DUMMYFUNCTION("""COMPUTED_VALUE"""),"VP") -> VP | J28: =IFERROR(__xludf.DUMMYFUNCTION("""COMPUTED_VALUE"""),"MarketingCalendar, PartnerActivites, PartnerHealthHeatmap, PartnerManagement, SolutionOps, MarketingProjects, Marketplace, MarketingApprovals, 2026MarketingApprovals, Activity Stats") -> MarketingCalendar, PartnerActivites, PartnerHealthHeatmap, PartnerManagement, SolutionOps, MarketingProjects, Marketplace, MarketingApprovals, 2026MarketingApprovals, Activity Stats | K28: =IFERROR(__xludf.DUMMYFUNCTION("""COMPUTED_VALUE"""),"User") -> User | M28: =IFERROR(__xludf.DUMMYFUNCTION("""COMPUTED_VALUE"""),"384a8e96b7b15609") -> 384a8e96b7b15609

Sheet MondayDashboard
A1: Item | B1: Monday Item ID | C1: Board ID | D1: Subitems | E1: Summary of Partner Activities | F1: AllianceManager | G1: Temperature | H1: Engagement | I1: Status | J1: PartnerBoard | K1: CustomerBoard | L1: Files | M1: MarketingLevel | N1: Partner Name | O1: Alliance Manager
A2: Mitchell International, Inc. | B2: 11428906921 | C2: 8705508201 | F2: Tim Kennedy | G2: Green | H2: Active | I2: Activated | J2: 18402617065 | K2: 18402617066 | M2: High | N2: Mitchell International, Inc. | O2: Tim Kennedy
A3: Perforce Software, Inc. | B3: 11428896407 | C3: 8705508201 | F3: Tim Kennedy | G3: Green | H3: Active | I3: Activated | J3: 18402616813 | K3: 18402616815 | M3: Medium | N3: Perforce Software, Inc. | O3: Tim Kennedy
A4: Mitchell International, Inc. | B4: 11428442783 | C4: 8705508201 | F4: Tim Kennedy | G4: Green | H4: Very Active | I4: Activated | J4: 18402609254 | K4: 18402609253 | M4: High | N4: Mitchell International, Inc. | O4: Tim Kennedy
A5: Wilbur Solutions Pty Ltd | B5: 11427232980 | C5: 8705508201 | F5: Rod Gowin | G5: Green | H5: Occational | I5: Activated | J5: 18402585657 | K5: 18402585645 | M5: Medium | N5: Wilbur Solutions Pty Ltd | O5: Rod Gowin
A6: Vertafore Agency Platform | B6: 11427182266 | C6: 8705508201 | F6: Eric Apse | G6: Green | H6: Occational | I6: Activated | J6: 18402585523 | K6: 18402585524 | M6: Medium | N6: Vertafore Agency Platform | O6: Eric Apse
A7: Roots Automation, Inc. | B7: 11427193258 | C7: 8705508201 | F7: Aaron Shaw | G7: Green | H7: Occational | I7: Activated | J7: 18402585265 | K7: 18402585264 | M7: Medium | N7: Roots Automation, Inc. | O7: Aaron Shaw
A8: Risk Control Technologies Inc. | B8: 11427185074 | C8: 8705508201 | F8: Rod Gowin | G8: Green | H8: Occational | I8: Activated | J8: 18402585089 | K8: 18402585090 | M8: Medium | N8: Risk Control Technologies Inc. | O8: Rod Gowin
A9: Quantexa Limited | B9: 11426988576 | C9: 8705508201 | F9: Vivienne Hoary | G9: Green | H9: Occational | I9: Activated | J9: 18402582976 | K9: 18402582978 | M9: Medium | N9: Quantexa Limited | O9: Vivienne Hoary
A10: Paymentus | B10: 11426987836 | C10: 8705508201 | F10: Shannon Spies | G10: Green | H10: Occational | I10: Activated | J10: 18402581254 | K10: 18402581255 | M10: Medium | N10: Paymentus | O10: Shannon Spies
A11: OneSpan Canada Inc. (VASCO eSignLive) | B11: 11426990728 | C11: 8705508201 | F11: Lisa Vingerhoet | G11: Green | H11: Occational | I11: Activated | J11: 18402581135 | K11: 18402581140 | M11: Medium | N11: OneSpan Canada Inc. (VASCO eSignLive) | O11: Lisa Vingerhoet
A12: ODG by MCG Health | B12: 11426974881 | C12: 8705508201 | F12: Eric Apse | G12: Green | H12: Occational | I12: Activated | J12: 18402581058 | K12: 18402581059 | M12: Medium | N12: ODG by MCG Health | O12: Eric Apse
A13: Nation Safe Drivers | B13: 11426968980 | C13: 8705508201 | F13: Rod Gowin | G13: Green | H13: Occational | I13: Activated | J13: 18402580968 | K13: 18402581007 | M13: Medium | N13: Nation Safe Drivers | O13: Rod Gowin
... A28: Belron Canada | B28: 11426488337 | C28: 8705508201 | F28: Rod Gowin | G28: Green | H28: Occational | I28: Activated | J28: 18402578450 | K28: 18402578447 | M28: Medium | N28: Belron Canada | O28: Rod Gowin
A29: WTW | B29: 11426283116 | C29: 8705508201 | E29: Quite happy generally. Not seeing huge traction with downloads or customer connections. Need to do more to support and promote | F29: Tim Kennedy | G29: Green | H29: Active | I29: Activated | J29: 18402568518 | K29: 18402568520 | M29: High | N29: WTW | O29: Tim Kennedy
A30: Whatfix Inc. | B30: 11426277710 | C30: 8705508201 | E30: Company made major cuts due to earnings miss and gutted their alliance program down to two people. Very good traction with Guidewire custmers | F30: Tim Kennedy | G30: Green | H30: Very Active | I30: Activated | J30: 18402568372 | K30: 18402568373 | M30: High | N30: Whatfix Inc. | O30: Tim Kennedy
A31: Verisk | B31: 11426251754 | C31: 8705508201 | E31: 42 Accelerators. Huge footprint | F31: Tim Kennedy | G31: Green | H31: Very Active | I31: Activated | J31: 18402568111 | K31: 18402568112 | M31: High | N31: Insurance Services Office (ISO) | O31: Tim Kennedy
A32: Transcard | B32: 11426266508 | C32: 8705508201 | E32: Just published their accelerator. One customer asking for changes due to unique way of batching transactions. | F32: Tim Kennedy | G32: Green | H32: Occational | I32: Activated | J32: 18402567609 | K32: 18402567610 | M32: Medium | N32: Transcard | O32: Tim Kennedy
A33: Smarty, LLC | B33: 11426249222 | C33: 8705508201 | E33: Very happy. Asking for some fixes due to api breaking changes that will cost $8K | F33: Tim Kennedy | G33: Green | H33: Very Active | I33: Activated | J33: 18402567457 | K33: 18402567456 | M33: Medium | N33: Smarty, LLC | O33: Tim Kennedy
A34: SailPoint Technologies, Inc. | B34: 11426248637 | C34: 8705508201 | F34: Tim Kennedy | G34: Green | H34: Active | I34: Activated | J34: 18402567312 | K34: 18402567311 | M34: High | N34: SailPoint Technologies, Inc. | O34: Tim Kennedy
A35: Precisely Software | B35: 11426231946 | C35: 8705508201 | E35: Built RFG Accelerator. Wanting a quote on a new one for their property apis similar to Smarty | F35: Tim Kennedy | G35: Green | H35: Active | I35: Activated | J35: 18402567162 | K35: 18402567161 | M35: Medium | N35: Precisely Software | O35: Tim Kennedy
A36: Agentsync | B36: 11416633623 | C36: 8705508201 | F36: Shannon Spies | G36: Green | H36: Active | I36: Activated | J36: 18402404464 | K36: 18402404465 | M36: High | N36: AgentSync | O36: Shannon Spies
A37: Akur8 | B37: 11425931219 | C37: 8705508201 | F37: Tim Kennedy | G37: Yellow | H37: Active | I37: Activated | J37: 18402561158 | K37: 18402561152 | M37: Medium | N37: AKUR8 | O37: Tim Kennedy
A38: Amazon Web Services, Inc. | B38: 11416792834 | C38: 8705508201 | F38: Paul Harper | G38: Green | H38: Very Active | I38: Activated | J38: 18402407351 | K38: 18402407354 | M38: High | N38: Amazon Web Services, Inc.
A39: American Association of Insurance Services (AAIS) | B39: 11416948168 | C39: 8705508201 | F39: Eric Apse | G39: Green | H39: Active | I39: Activated | J39: 18402411178 | K39: 18402411177 | M39: High | N39: American Association of Insurance Services (AAIS) | O39: Eric Apse
A40: Appian | B40: 11416919307 | C40: 8705508201 | F40: Fatima Aoulagha-Bannou | G40: Green | H40: Active | I40: Activated | J40: 18402409821 | K40: 18402409819 | M40: High | N40: Appian | O40: Fatima Aoulagha-Bannou
A41: Applied Systems Inc | B41: 11416670807 | C41: 8705508201 | F41: Rod Gowin | G41: Green | H41: Active | I41: Activated | J41: 18402404892 | K41: 18402404896 | M41: High | N41: Applied Systems Inc | O41: Rod Gowin
A42: Appulate, Inc. | B42: 11425988783 | C42: 8705508201 | E42: Happy about accelerator publishing. Very cost conscious | F42: Tim Kennedy | G42: Green | H42: Occational | I42: Activated | J42: 18402562945 | K42: 18402562936 | M42: Medium | N42: Appulate, Inc. | O42: Tim Kennedy
A43: Arbitration Forums, Inc | B43: 11416688772 | C43: 8705508201 | F43: Rod Gowin | G43: Green | H43: Occational | I43: Activated | J43: 18402405099 | K43: 18402405102 | M43: Medium | N43: Arbitration Forums, Inc | O43: Rod Gowin
A44: Assurant | B44: 11416714010 | C44: 8705508201 | F44: Aaron Shaw | G44: Green | H44: Active | I44: Activated | J44: 18402405438 | K44: 18402405436 | M44: Medium | N44: Assurant | O44: Aaron Shaw
A45: Audatex UK Limited | B45: 11416944892 | C45: 8705508201 | F45: Eric Apse | G45: Green | H45: Active | I45: Activated | J45: 18402410994 | K45: 18402410992 | M45: High | N45: Audatex UK Limited | O45: Eric Apse
A46: Blue Prism | B46: 11426078226 | C46: 8705508201 | E46: Not seeing value from partnership | F46: Tim Kennedy | G46: Red | H46: Occational | I46: Activated | J46: 18402563983 | K46: 18402563985 | M46: Medium | N46: SS&C Blue Prism | O46: Tim Kennedy
A47: Box | B47: 11426059749 | C47: 8705508201 | E47: Expecting to sign a build and maintenance BBG agreement for around 200K | F47: Tim Kennedy | G47: Green | H47: Active | I47: Activated | J47: 18402563866 | K47: 18402563865 | M47: Medium | N47: Box | O47: Tim Kennedy
A48: CCC Intelligent Solutions Inc | B48: 11416861335 | C48: 8705508201 | F48: Kelly Clayton | G48: Green | H48: Active | I48: Activated | J48: 18402409000 | K48: 18402409002 | M48: High | N48: CCC Intelligent Solutions Inc | O48: Kelly Clayton
A49: ClaimTECH | B49: 11416878214 | C49: 8705508201 | F49: Kelly Clayton | G49: Green | H49: Active | I49: Activated | J49: 18402409223 | K49: 18402409227 | M49: High | N49: ClaimTECH | O49: Kelly Clayton
A50: Copart, Inc. | B50: 11416804648 | C50: 8705508201 | F50: Aaron Shaw | G50: Green | H50: N/A | I50: Activated | J50: 18402407264 | K50: 18402407256 | M50: High | N50: Copart, Inc. | O50: Aaron Shaw
A51: CoreLogic | B51: 11426026636 | C51: 8705508201 | E51: Mostly checked out. We were unable to sponsor their conference | F51: Tim Kennedy | G51: Green | H51: Disengaged | I51: Activated | J51: 18402564170 | K51: 18402564171 | N51: CoreLogic | O51: Tim Kennedy
A52: Databricks | B52: 11416806468 | C52: 8705508201 | F52: Paul Harper | G52: Green | H52: Occational | I52: Activated | J52: 18402407798 | K52: 18402407796 | M52: High | N52: Databricks | O52: Paul Harper
A53: Docusign Inc | B53: 11416843889 | C53: 8705508201 | F53: Kelly Clayton | G53: Green | H53: Active | I53: Activated | J53: 18402408813 | K53: 18402408810 | M53: Strategic | N53: Docusign Inc | O53: Kelly Clayton
A54: Dynatrace LLC | B54: 11426083228 | C54: 8705508201 | F54: Tim Kennedy | G54: Green | H54: Occational | I54: Activated | J54: 18402564263 | K54: 18402564264 | M54: Medium | N54: Dynatrace LLC | O54: Tim Kennedy
A55: Earnix | B55: 11426082645 | C55: 8705508201 | E55: Very unhappy with how relationship has cooled since PricingCenter announced. Still heavy traction with our customers | F55: Tim Kennedy | G55: Yellow | H55: Very Active | I55: Activated | J55: 18402564352 | K55: 18402564350 | M55: High | N55: Earnix | O55: Tim Kennedy
A56: EPAM Systems Inc. | B56: 11416699172 | C56: 8705508201 | F56: Rod Gowin | G56: Green | H56: Active | I56: Activated | J56: 18402405223 | K56: 18402405224 | M56: Medium | N56: EPAM Systems Inc. | O56: Rod Gowin
A57: EvolutionIQ | B57: 11416872057 | C57: 8705508201 | F57: Kelly Clayton | G57: Green | H57: Active | I57: Activated | J57: 18402409269 | K57: 18402409275 | M57: High | N57: EvolutionIQ | O57: Kelly Clayton
A58: FRISS | B58: 11416903679 | C58: 8705508201 | F58: Eric Apse | G58: Green | H58: Active | I58: Activated | J58: 18402410902 | K58: 18402410904 | M58: High | N58: FRISS | O58: Eric Apse
A59: GhostDraft Enterprises LLC | B59: 11417599996 | C59: 8705508201 | F59: Lisa Vingerhoet | G59: Green | H59: Active | I59: Activated | J59: 18402556782 | K59: 18402556784 | M59: High | N59: GhostDraft Enterprises LLC | O59: Lisa Vingerhoet
A60: Hertz | B60: 11416928614 | C60: 8705508201 | F60: Eric Apse | G60: Green | H60: Active | I60: Activated | J60: 18402410494 | K60: 18402410492 | M60: High | N60: Hertz | O60: Eric Apse
A61: Hyland Software, Inc | B61: 11416686074 | C61: 8705508201 | F61: Rod Gowin | G61: Green | H61: Disengaged | I61: Activated | J61: 18402404979 | K61: 18402404980 | M61: Medium | N61: Hyland Software, Inc
A62: Hyperexponential Ltd | B62: 11426087917 | C62: 8705508201 | E62: Patrick joined as Alliance Manager. Very engaged building accelerator. | F62: Tim Kennedy | G62: Green | H62: Active | I62: Activated | J62: 18402564488 | K62: 18402564490 | M62: High | N62: Hyperexponential Ltd | O62: Tim Kennedy
A63: Indigo Data Solutions, Inc. | B63: 11416650867 | C63: 8705508201 | F63: Shannon Spies | G63: Green | H63: Active | I63: Activated | J63: 18402404771 | K63: 18402404769 | M63: Medium | N63: Indigo Data Solutions, Inc.
A64: InsurePay | B64: 11416702753 | C64: 8705508201 | F64: Rod Gowin | G64: Green | H64: Active | I64: Activated | J64: 18402563361 | K64: 18402405311 | M64: Medium | N64: InsurePay | O64: Rod Gowin
A65: LexisNexis Risk Solutions Inc. | B65: 11426109451 | C65: 8705508201 | E65: Agreed to pay for maintenance.,Showing delivery in February | F65: Tim Kennedy | G65: Green | H65: Very Active | I65: Activated | J65: 18402564676 | K65: 18402564677 | M65: High | N65: LexisNexis Risk Solutions Inc. | O65: Tim Kennedy
A66: Nearmap US, Inc | B66: 11416703131 | C66: 8705508201 | F66: Aaron Shaw | G66: Green | H66: Active | I66: Activated | J66: 18402407051 | K66: 18402407055 | M66: High | N66: Nearmap US, Inc
A67: Newgen Software Inc. | B67: 8707596675 | C67: 8705508201 | E67: Accelerators modernized finally | F67: Tim Kennedy | G67: Green | H67: Very Active | I67: Onboarded | J67: 18402565546 | K67: 18402565547 | M67: High | N67: Newgen Software Inc. | O67: Tim Kennedy
A68: One Inc | B68: 11416799850 | C68: 8705508201 | F68: Kelly Clayton | G68: Green | H68: Very Active | I68: Activated | J68: 18402407903 | K68: 18402407901 | M68: High | N68: One Inc | O68: Kelly Clayton
A69: Open Text Corporation | B69: 11426145034 | C69: 8705508201 | F69: Tim Kennedy | G69: Green | H69: Very Active | I69: Activated | J69: 18402565219 | K69: 18402565212 | M69: High | N69: Open Text Corporation | O69: Tim Kennedy
A70: Progi | B70: 11416657893 | C70: 8705508201 | F70: Shannon Spies | G70: Green | H70: Active | I70: Activated | J70: 18402404629 | K70: 18402404637 | M70: Medium | N70: Progi | O70: Shannon Spies
A71: Shift | B71: 11416903682 | C71: 8705508201 | F71: Fatima Aoulagha-Bannou | G71: Green | H71: Active | I71: Activated | J71: 18402410270 | K71: 18402410273 | M71: High | N71: Shift
A72: SmartComms LLC | B72: 11416860993 | C72: 8705508201 | F72: Kelly Clayton | G72: Green | H72: Active | I72: Activated | J72: 18402408094 | K72: 18402408092 | M72: Strategic | N72: SmartComms LLC | O72: Kelly Clayton
A73: Snowflake | B73: 11416814244 | C73: 8705508201 | F73: Paul Harper | G73: Green | H73: Occational | I73: Activated | J73: 18402407709 | K73: 18402407710 | N73: Snowflake | O73: Paul Harper
A74: Stripe | B74: 11416906711 | C74: 8705508201 | F74: Fatima Aoulagha-Bannou | G74: Green | H74: Active | I74: Activated | J74: 18402409783 | K74: 18402409782 | M74: High | N74: Stripe, Inc. | O74: Fatima Aoulagha-Bannou
A75: Swiss Re Solutions Ltd. | B75: 11416915309 | C75: 8705508201 | F75: Fatima Aoulagha-Bannou | G75: Green | H75: Active | I75: Activated | J75: 18402410404 | K75: 18402410403 | M75: Strategic | N75: Swiss Re Solutions Ltd. | O75: Fatima Aoulagha-Bannou

Sheet InternalBoards
A1: BoardName | B1: ID | C1: Tab | D1: Permission
A2: Partner Management Activities | B2: 9791255941 | C2: GW_PartnerManagementActivities | D2: PartnerManagement
A3: Tech Ops Activities | B3: 9791272390 | C3: GW_TechOpsActivities | D3: SolutionOps
A4: Marketing Activities | B4: 18374691224 | C4: GW_MarketingActivities | D4: MarketingProjects
A5: Marketplace Activities | B5: 18375013360 | C5: GW_IntegrationComplianceActivities | D5: Marketplace

Sheet MarketingCalendar
A1: Item Name | B1: Group | C1: Board Name | D1: Partner Name | E1: Monday Item ID | F1: Board ID | G1: Month | H1: Partner | I1: Owner | J1: Week | K1: Activity Type | L1: Date | M1: Formula | N1: EventDate | O1: Submission link | P1: Scope Document Public URL | Q1: Alliance Manager | R1: Scope Document Public URL | S1: Alliance Manager
A2: Tech Alert - Portal UI/UX Refresh | B2: Pending | C2: Marketing Event Calendar | D2: Marketing Team | E2: 18024022367 | F2: 9770467355 | G2: September | I2: Marketing | J2: 2 | K2: Newsletters + Email Campaigns | N2: 45908
A3: Synergy | B3: Pending | C3: Marketing Event Calendar | D3: Marketing Team | E3: 18024013075 | F3: 9770467355 | G3: August | I3: Marketing | J3: 4 | K3: GW Events/ MP Summit | N3: 45887
A4: Tech Alert BTS Education | B4: Pending | C4: Marketing Event Calendar | D4: Marketing Team | E4: 18023986922 | F4: 9770467355 | G4: August | I4: Marketing | J4: 1 | K4: Newsletters + Email Campaigns | N4: 45873
A5: Connections Executive Track | B5: Pending | C5: Marketing Event Calendar | D5: Marketing Team | E5: 18023951154 | F5: 9770467355 | G5: October | I5: Marketing | J5: 4 | K5: GW Events/ MP Summit | N5: 45957
A6: Marketplace Summit APAC | B6: Pending | C6: Marketing Event Calendar | D6: Marketing Team | E6: 18023934875 | F6: 9770467355 | G6: November | I6: Marketing | J6: 1 | K6: GW Events/ MP Summit | N6: 45964
A7: Insuretech Innovators Summit London | B7: Pending | C7: Marketing Event Calendar | D7: Marketing Team | E7: 18023924937 | F7: 9770467355 | G7: November | I7: Marketing | J7: 1 | K7: LIve Event | N7: 45964
A8: ITC OneSpan Reception | B8: Pending | C8: Marketing Event Calendar | D8: Marketing Team | E8: 18023921128 | F8: 9770467355 | G8: October | H8: OneSpan Canada Inc. (VASCO eSignLive) | I8: Marketing | J8: 3 | K8: LIve Event | N8: 45943
A9: ITC Insuretech Pitch | B9: Pending | C9: Marketing Event Calendar | D9: Marketing Team | E9: 18023914409 | F9: 9770467355 | G9: October | I9: Marketing | J9: 3 | K9: LIve Event | N9: 45943
A10: ITC Nearmap Reception | B10: Pending | C10: Marketing Event Calendar | D10: Marketing Team | E10: 18023906048 | F10: 9770467355 | G10: October | H10: Nearmap US, Inc. | I10: Marketing | J10: 2 | K10: LIve Event | N10: 45936
A11: Roots Webinar with M Anderson + Erie | B11: Pending | C11: Marketing Event Calendar | D11: Marketing Team | E11: 18023862471 | F11: 9770467355 | G11: September | H11: Roots Automation, Inc. | I11: Marketing | J11: 4 | K11: Press Releae | N11: 45922
A12: Roots PR for joint Webinar | B12: Pending | C12: Marketing Event Calendar | D12: Marketing Team | E12: 18023853987 | F12: 9770467355 | G12: September | H12: Roots Automation, Inc. | I12: Marketing | J12: 3 | K12: Press Releae | N12: 45915
A13: Partner Newsletter | B13: Pending | C13: Marketing Event Calendar | D13: Marketing Team | E13: 9771935915 | F13: 9770467355 | G13: August | I13: Marketing | J13: 2 | K13: Newsletters + Email Campaigns | N13: 45873
A14: Customer Newsletter | B14: Pending | C14: Marketing Event Calendar | D14: Marketing Team | E14: 9771935473 | F14: 9770467355 | G14: August | I14: Marketing | J14: 2 | K14: Newsletters + Email Campaigns | N14: 45873
A15: Internal Newsletter | B15: Pending | C15: Marketing Event Calendar | D15: Marketing Team | E15: 9771935508 | F15: 9770467355 | G15: August | I15: Marketing | J15: 2 | K15: Newsletters + Email Campaigns | N15: 45873
A16: Partner Newsletter | B16: Pending | C16: Marketing Event Calendar | D16: Marketing Team | E16: 9771935531 | F16: 9770467355 | G16: September | I16: Marketing | J16: 2 | K16: Newsletters + Email Campaigns | N16: 45907
A17: Partner Newsletter (copy) | B17: Pending | C17: Marketing Event Calendar | D17: Marketing Team | E17: 18023840104 | F17: 9770467355 | G17: September | I17: Marketing | J17: 2 | K17: Newsletters + Email Campaigns | N17: 45907
A18: Internal Newsletter | B18: Pending | C18: Marketing Event Calendar | D18: Marketing Team | E18: 9771935563 | F18: 9770467355 | G18: December | I18: Marketing | J18: 3 | K18: Newsletters + Email Campaigns | N18: 46006
A19: Internal Newsletter (copy) | B19: Pending | C19: Marketing Event Calendar | D19: Marketing Team | E19: 18023842917 | F19: 9770467355 | G19: December | I19: Marketing | J19: 3 | K19: Newsletters + Email Campaigns | N19: 46006
A20: Connections Know Before You Go Email | B20: Pending | C20: Marketing Event Calendar | D20: Marketing Team | E20: 9771935591 | F20: 9770467355 | G20: October | I20: Marketing | J20: 2 | K20: Newsletters + Email Campaigns | N20: 45937
A21: Partner Newsletter | B21: Pending | C21: Marketing Event Calendar | D21: Marketing Team | E21: 18023805292 | F21: 9770467355 | G21: November | I21: Marketing | J21: 2 | K21: Newsletters + Email Campaigns | N21: 45964
A22: Customer Newsletter | B22: Pending | C22: Marketing Event Calendar | D22: Marketing Team | E22: 18023806331 | F22: 9770467355 | G22: November | I22: Marketing | J22: 2 | K22: Newsletters + Email Campaigns | N22: 45964
A23: Internal Newsletter | B23: Pending | C23: Marketing Event Calendar | D23: Marketing Team | E23: 18023807086 | F23: 9770467355 | G23: November | I23: Marketing | J23: 2 | K23: Newsletters + Email Campaigns | N23: 45964
A24: Partner Awards Linked in | B24: Pending | C24: Marketing Event Calendar | D24: Marketing Team | E24: 9771935650 | F24: 9770467355 | G24: August | I24: Marketing | J24: 3 | K24: Social Promo | N24: 45883
A25: Newgen Spring Campaign Post | B25: Pending | C25: Marketing Event Calendar | D25: Marketing Team | E25: 18023473841 | F25: 9770467355 | G25: August | H25: Newgen Software Inc. | I25: Marketing | J25: 2 | K25: Social Promo | N25: 45944
A26: Cadenx RX Announcement | B26: Pending | C26: Marketing Event Calendar | D26: Marketing Team | E26: 18023745921 | F26: 9770467355 | G26: August | H26: Cadenx | I26: Marketing | J26: 3 | K26: Social Promo | N26: 45880
A27: Livegenic new Integration | B27: Pending | C27: Marketing Event Calendar | D27: Marketing Team | E27: 18023752812 | F27: 9770467355 | G27: September | H27: Livegenic, Inc aka Wilbur | I27: Marketing | J27: 2 | K27: Social Promo | N27: 45908
A28: DingGo new Partner Announcement | B28: Pending | C28: Marketing Event Calendar | D28: Marketing Team | E28: 18023762807 | F28: 9770467355 | G28: September | H28: DingGo | I28: Marketing | J28: 3 | K28: Social Promo | N28: 45915
A29: Postex New Partner Announcement | B29: Pending | C29: Marketing Event Calendar | D29: Marketing Team | E29: 18023773861 | F29: 9770467355 | G29: September | H29: Postex | I29: Marketing | J29: 4 | K29: Social Promo | N29: 45922
A30: Epam | B30: Pending | C30: Marketing Event Calendar | D30: Marketing Team | E30: 18023784407 | F30: 9770467355 | G30: November | H30: Epam | I30: Marketing | J30: 1 | K30: Social Promo | N30: 45964
A31: OpenText | B31: Pending | C31: Marketing Event Calendar | D31: Marketing Team | E31: 18023604658 | F31: 9770467355 | G31: November | H31: OpenText Inc. | I31: Marketing | J31: 3 | K31: LIve Event | N31: 45975
A32: ITV Vegas | B32: Pending | C32: Marketing Event Calendar | D32: Marketing Team | E32: 18023600830 | F32: 9770467355 | G32: October | I32: Marketing | J32: 3 | K32: LIve Event | N32: 45944
A33: Genesys | B33: Pending | C33: Marketing Event Calendar | D33: Marketing Team | E33: 18023581847 | F33: 9770467355 | G33: September | H33: Genesys Cloud Services, Inc. | I33: Marketing | J33: 2 | K33: LIve Event | N33: 45907
A34: Boxworks | B34: Pending | C34: Marketing Event Calendar | D34: Marketing Team | E34: 18023575300 | F34: 9770467355 | G34: September | H34: Box | I34: Marketing | J34: 2 | K34: LIve Event | N34: 45909
A35: Swiss Re Enablement Webinar | B35: Pending | C35: Marketing Event Calendar | D35: Marketing Team | E35: 9771935576 | F35: 9770467355 | G35: August | H35: Swiss Re Solutions Ltd. | I35: Alliance Manager | J35: 2 | K35: Webinar | N35: 45876
A36: Tim on Newgen Webinar | B36: Pending | C36: Marketing Event Calendar | D36: Marketing Team | E36: 9771935599 | F36: 9770467355 | G36: August | H36: Newgen Software Inc. | I36: Alliance Manager | J36: 3 | K36: Webinar | N36: 45883
A37: Hyland Webinar w/Gregg | B37: Pending | C37: Marketing Event Calendar | D37: Marketing Team | E37: 18023669897 | F37: 9770467355 | G37: September | H37: Hyland Software, Inc. | I37: Marketing | J37: 2 | K37: Webinar | N37: 45909
A38: Marketplace Enablement Webinar | B38: Pending | C38: Marketing Event Calendar | D38: Marketing Team | E38: 18023676729 | F38: 9770467355 | G38: September | I38: Marketing | J38: 4 | K38: Webinar | N38: 45922
A39: Roots Webinar w/Michael A | B39: Pending | C39: Marketing Event Calendar | D39: Marketing Team | E39: 18023685550 | F39: 9770467355 | G39: September | H39: Roots Automation, Inc. | I39: Marketing | J39: 5 | K39: Webinar | N39: 45929
A40: OpenText Webinar w/Gregg | B40: Pending | C40: Marketing Event Calendar | D40: Marketing Team | E40: 18023694241 | F40: 9770467355 | G40: October | H40: OpenText Inc. | I40: Marketing | J40: 2 | K40: Webinar | N40: 45936
A41: One Inc/GW blog: Claims litigation and nuclear verdicts | B41: Pending | C41: Marketing Event Calendar | D41: Marketing Team | E41: 9771935877 | F41: 9770467355 | G41: August | H41: One Inc | I41: Alliance Manager | J41: 3 | K41: Blogs | N41: 45883
A42: Smarty Blog | B42: Pending | C42: Marketing Event Calendar | D42: Marketing Team | E42: 18023706846 | F42: 9770467355 | G42: August | H42: Smarty, LLC | I42: Marketing | J42: 2 | K42: Blogs | N42: 45880
A43: Hi Marley Blog | B43: Pending | C43: Marketing Event Calendar | D43: Marketing Team | E43: 18023714620 | F43: 9770467355 | G43: September | H43: Hi Marley | I43: Marketing | J43: 1 | K43: Blogs | N43: 45901
A44: Roots Partner Posting Blog | B44: Pending | C44: Marketing Event Calendar | D44: Marketing Team | E44: 18023720402 | F44: 9770467355 | G44: September | H44: Roots Automation, Inc. | I44: Marketing | J44: 4 | K44: Blogs | N44: 45922
A45: Connections on MP.com (copy) | B45: Pending | C45: Marketing Event Calendar | D45: Marketing Team | E45: 18023510408 | F45: 9770467355 | G45: August | I45: Marketing | J45: 4 | K45: GW.com or MP.com Promo | N45: 45890
A46: Connections on MP.com | B46: Pending | C46: Marketing Event Calendar | D46: Marketing Team | E46: 18023485165 | F46: 9770467355 | G46: August | I46: Marketing | J46: 1 | K46: GW.com or MP.com Promo | N46: 45874
A47: Connections on MP.com | B47: Pending | C47: Marketing Event Calendar | D47: Marketing Team | E47: 18023493589 | F47: 9770467355 | G47: August | I47: Marketing | J47: 2 | K47: GW.com or MP.com Promo | N47: 45874
A48: Connections on MP.com | B48: Pending | C48: Marketing Event Calendar | D48: Marketing Team | E48: 18023499055 | F48: 9770467355 | G48: August | I48: Marketing | J48: 3 | K48: GW.com or MP.com Promo | N48: 45944
A49: Connections on MP.com | B49: Pending | C49: Marketing Event Calendar | D49: Marketing Team | E49: 18023503864 | F49: 9770467355 | G49: August | I49: Marketing | J49: 1 | K49: GW.com or MP.com Promo | N49: 45931
A50: Connections on MP.com | B50: Pending | C50: Marketing Event Calendar | D50: Marketing Team | E50: 18023540157 | F50: 9770467355 | G50: September | I50: Marketing | J50: 1 | K50: GW.com or MP.com Promo | N50: 45901
A51: Connections on MP.com | B51: Pending | C51: Marketing Event Calendar | D51: Marketing Team | E51: 18023542734 | F51: 9770467355 | G51: October | I51: Marketing | J51: 1 | K51: GW.com or MP.com Promo | N51: 45931
A52: Connections on MP.com | B52: Pending | C52: Marketing Event Calendar | D52: Marketing Team | E52: 18023509267 | F52: 9770467355 | G52: September | I52: Marketing | J52: 2 | K52: GW.com or MP.com Promo | N52: 45908
A53: Connections on MP.com | B53: Pending | C53: Marketing Event Calendar | D53: Marketing Team | E53: 18023528189 | F53: 9770467355 | G53: October | I53: Marketing | J53: 2 | K53: GW.com or MP.com Promo | N53: 45936
A54: Connections on MP.com | B54: Pending | C54: Marketing Event Calendar | D54: Marketing Team | E54: 18023511132 | F54: 9770467355 | G54: September | I54: Marketing | J54: 3 | K54: GW.com or MP.com Promo | N54: 45915
A55: Connections on MP.com | B55: Pending | C55: Marketing Event Calendar | D55: Marketing Team | E55: 18023531363 | F55: 9770467355 | G55: October | I55: Marketing | J55: 3 | K55: GW.com or MP.com Promo | N55: 45943
A56: Connections on MP.com | B56: Pending | C56: Marketing Event Calendar | D56: Marketing Team | E56: 18023512234 | F56: 9770467355 | G56: September | I56: Marketing | J56: 4 | K56: GW.com or MP.com Promo | N56: 45922
... A59: Excellence Award Winners | B59: Pending | C59: Marketing Event Calendar | D59: Marketing Team | E59: 18023553109 | F59: 9770467355 | G59: October | I59: Marketing | J59: 5 | K59: GW.com or MP.com Promo | N59: 45957
A60: Smart Innovate London | B60: Pending | C60: Marketing Event Calendar | D60: Marketing Team | E60: 18023595072 | F60: 9770467355 | G60: October | H60: SmartComms LLC | I60: Marketing | J60: 2 | K60: LIve Event | N60: 45937
A61: Nordic User Group Michael Anderson Presentation | B61: Pending | C61: Marketing Event Calendar | D61: Marketing Team | E61: 18023587844 | F61: 9770467355 | G61: September | I61: Marketing | J61: 1 | K61: LIve Event | N61: 45901
A62: HX Live | B62: Pending | C62: Marketing Event Calendar | D62: Marketing Team | E62: 18023562174 | F62: 9770467355 | G62: September | H62: Hyperexponential Ltd | I62: Marketing | J62: 3 | K62: LIve Event | N62: 45914
A63: Earnix Excelerate | B63: Pending | C63: Marketing Event Calendar | D63: Marketing Team | E63: 9771935746 | F63: 9770467355 | G63: September | H63: Earnix | I63: Alliance Manager | J63: 2 | K63: LIve Event | N63: 45907
A64: Connections | B64: Pending | C64: Marketing Event Calendar | D64: Marketing Team | E64: 9771935771 | F64: 9770467355 | G64: October | I64: Marketing | J64: 3 | K64: LIve Event | N64: 45951
A65: Smarty Talking Points | B65: Pending | C65: Marketing Event Calendar | D65: Marketing Team | E65: 18023728244 | F65: 9770467355 | G65: August | H65: Smarty, LLC | I65: Marketing | J65: 3 | K65: Sales Enablement Pitch Pkgs | N65: 45880
A66: Nearmap Talking Points | B66: Pending | C66: Marketing Event Calendar | D66: Marketing Team | E66: 18023733710 | F66: 9770467355 | G66: August | H66: Nearmap US, Inc. | I66: Marketing | J66: 3 | K66: Sales Enablement Pitch Pkgs | N66: 45943
A67: Whatfix Pannel at ITC | B67: Pending | C67: Marketing Event Calendar | D67: Marketing Team | E67: 18281477420 | F67: 9770467355 | G67: October | H67: Whatfix Inc. | I67: Alliance Manager | J67: 3 | K67: LIve Event | N67: 45946
A68: Whatfix Partner Day | B68: Pending | C68: Marketing Event Calendar | D68: Marketing Team | E68: 18290777137 | F68: 9770467355 | G68: November | H68: Whatfix Inc. | I68: Alliance Manager | J68: 2 | K68: LIve Event | N68: 45972
A69: Whatfix Partner Day Webinar | B69: Pending | C69: Marketing Event Calendar | D69: Marketing Team | E69: 10538690350 | F69: 9770467355 | G69: November | H69: Whatfix Inc. | I69: Alliance Manager | J69: 2 | K69: Webinar | N69: 45972
A70: Verisk Blog | B70: Pending | C70: Marketing Event Calendar | D70: Marketing Team | E70: 10552867061 | F70: 9770467355 | G70: November | H70: Insurance Services Office (ISO) | I70: Alliance Manager | J70: 2 | K70: Blogs | N70: 45973
A71: Verisk Blog | B71: Pending | C71: Marketing Event Calendar | D71: Marketing Team | E71: 10552909245 | F71: 9770467355 | G71: November | H71: Insurance Services Office (ISO) | I71: Alliance Manager | J71: 2 | K71: Blogs | N71: 45973
A72: test 2ab | B72: Pending | C72: Marketing Event Calendar | D72: Marketing Team | E72: 10819797220 | F72: 9770467355 | G72: December | H72: Box | I72: Alliance Manager | J72: 5 | K72: Blogs | N72: 46023

Sheet PartnerTranslate
A1: From | B1: To
A2: Addatech | B2: ADDATECH Systems
A3: AgentSync | B3: AgentSync
A4: Akur8 | B4: AKUR8
A5: Appulate | B5: Appulate, Inc.
A6: ARB | B6: Arbitration Forums, Inc
A7: ARMA | B7: ARMA Group Holdings
A8: Assurant | B8: Assurant
A9: AWS | B9: Amazon Web Services, Inc
A10: Belron | B10: Belron Canada
A11: Blue Prism | B11: SS&C Blue Prism
A12: Box | B12: Box
... A107: WTW | B107: WTW

Sheet Partner
A1: =IFERROR(__xludf.DUMMYFUNCTION("ImportRange(""https://docs.google.com/spreadsheets/d/1KgCYm9vziZoCzLB0WQ0Koimu8-IHnpz-b43ueLUEuQI/edit"",""Partner!A:AZ"")"),"Account Name") -> Account Name | B1: =IFERROR(__xludf.DUMMYFUNCTION("""COMPUTED_VALUE"""),"Tier") -> Tier | C1: =IFERROR(__xludf.DUMMYFUNCTION("""COMPUTED_VALUE"""),"Region") -> Region | D1: =IFERROR(__xludf.DUMMYFUNCTION("""COMPUTED_VALUE"""),"Account Owner") -> Account Owner | E1: =IFERROR(__xludf.DUMMYFUNCTION("""COMPUTED_VALUE"""),"Geo's Supported") -> Geo's Supported | F1: =IFERROR(__xludf.DUMMYFUNCTION("""COMPUTED_VALUE"""),"Guidewire Product") -> Guidewire Product | G1: =IFERROR(__xludf.DUMMYFUNCTION("""COMPUTED_VALUE"""),"Program Agreement Effective Date") -> Program Agreement Effective Date | H1: =IFERROR(__xludf.DUMMYFUNCTION("""COMPUTED_VALUE"""),"Program Agreement Expiration Date") -> Program Agreement Expiration Date | I1: =IFERROR(__xludf.DUMMYFUNCTION("""COMPUTED_VALUE"""),"RfG Agreement Effective Date") -> RfG Agreement Effective Date | J1: =IFERROR(__xludf.DUMMYFUNCTION("""COMPUTED_VALUE"""),"Date Left Program") -> Date Left Program | K1: =IFERROR(__xludf.DUMMYFUNCTION("""COMPUTED_VALUE"""),"First Accelerator Published") -> First Accelerator Published | L1: =IFERROR(__xludf.DUMMYFUNCTION("""COMPUTED_VALUE"""),"Alliances Marketing Tier Level") -> Alliances Marketing Tier Level | M1: =IFERROR(__xludf.DUMMYFUNCTION("""COMPUTED_VALUE"""),"Alliance Type") -> Alliance Type | N1: =IFERROR(__xludf.DUMMYFUNCTION("""COMPUTED_VALUE"""),"Quarter") -> Quarter | O1: =IFERROR(__xludf.DUMMYFUNCTION("""COMPUTED_VALUE"""),"Cloud Integrations") -> Cloud Integrations | P1: =IFERROR(__xludf.DUMMYFUNCTION("""COMPUTED_VALUE"""),"Integrations") -> Integrations | Q1: =IFERROR(__xludf.DUMMYFUNCTION("""COMPUTED_VALUE"""),"Downloads") -> Downloads | R1: =IFERROR(__xludf.DUMMYFUNCTION("""COMPUTED_VALUE"""),"Downloads YTD") -> Downloads YTD | S1: =IFERROR(__xludf.DUMMYFUNCTION("""COMPUTED_VALUE"""),"Marketplace Hits") -> Marketplace Hits | T1: =IFERROR(__xludf.DUMMYFUNCTION("""COMPUTED_VALUE"""),"Unique Customers") -> Unique Customers | U1: =IFERROR(__xludf.DUMMYFUNCTION("""COMPUTED_VALUE"""),"Cloud Downloads") -> Cloud Downloads | V1: =IFERROR(__xludf.DUMMYFUNCTION("""COMPUTED_VALUE"""),"Cloud Downloads YTD") -> Cloud Downloads YTD | W1: =IFERROR(__xludf.DUMMYFUNCTION("""COMPUTED_VALUE"""),"Training Compliance") -> Training Compliance | X1: =IFERROR(__xludf.DUMMYFUNCTION("""COMPUTED_VALUE"""),"SI Used") -> SI Used
A2: =IFERROR(__xludf.DUMMYFUNCTION("""COMPUTED_VALUE"""),"ABI Document Support Services(R) LLC") -> ABI Document Support Services(R) LLC | B2: =IFERROR(__xludf.DUMMYFUNCTION("""COMPUTED_VALUE"""),"Growth") -> Growth | C2: =IFERROR(__xludf.DUMMYFUNCTION("""COMPUTED_VALUE"""),"NAM") -> NAM | D2: =IFERROR(__xludf.DUMMYFUNCTION("""COMPUTED_VALUE"""),"Aaron Shaw") -> Aaron Shaw | E2: =IFERROR(__xludf.DUMMYFUNCTION("""COMPUTED_VALUE"""),"United States") -> United States | F2: =IFERROR(__xludf.DUMMYFUNCTION("""COMPUTED_VALUE"""),"ClaimCenter") -> ClaimCenter | G2: =IFERROR(__xludf.DUMMYFUNCTION("""COMPUTED_VALUE"""),43934.0) -> 43934 | H2: =IFERROR(__xludf.DUMMYFUNCTION("""COMPUTED_VALUE"""),44665.0) -> 44665 | I2: =IFERROR(__xludf.DUMMYFUNCTION("""COMPUTED_VALUE"""),44337.0) -> 44337 | K2: =IFERROR(__xludf.DUMMYFUNCTION("""COMPUTED_VALUE"""),44376.0) -> 44376 | L2: =IFERROR(__xludf.DUMMYFUNCTION("""COMPUTED_VALUE"""),"Low") -> Low | M2: =IFERROR(__xludf.DUMMYFUNCTION("""COMPUTED_VALUE"""),"PartnerConnect Technology") -> PartnerConnect Technology | N2: =IFERROR(__xludf.DUMMYFUNCTION("""COMPUTED_VALUE"""),"FY20 - Q3") -> FY20 - Q3 | O2: =IFERROR(__xludf.DUMMYFUNCTION("""COMPUTED_VALUE"""),0.0) -> 0 | P2: =IFERROR(__xludf.DUMMYFUNCTION("""COMPUTED_VALUE"""),0.0) -> 0 | Q2: =IFERROR(__xludf.DUMMYFUNCTION("""COMPUTED_VALUE"""),0.0) -> 0 | R2: =IFERROR(__xludf.DUMMYFUNCTION("""COMPUTED_VALUE"""),0.0) -> 0 | S2: =IFERROR(__xludf.DUMMYFUNCTION("""COMPUTED_VALUE"""),0.0) -> 0 | T2: =IFERROR(__xludf.DUMMYFUNCTION("""COMPUTED_VALUE"""),0.0) -> 0 | U2: =IFERROR(__xludf.DUMMYFUNCTION("""COMPUTED_VALUE"""),0.0) -> 0 | V2: =IFERROR(__xludf.DUMMYFUNCTION("""COMPUTED_VALUE"""),0.0) -> 0 | W2: =IFERROR(__xludf.DUMMYFUNCTION("""COMPUTED_VALUE"""),"#REF!") -> #REF! | X2: =IFERROR(__xludf.DUMMYFUNCTION("""COMPUTED_VALUE"""),FALSE) -> FALSE
A3: =IFERROR(__xludf.DUMMYFUNCTION("""COMPUTED_VALUE"""),"accuro Solutions") -> accuro Solutions | B3: =IFERROR(__xludf.DUMMYFUNCTION("""COMPUTED_VALUE"""),"Growth") -> Growth | C3: =IFERROR(__xludf.DUMMYFUNCTION("""COMPUTED_VALUE"""),"NAM") -> NAM | D3: =IFERROR(__xludf.DUMMYFUNCTION("""COMPUTED_VALUE"""),"Rod Gowin") -> Rod Gowin | E3: =IFERROR(__xludf.DUMMYFUNCTION("""COMPUTED_VALUE"""),"United States") -> United States | F3: =IFERROR(__xludf.DUMMYFUNCTION("""COMPUTED_VALUE"""),"ClaimCenter") -> ClaimCenter | G3: =IFERROR(__xludf.DUMMYFUNCTION("""COMPUTED_VALUE"""),45870.0) -> 45870 | I3: =IFERROR(__xludf.DUMMYFUNCTION("""COMPUTED_VALUE"""),45870.0) -> 45870 | L3: =IFERROR(__xludf.DUMMYFUNCTION("""COMPUTED_VALUE"""),"Medium") -> Medium | M3: =IFERROR(__xludf.DUMMYFUNCTION("""COMPUTED_VALUE"""),"PartnerConnect Technology") -> PartnerConnect Technology | N3: =IFERROR(__xludf.DUMMYFUNCTION("""COMPUTED_VALUE"""),"FY25 - Q1") -> FY25 - Q1 | O3: =IFERROR(__xludf.DUMMYFUNCTION("""COMPUTED_VALUE"""),0.0) -> 0 | P3: =IFERROR(__xludf.DUMMYFUNCTION("""COMPUTED_VALUE"""),0.0) -> 0 | Q3: =IFERROR(__xludf.DUMMYFUNCTION("""COMPUTED_VALUE"""),0.0) -> 0 | R3: =IFERROR(__xludf.DUMMYFUNCTION("""COMPUTED_VALUE"""),0.0) -> 0 | S3: =IFERROR(__xludf.DUMMYFUNCTION("""COMPUTED_VALUE"""),0.0) -> 0 | T3: =IFERROR(__xludf.DUMMYFUNCTION("""COMPUTED_VALUE"""),0.0) -> 0 | U3: =IFERROR(__xludf.DUMMYFUNCTION("""COMPUTED_VALUE"""),0.0) -> 0 | V3: =IFERROR(__xludf.DUMMYFUNCTION("""COMPUTED_VALUE"""),0.0) -> 0 | W3: =IFERROR(__xludf.DUMMYFUNCTION("""COMPUTED_VALUE"""),0.0) -> 0 | X3: =IFERROR(__xludf.DUMMYFUNCTION("""COMPUTED_VALUE"""),FALSE) -> FALSE
A4: =IFERROR(__xludf.DUMMYFUNCTION("""COMPUTED_VALUE"""),"ACI Worldwide") -> ACI Worldwide | B4: =IFERROR(__xludf.DUMMYFUNCTION("""COMPUTED_VALUE"""),"Growth") -> Growth | C4: =IFERROR(__xludf.DUMMYFUNCTION("""COMPUTED_VALUE"""),"NAM") -> NAM | D4: =IFERROR(__xludf.DUMMYFUNCTION("""COMPUTED_VALUE"""),"Aaron Shaw") -> Aaron Shaw | E4: =IFERROR(__xludf.DUMMYFUNCTION("""COMPUTED_VALUE"""),"United States") -> United States | F4: =IFERROR(__xludf.DUMMYFUNCTION("""COMPUTED_VALUE"""),"ClaimCenter, PolicyCenter, BillingCenter") -> ClaimCenter, PolicyCenter, BillingCenter | G4: =IFERROR(__xludf.DUMMYFUNCTION("""COMPUTED_VALUE"""),43383.0) -> 43383 | H4: =IFERROR(__xludf.DUMMYFUNCTION("""COMPUTED_VALUE"""),44114.0) -> 44114 | I4: =IFERROR(__xludf.DUMMYFUNCTION("""COMPUTED_VALUE"""),43383.0) -> 43383 | K4: =IFERROR(__xludf.DUMMYFUNCTION("""COMPUTED_VALUE"""),43620.0) -> 43620 | L4: =IFERROR(__xludf.DUMMYFUNCTION("""COMPUTED_VALUE"""),"Low") -> Low | M4: =IFERROR(__xludf.DUMMYFUNCTION("""COMPUTED_VALUE"""),"PartnerConnect Technology") -> PartnerConnect Technology | N4: =IFERROR(__xludf.DUMMYFUNCTION("""COMPUTED_VALUE"""),"FY18 - Q1") -> FY18 - Q1 | O4: =IFERROR(__xludf.DUMMYFUNCTION("""COMPUTED_VALUE"""),3.0) -> 3 | P4: =IFERROR(__xludf.DUMMYFUNCTION("""COMPUTED_VALUE"""),3.0) -> 3 | Q4: =IFERROR(__xludf.DUMMYFUNCTION("""COMPUTED_VALUE"""),38.0) -> 38 | R4: =IFERROR(__xludf.DUMMYFUNCTION("""COMPUTED_VALUE"""),10.0) -> 10 | S4: =IFERROR(__xludf.DUMMYFUNCTION("""COMPUTED_VALUE"""),46038.0) -> 46038 | T4: =IFERROR(__xludf.DUMMYFUNCTION("""COMPUTED_VALUE"""),15.0) -> 15 | U4: =IFERROR(__xludf.DUMMYFUNCTION("""COMPUTED_VALUE"""),0.0) -> 0 | V4: =IFERROR(__xludf.DUMMYFUNCTION("""COMPUTED_VALUE"""),0.0) -> 0 | W4: =IFERROR(__xludf.DUMMYFUNCTION("""COMPUTED_VALUE"""),0.0) -> 0 | X4: =IFERROR(__xludf.DUMMYFUNCTION("""COMPUTED_VALUE"""),TRUE) -> TRUE
A5: =IFERROR(__xludf.DUMMYFUNCTION("""COMPUTED_VALUE"""),"ADDATECH Systems") -> ADDATECH Systems | B5: =IFERROR(__xludf.DUMMYFUNCTION("""COMPUTED_VALUE"""),"Growth") -> Growth | C5: =IFERROR(__xludf.DUMMYFUNCTION("""COMPUTED_VALUE"""),"NAM") -> NAM | D5: =IFERROR(__xludf.DUMMYFUNCTION("""COMPUTED_VALUE"""),"Rod Gowin") -> Rod Gowin | E5: =IFERROR(__xludf.DUMMYFUNCTION("""COMPUTED_VALUE"""),"Canada") -> Canada | F5: =IFERROR(__xludf.DUMMYFUNCTION("""COMPUTED_VALUE"""),"ClaimCenter") -> ClaimCenter | G5: =IFERROR(__xludf.DUMMYFUNCTION("""COMPUTED_VALUE"""),44607.0) -> 44607 | H5: =IFERROR(__xludf.DUMMYFUNCTION("""COMPUTED_VALUE"""),45336.0) -> 45336 | I5: =IFERROR(__xludf.DUMMYFUNCTION("""COMPUTED_VALUE"""),44607.0) -> 44607 | L5: =IFERROR(__xludf.DUMMYFUNCTION("""COMPUTED_VALUE"""),"Low") -> Low | M5: =IFERROR(__xludf.DUMMYFUNCTION("""COMPUTED_VALUE"""),"PartnerConnect Technology") -> PartnerConnect Technology | N5: =IFERROR(__xludf.DUMMYFUNCTION("""COMPUTED_VALUE"""),"FY22 - Q2") -> FY22 - Q2 | O5: =IFERROR(__xludf.DUMMYFUNCTION("""COMPUTED_VALUE"""),0.0) -> 0 | P5: =IFERROR(__xludf.DUMMYFUNCTION("""COMPUTED_VALUE"""),0.0) -> 0 | Q5: =IFERROR(__xludf.DUMMYFUNCTION("""COMPUTED_VALUE"""),0.0) -> 0 | R5: =IFERROR(__xludf.DUMMYFUNCTION("""COMPUTED_VALUE"""),0.0) -> 0 | S5: =IFERROR(__xludf.DUMMYFUNCTION("""COMPUTED_VALUE"""),0.0) -> 0 | T5: =IFERROR(__xludf.DUMMYFUNCTION("""COMPUTED_VALUE"""),0.0) -> 0 | U5: =IFERROR(__xludf.DUMMYFUNCTION("""COMPUTED_VALUE"""),0.0) -> 0 | V5: =IFERROR(__xludf.DUMMYFUNCTION("""COMPUTED_VALUE"""),0.0) -> 0 | W5: =IFERROR(__xludf.DUMMYFUNCTION("""COMPUTED_VALUE"""),0.0) -> 0 | X5: =IFERROR(__xludf.DUMMYFUNCTION("""COMPUTED_VALUE"""),FALSE) -> FALSE
A6: =IFERROR(__xludf.DUMMYFUNCTION("""COMPUTED_VALUE"""),"Administrative Claim Service, Inc.") -> Administrative Claim Service, Inc. | B6: =IFERROR(__xludf.DUMMYFUNCTION("""COMPUTED_VALUE"""),"Growth") -> Growth | C6: =IFERROR(__xludf.DUMMYFUNCTION("""COMPUTED_VALUE"""),"NAM") -> NAM | D6: =IFERROR(__xludf.DUMMYFUNCTION("""COMPUTED_VALUE"""),"Rod Gowin") -> Rod Gowin | E6: =IFERROR(__xludf.DUMMYFUNCTION("""COMPUTED_VALUE"""),"United States") -> United States | G6: =IFERROR(__xludf.DUMMYFUNCTION("""COMPUTED_VALUE"""),46037.0) -> 46037 | I6: =IFERROR(__xludf.DUMMYFUNCTION("""COMPUTED_VALUE"""),46037.0) -> 46037 | L6: =IFERROR(__xludf.DUMMYFUNCTION("""COMPUTED_VALUE"""),"Medium") -> Medium | M6: =IFERROR(__xludf.DUMMYFUNCTION("""COMPUTED_VALUE"""),"PartnerConnect Technology") -> PartnerConnect Technology | N6: =IFERROR(__xludf.DUMMYFUNCTION("""COMPUTED_VALUE"""),"FY26 - Q2") -> FY26 - Q2 | O6: =IFERROR(__xludf.DUMMYFUNCTION("""COMPUTED_VALUE"""),0.0) -> 0 | P6: =IFERROR(__xludf.DUMMYFUNCTION("""COMPUTED_VALUE"""),0.0) -> 0 | Q6: =IFERROR(__xludf.DUMMYFUNCTION("""COMPUTED_VALUE"""),0.0) -> 0 | R6: =IFERROR(__xludf.DUMMYFUNCTION("""COMPUTED_VALUE"""),0.0) -> 0 | S6: =IFERROR(__xludf.DUMMYFUNCTION("""COMPUTED_VALUE"""),0.0) -> 0 | T6: =IFERROR(__xludf.DUMMYFUNCTION("""COMPUTED_VALUE"""),0.0) -> 0 | U6: =IFERROR(__xludf.DUMMYFUNCTION("""COMPUTED_VALUE"""),0.0) -> 0 | V6: =IFERROR(__xludf.DUMMYFUNCTION("""COMPUTED_VALUE"""),0.0) -> 0 | W6: =IFERROR(__xludf.DUMMYFUNCTION("""COMPUTED_VALUE"""),0.0) -> 0 | X6: =IFERROR(__xludf.DUMMYFUNCTION("""COMPUTED_VALUE"""),FALSE) -> FALSE
A7: =IFERROR(__xludf.DUMMYFUNCTION("""COMPUTED_VALUE"""),"Advanced Remarketing Services, Inc.") -> Advanced Remarketing Services, Inc. | B7: =IFERROR(__xludf.DUMMYFUNCTION("""COMPUTED_VALUE"""),"Growth") -> Growth | C7: =IFERROR(__xludf.DUMMYFUNCTION("""COMPUTED_VALUE"""),"NAM") -> NAM | D7: =IFERROR(__xludf.DUMMYFUNCTION("""COMPUTED_VALUE"""),"Rod Gowin") -> Rod Gowin | E7: =IFERROR(__xludf.DUMMYFUNCTION("""COMPUTED_VALUE"""),"United States") -> United States | F7: =IFERROR(__xludf.DUMMYFUNCTION("""COMPUTED_VALUE"""),"ClaimCenter") -> ClaimCenter | G7: =IFERROR(__xludf.DUMMYFUNCTION("""COMPUTED_VALUE"""),43572.0) -> 43572 | H7: =IFERROR(__xludf.DUMMYFUNCTION("""COMPUTED_VALUE"""),44303.0) -> 44303 | I7: =IFERROR(__xludf.DUMMYFUNCTION("""COMPUTED_VALUE"""),43572.0) -> 43572 | K7: =IFERROR(__xludf.DUMMYFUNCTION("""COMPUTED_VALUE"""),43686.0) -> 43686 | L7: =IFERROR(__xludf.DUMMYFUNCTION("""COMPUTED_VALUE"""),"Low") -> Low | M7: =IFERROR(__xludf.DUMMYFUNCTION("""COMPUTED_VALUE"""),"PartnerConnect Technology") -> PartnerConnect Technology | N7: =IFERROR(__xludf.DUMMYFUNCTION("""COMPUTED_VALUE"""),"FY19 - Q3") -> FY19 - Q3 | O7: =IFERROR(__xludf.DUMMYFUNCTION("""COMPUTED_VALUE"""),0.0) -> 0 | P7: =IFERROR(__xludf.DUMMYFUNCTION("""COMPUTED_VALUE"""),0.0) -> 0 | Q7: =IFERROR(__xludf.DUMMYFUNCTION("""COMPUTED_VALUE"""),0.0) -> 0 | R7: =IFERROR(__xludf.DUMMYFUNCTION("""COMPUTED_VALUE"""),0.0) -> 0 | S7: =IFERROR(__xludf.DUMMYFUNCTION("""COMPUTED_VALUE"""),0.0) -> 0 | T7: =IFERROR(__xludf.DUMMYFUNCTION("""COMPUTED_VALUE"""),0.0) -> 0 | U7: =IFERROR(__xludf.DUMMYFUNCTION("""COMPUTED_VALUE"""),0.0) -> 0 | V7: =IFERROR(__xludf.DUMMYFUNCTION("""COMPUTED_VALUE"""),0.0) -> 0 | W7: =IFERROR(__xludf.DUMMYFUNCTION("""COMPUTED_VALUE"""),5.0) -> 5 | X7: =IFERROR(__xludf.DUMMYFUNCTION("""COMPUTED_VALUE"""),FALSE) -> FALSE
A8: =IFERROR(__xludf.DUMMYFUNCTION("""COMPUTED_VALUE"""),"AgentSync") -> AgentSync | B8: =IFERROR(__xludf.DUMMYFUNCTION("""COMPUTED_VALUE"""),"Growth") -> Growth | C8: =IFERROR(__xludf.DUMMYFUNCTION("""COMPUTED_VALUE"""),"NAM") -> NAM | D8: =IFERROR(__xludf.DUMMYFUNCTION("""COMPUTED_VALUE"""),"Shannon Spies") -> Shannon Spies | E8: =IFERROR(__xludf.DUMMYFUNCTION("""COMPUTED_VALUE"""),"United States") -> United States | F8: =IFERROR(__xludf.DUMMYFUNCTION("""COMPUTED_VALUE"""),"PolicyCenter") -> PolicyCenter | G8: =IFERROR(__xludf.DUMMYFUNCTION("""COMPUTED_VALUE"""),45364.0) -> 45364 | H8: =IFERROR(__xludf.DUMMYFUNCTION("""COMPUTED_VALUE"""),46094.0) -> 46094 | I8: =IFERROR(__xludf.DUMMYFUNCTION("""COMPUTED_VALUE"""),45363.0) -> 45363 | K8: =IFERROR(__xludf.DUMMYFUNCTION("""COMPUTED_VALUE"""),45951.0) -> 45951 | L8: =IFERROR(__xludf.DUMMYFUNCTION("""COMPUTED_VALUE"""),"High") -> High | M8: =IFERROR(__xludf.DUMMYFUNCTION("""COMPUTED_VALUE"""),"PartnerConnect Technology") -> PartnerConnect Technology | N8: =IFERROR(__xludf.DUMMYFUNCTION("""COMPUTED_VALUE"""),"FY24 - Q2") -> FY24 - Q2 | O8: =IFERROR(__xludf.DUMMYFUNCTION("""COMPUTED_VALUE"""),1.0) -> 1 | P8: =IFERROR(__xludf.DUMMYFUNCTION("""COMPUTED_VALUE"""),1.0) -> 1 | Q8: =IFERROR(__xludf.DUMMYFUNCTION("""COMPUTED_VALUE"""),6.0) -> 6 | R8: =IFERROR(__xludf.DUMMYFUNCTION("""COMPUTED_VALUE"""),6.0) -> 6 | S8: =IFERROR(__xludf.DUMMYFUNCTION("""COMPUTED_VALUE"""),1804.0) -> 1804 | T8: =IFERROR(__xludf.DUMMYFUNCTION("""COMPUTED_VALUE"""),4.0) -> 4 | U8: =IFERROR(__xludf.DUMMYFUNCTION("""COMPUTED_VALUE"""),6.0) -> 6 | V8: =IFERROR(__xludf.DUMMYFUNCTION("""COMPUTED_VALUE"""),6.0) -> 6 | W8: =IFERROR(__xludf.DUMMYFUNCTION("""COMPUTED_VALUE"""),2.0) -> 2 | X8: =IFERROR(__xludf.DUMMYFUNCTION("""COMPUTED_VALUE"""),TRUE) -> TRUE
A9: =IFERROR(__xludf.DUMMYFUNCTION("""COMPUTED_VALUE"""),"Akur8") -> Akur8 | B9: =IFERROR(__xludf.DUMMYFUNCTION("""COMPUTED_VALUE"""),"Growth") -> Growth | C9: =IFERROR(__xludf.DUMMYFUNCTION("""COMPUTED_VALUE"""),"APAC, EMEA, NAM, LatAm") -> APAC, EMEA, NAM, LatAm | D9: =IFERROR(__xludf.DUMMYFUNCTION("""COMPUTED_VALUE"""),"Tim Kennedy") -> Tim Kennedy | E9: =IFERROR(__xludf.DUMMYFUNCTION("""COMPUTED_VALUE"""),"France") -> France | F9: =IFERROR(__xludf.DUMMYFUNCTION("""COMPUTED_VALUE"""),"PolicyCenter") -> PolicyCenter | G9: =IFERROR(__xludf.DUMMYFUNCTION("""COMPUTED_VALUE"""),44550.0) -> 44550 | H9: =IFERROR(__xludf.DUMMYFUNCTION("""COMPUTED_VALUE"""),45280.0) -> 45280 | I9: =IFERROR(__xludf.DUMMYFUNCTION("""COMPUTED_VALUE"""),44550.0) -> 44550 | K9: =IFERROR(__xludf.DUMMYFUNCTION("""COMPUTED_VALUE"""),45218.0) -> 45218 | L9: =IFERROR(__xludf.DUMMYFUNCTION("""COMPUTED_VALUE"""),"Medium") -> Medium | M9: =IFERROR(__xludf.DUMMYFUNCTION("""COMPUTED_VALUE"""),"PartnerConnect Technology") -> PartnerConnect Technology | N9: =IFERROR(__xludf.DUMMYFUNCTION("""COMPUTED_VALUE"""),"FY21 - Q2") -> FY21 - Q2 | O9: =IFERROR(__xludf.DUMMYFUNCTION("""COMPUTED_VALUE"""),2.0) -> 2 | P9: =IFERROR(__xludf.DUMMYFUNCTION("""COMPUTED_VALUE"""),2.0) -> 2 | Q9: =IFERROR(__xludf.DUMMYFUNCTION("""COMPUTED_VALUE"""),10.0) -> 10 | R9: =IFERROR(__xludf.DUMMYFUNCTION("""COMPUTED_VALUE"""),8.0) -> 8 | S9: =IFERROR(__xludf.DUMMYFUNCTION("""COMPUTED_VALUE"""),37143.0) -> 37143 | T9: =IFERROR(__xludf.DUMMYFUNCTION("""COMPUTED_VALUE"""),8.0) -> 8 | U9: =IFERROR(__xludf.DUMMYFUNCTION("""COMPUTED_VALUE"""),2.0) -> 2 | V9: =IFERROR(__xludf.DUMMYFUNCTION("""COMPUTED_VALUE"""),2.0) -> 2 | W9: =IFERROR(__xludf.DUMMYFUNCTION("""COMPUTED_VALUE"""),0.0) -> 0 | X9: =IFERROR(__xludf.DUMMYFUNCTION("""COMPUTED_VALUE"""),FALSE) -> FALSE
A10: =IFERROR(__xludf.DUMMYFUNCTION("""COMPUTED_VALUE"""),"Alacrity Solutions Group") -> Alacrity Solutions Group | B10: =IFERROR(__xludf.DUMMYFUNCTION("""COMPUTED_VALUE"""),"Growth") -> Growth | C10: =IFERROR(__xludf.DUMMYFUNCTION("""COMPUTED_VALUE"""),"NAM") -> NAM | D10: =IFERROR(__xludf.DUMMYFUNCTION("""COMPUTED_VALUE"""),"Rod Gowin") -> Rod Gowin | E10: =IFERROR(__xludf.DUMMYFUNCTION("""COMPUTED_VALUE"""),"United States") -> United States | F10: =IFERROR(__xludf.DUMMYFUNCTION("""COMPUTED_VALUE"""),"ClaimCenter") -> ClaimCenter | G10: =IFERROR(__xludf.DUMMYFUNCTION("""COMPUTED_VALUE"""),44433.0) -> 44433 | H10: =IFERROR(__xludf.DUMMYFUNCTION("""COMPUTED_VALUE"""),45162.0) -> 45162 | I10: =IFERROR(__xludf.DUMMYFUNCTION("""COMPUTED_VALUE"""),44433.0) -> 44433 | L10: =IFERROR(__xludf.DUMMYFUNCTION("""COMPUTED_VALUE"""),"Low") -> Low | M10: =IFERROR(__xludf.DUMMYFUNCTION("""COMPUTED_VALUE"""),"PartnerConnect Technology") -> PartnerConnect Technology | N10: =IFERROR(__xludf.DUMMYFUNCTION("""COMPUTED_VALUE"""),"FY21 - Q1") -> FY21 - Q1 | O10: =IFERROR(__xludf.DUMMYFUNCTION("""COMPUTED_VALUE"""),0.0) -> 0 | P10: =IFERROR(__xludf.DUMMYFUNCTION("""COMPUTED_VALUE"""),0.0) -> 0 | Q10: =IFERROR(__xludf.DUMMYFUNCTION("""COMPUTED_VALUE"""),0.0) -> 0 | R10: =IFERROR(__xludf.DUMMYFUNCTION("""COMPUTED_VALUE"""),0.0) -> 0 | S10: =IFERROR(__xludf.DUMMYFUNCTION("""COMPUTED_VALUE"""),0.0) -> 0 | T10: =IFERROR(__xludf.DUMMYFUNCTION("""COMPUTED_VALUE"""),0.0) -> 0 | U10: =IFERROR(__xludf.DUMMYFUNCTION("""COMPUTED_VALUE"""),0.0) -> 0 | V10: =IFERROR(__xludf.DUMMYFUNCTION("""COMPUTED_VALUE"""),0.0) -> 0 | W10: =IFERROR(__xludf.DUMMYFUNCTION("""COMPUTED_VALUE"""),0.0) -> 0 | X10: =IFERROR(__xludf.DUMMYFUNCTION("""COMPUTED_VALUE"""),FALSE) -> FALSE
A11: =IFERROR(__xludf.DUMMYFUNCTION("""COMPUTED_VALUE"""),"ALE Solutions") -> ALE Solutions | B11: =IFERROR(__xludf.DUMMYFUNCTION("""COMPUTED_VALUE"""),"Growth") -> Growth | C11: =IFERROR(__xludf.DUMMYFUNCTION("""COMPUTED_VALUE"""),"NAM") -> NAM | D11: =IFERROR(__xludf.DUMMYFUNCTION("""COMPUTED_VALUE"""),"Aaron Shaw") -> Aaron Shaw | E11: =IFERROR(__xludf.DUMMYFUNCTION("""COMPUTED_VALUE"""),"United States") -> United States | F11: =IFERROR(__xludf.DUMMYFUNCTION("""COMPUTED_VALUE"""),"ClaimCenter") -> ClaimCenter | G11: =IFERROR(__xludf.DUMMYFUNCTION("""COMPUTED_VALUE"""),44725.0) -> 44725 | H11: =IFERROR(__xludf.DUMMYFUNCTION("""COMPUTED_VALUE"""),45455.0) -> 45455 | I11: =IFERROR(__xludf.DUMMYFUNCTION("""COMPUTED_VALUE"""),44725.0) -> 44725 | K11: =IFERROR(__xludf.DUMMYFUNCTION("""COMPUTED_VALUE"""),45016.0) -> 45016 | L11: =IFERROR(__xludf.DUMMYFUNCTION("""COMPUTED_VALUE"""),"Low") -> Low | M11: =IFERROR(__xludf.DUMMYFUNCTION("""COMPUTED_VALUE"""),"PartnerConnect Technology") -> PartnerConnect Technology | N11: =IFERROR(__xludf.DUMMYFUNCTION("""COMPUTED_VALUE"""),"FY22 - Q3") -> FY22 - Q3 | O11: =IFERROR(__xludf.DUMMYFUNCTION("""COMPUTED_VALUE"""),1.0) -> 1 | P11: =IFERROR(__xludf.DUMMYFUNCTION("""COMPUTED_VALUE"""),1.0) -> 1 | Q11: =IFERROR(__xludf.DUMMYFUNCTION("""COMPUTED_VALUE"""),10.0) -> 10 | R11: =IFERROR(__xludf.DUMMYFUNCTION("""COMPUTED_VALUE"""),3.0) -> 3 | S11: =IFERROR(__xludf.DUMMYFUNCTION("""COMPUTED_VALUE"""),226.0) -> 226 | T11: =IFERROR(__xludf.DUMMYFUNCTION("""COMPUTED_VALUE"""),3.0) -> 3 | U11: =IFERROR(__xludf.DUMMYFUNCTION("""COMPUTED_VALUE"""),0.0) -> 0 | V11: =IFERROR(__xludf.DUMMYFUNCTION("""COMPUTED_VALUE"""),0.0) -> 0 | W11: =IFERROR(__xludf.DUMMYFUNCTION("""COMPUTED_VALUE"""),0.0) -> 0 | X11: =IFERROR(__xludf.DUMMYFUNCTION("""COMPUTED_VALUE"""),TRUE) -> TRUE
A12: =IFERROR(__xludf.DUMMYFUNCTION("""COMPUTED_VALUE"""),"Amazon Web Services, Inc") -> Amazon Web Services, Inc | B12: =IFERROR(__xludf.DUMMYFUNCTION("""COMPUTED_VALUE"""),"Advantage") -> Advantage | C12: =IFERROR(__xludf.DUMMYFUNCTION("""COMPUTED_VALUE"""),"APAC, EMEA, NAM, LatAm") -> APAC, EMEA, NAM, LatAm | D12: =IFERROR(__xludf.DUMMYFUNCTION("""COMPUTED_VALUE"""),"Paul Harper") -> Paul Harper | F12: =IFERROR(__xludf.DUMMYFUNCTION("""COMPUTED_VALUE"""),"Cloud Data Access (CDA)") -> Cloud Data Access (CDA) | G12: =IFERROR(__xludf.DUMMYFUNCTION("""COMPUTED_VALUE"""),43334.0) -> 43334 | I12: =IFERROR(__xludf.DUMMYFUNCTION("""COMPUTED_VALUE"""),45293.0) -> 45293 | K12: =IFERROR(__xludf.DUMMYFUNCTION("""COMPUTED_VALUE"""),45450.0) -> 45450 | L12: =IFERROR(__xludf.DUMMYFUNCTION("""COMPUTED_VALUE"""),"High") -> High | M12: =IFERROR(__xludf.DUMMYFUNCTION("""COMPUTED_VALUE"""),"PartnerConnect Technology") -> PartnerConnect Technology | N12: =IFERROR(__xludf.DUMMYFUNCTION("""COMPUTED_VALUE"""),"FY18 - Q1") -> FY18 - Q1 | O12: =IFERROR(__xludf.DUMMYFUNCTION("""COMPUTED_VALUE"""),0.0) -> 0 | P12: =IFERROR(__xludf.DUMMYFUNCTION("""COMPUTED_VALUE"""),0.0) -> 0 | Q12: =IFERROR(__xludf.DUMMYFUNCTION("""COMPUTED_VALUE"""),0.0) -> 0 | R12: =IFERROR(__xludf.DUMMYFUNCTION("""COMPUTED_VALUE"""),0.0) -> 0 | S12: =IFERROR(__xludf.DUMMYFUNCTION("""COMPUTED_VALUE"""),0.0) -> 0 | T12: =IFERROR(__xludf.DUMMYFUNCTION("""COMPUTED_VALUE"""),0.0) -> 0 | U12: =IFERROR(__xludf.DUMMYFUNCTION("""COMPUTED_VALUE"""),0.0) -> 0 | V12: =IFERROR(__xludf.DUMMYFUNCTION("""COMPUTED_VALUE"""),0.0) -> 0 | W12: =IFERROR(__xludf.DUMMYFUNCTION("""COMPUTED_VALUE"""),0.0) -> 0 | X12: =IFERROR(__xludf.DUMMYFUNCTION("""COMPUTED_VALUE"""),FALSE) -> FALSE
A13: =IFERROR(__xludf.DUMMYFUNCTION("""COMPUTED_VALUE"""),"American Association of Insurance Services (AAIS)") -> American Association of Insurance Services (AAIS) | B13: =IFERROR(__xludf.DUMMYFUNCTION("""COMPUTED_VALUE"""),"Growth") -> Growth | C13: =IFERROR(__xludf.DUMMYFUNCTION("""COMPUTED_VALUE"""),"NAM") -> NAM | D13: =IFERROR(__xludf.DUMMYFUNCTION("""COMPUTED_VALUE"""),"Eric Apse") -> Eric Apse | E13: =IFERROR(__xludf.DUMMYFUNCTION("""COMPUTED_VALUE"""),"United States") -> United States | G13: =IFERROR(__xludf.DUMMYFUNCTION("""COMPUTED_VALUE"""),45261.0) -> 45261 | H13: =IFERROR(__xludf.DUMMYFUNCTION("""COMPUTED_VALUE"""),45626.0) -> 45626 | L13: =IFERROR(__xludf.DUMMYFUNCTION("""COMPUTED_VALUE"""),"High") -> High | M13: =IFERROR(__xludf.DUMMYFUNCTION("""COMPUTED_VALUE"""),"PartnerConnect Technology") -> PartnerConnect Technology | N13: =IFERROR(__xludf.DUMMYFUNCTION("""COMPUTED_VALUE"""),"FY23 - Q2") -> FY23 - Q2 | O13: =IFERROR(__xludf.DUMMYFUNCTION("""COMPUTED_VALUE"""),0.0) -> 0 | P13: =IFERROR(__xludf.DUMMYFUNCTION("""COMPUTED_VALUE"""),0.0) -> 0 | Q13: =IFERROR(__xludf.DUMMYFUNCTION("""COMPUTED_VALUE"""),0.0) -> 0 | R13: =IFERROR(__xludf.DUMMYFUNCTION("""COMPUTED_VALUE"""),0.0) -> 0 | S13: =IFERROR(__xludf.DUMMYFUNCTION("""COMPUTED_VALUE"""),0.0) -> 0 | T13: =IFERROR(__xludf.DUMMYFUNCTION("""COMPUTED_VALUE"""),0.0) -> 0 | U13: =IFERROR(__xludf.DUMMYFUNCTION("""COMPUTED_VALUE"""),0.0) -> 0 | V13: =IFERROR(__xludf.DUMMYFUNCTION("""COMPUTED_VALUE"""),0.0) -> 0 | W13: =IFERROR(__xludf.DUMMYFUNCTION("""COMPUTED_VALUE"""),51.0) -> 51 | X13: =IFERROR(__xludf.DUMMYFUNCTION("""COMPUTED_VALUE"""),FALSE) -> FALSE
A14: =IFERROR(__xludf.DUMMYFUNCTION("""COMPUTED_VALUE"""),"Appian") -> Appian | B14: =IFERROR(__xludf.DUMMYFUNCTION("""COMPUTED_VALUE"""),"Growth") -> Growth | C14: =IFERROR(__xludf.DUMMYFUNCTION("""COMPUTED_VALUE"""),"APAC, EMEA, NAM, LatAm") -> APAC, EMEA, NAM, LatAm | D14: =IFERROR(__xludf.DUMMYFUNCTION("""COMPUTED_VALUE"""),"Fatima Aoulagha-Bannou") -> Fatima Aoulagha-Bannou | E14: =IFERROR(__xludf.DUMMYFUNCTION("""COMPUTED_VALUE"""),"United States") -> United States | F14: =IFERROR(__xludf.DUMMYFUNCTION("""COMPUTED_VALUE"""),"ClaimCenter, PolicyCenter, BillingCenter") -> ClaimCenter, PolicyCenter, BillingCenter | G14: =IFERROR(__xludf.DUMMYFUNCTION("""COMPUTED_VALUE"""),44771.0) -> 44771 | H14: =IFERROR(__xludf.DUMMYFUNCTION("""COMPUTED_VALUE"""),45501.0) -> 45501 | I14: =IFERROR(__xludf.DUMMYFUNCTION("""COMPUTED_VALUE"""),44972.0) -> 44972 | K14: =IFERROR(__xludf.DUMMYFUNCTION("""COMPUTED_VALUE"""),45223.0) -> 45223 | L14: =IFERROR(__xludf.DUMMYFUNCTION("""COMPUTED_VALUE"""),"Medium") -> Medium | M14: =IFERROR(__xludf.DUMMYFUNCTION("""COMPUTED_VALUE"""),"PartnerConnect Technology") -> PartnerConnect Technology | N14: =IFERROR(__xludf.DUMMYFUNCTION("""COMPUTED_VALUE"""),"FY22 - Q4") -> FY22 - Q4 | O14: =IFERROR(__xludf.DUMMYFUNCTION("""COMPUTED_VALUE"""),2.0) -> 2 | P14: =IFERROR(__xludf.DUMMYFUNCTION("""COMPUTED_VALUE"""),2.0) -> 2 | Q14: =IFERROR(__xludf.DUMMYFUNCTION("""COMPUTED_VALUE"""),87.0) -> 87 | R14: =IFERROR(__xludf.DUMMYFUNCTION("""COMPUTED_VALUE"""),51.0) -> 51 | S14: =IFERROR(__xludf.DUMMYFUNCTION("""COMPUTED_VALUE"""),39976.0) -> 39976 | T14: =IFERROR(__xludf.DUMMYFUNCTION("""COMPUTED_VALUE"""),16.0) -> 16 | U14: =IFERROR(__xludf.DUMMYFUNCTION("""COMPUTED_VALUE"""),51.0) -> 51 | V14: =IFERROR(__xludf.DUMMYFUNCTION("""COMPUTED_VALUE"""),51.0) -> 51 | W14: =IFERROR(__xludf.DUMMYFUNCTION("""COMPUTED_VALUE"""),76.0) -> 76 | X14: =IFERROR(__xludf.DUMMYFUNCTION("""COMPUTED_VALUE"""),FALSE) -> FALSE
A15: =IFERROR(__xludf.DUMMYFUNCTION("""COMPUTED_VALUE"""),"Applied Systems Inc") -> Applied Systems Inc | B15: =IFERROR(__xludf.DUMMYFUNCTION("""COMPUTED_VALUE"""),"Growth") -> Growth | C15: =IFERROR(__xludf.DUMMYFUNCTION("""COMPUTED_VALUE"""),"NAM") -> NAM | D15: =IFERROR(__xludf.DUMMYFUNCTION("""COMPUTED_VALUE"""),"Rod Gowin") -> Rod Gowin | E15: =IFERROR(__xludf.DUMMYFUNCTION("""COMPUTED_VALUE"""),"United States") -> United States | F15: =IFERROR(__xludf.DUMMYFUNCTION("""COMPUTED_VALUE"""),"ClaimCenter, PolicyCenter, BillingCenter, InsuranceNow") -> ClaimCenter, PolicyCenter, BillingCenter, InsuranceNow | G15: =IFERROR(__xludf.DUMMYFUNCTION("""COMPUTED_VALUE"""),42152.0) -> 42152 | I15: =IFERROR(__xludf.DUMMYFUNCTION("""COMPUTED_VALUE"""),42152.0) -> 42152 | K15: =IFERROR(__xludf.DUMMYFUNCTION("""COMPUTED_VALUE"""),42292.0) -> 42292 | L15: =IFERROR(__xludf.DUMMYFUNCTION("""COMPUTED_VALUE"""),"High") -> High | M15: =IFERROR(__xludf.DUMMYFUNCTION("""COMPUTED_VALUE"""),"PartnerConnect Technology") -> PartnerConnect Technology | N15: =IFERROR(__xludf.DUMMYFUNCTION("""COMPUTED_VALUE"""),"FY15 - Q3") -> FY15 - Q3 | O15: =IFERROR(__xludf.DUMMYFUNCTION("""COMPUTED_VALUE"""),4.0) -> 4 | P15: =IFERROR(__xludf.DUMMYFUNCTION("""COMPUTED_VALUE"""),4.0) -> 4 | Q15: =IFERROR(__xludf.DUMMYFUNCTION("""COMPUTED_VALUE"""),95.0) -> 95 | R15: =IFERROR(__xludf.DUMMYFUNCTION("""COMPUTED_VALUE"""),79.0) -> 79 | S15: =IFERROR(__xludf.DUMMYFUNCTION("""COMPUTED_VALUE"""),59454.0) -> 59454 | T15: =IFERROR(__xludf.DUMMYFUNCTION("""COMPUTED_VALUE"""),38.0) -> 38 | U15: =IFERROR(__xludf.DUMMYFUNCTION("""COMPUTED_VALUE"""),79.0) -> 79 | V15: =IFERROR(__xludf.DUMMYFUNCTION("""COMPUTED_VALUE"""),79.0) -> 79 | W15: =IFERROR(__xludf.DUMMYFUNCTION("""COMPUTED_VALUE"""),2.0) -> 2 | X15: =IFERROR(__xludf.DUMMYFUNCTION("""COMPUTED_VALUE"""),FALSE) -> FALSE
